Workbook
Name Xперемен: [1]Интервалы!$B$53:$B$113
Name Yперемен: [1]Интервалы!$C$53:$C$113

Sheet Вводные
B2: Цели 2025–2029, тыс. руб.
C3: А | K3: Б | S3: В | AA3: Г
D4: 2025 факт | E4: 2026 | F4: 2027 | G4: 2028 | H4: 2029 | I4: 2030 | L4: 2025 факт | M4: 2026 | N4: 2027 | O4: 2028 | P4: 2029 | Q4: 2030 | T4: 2025 факт | U4: 2026 | V4: 2027 | W4: 2028 | X4: 2029 | Y4: 2030 | AB4: 2025 факт | AC4: 2026 | AD4: 2027 | AE4: 2028 | AF4: 2029 | AG4: 2030
B5: Выручка | C5: 2030 х2 к 2025 | D5: 51502 | E5: 59031.592 | F5: 67732.849 | G5: 77797.95 | H5: 89452.083 | I5: =D5*2 -> 103004 | K5: 2030 х2 к 2025 | L5: 43215.028 | M5: 49498.493 | N5: 56824.27 | O5: 65274.039 | P5: 75065.145 | Q5: =L5*2 -> 86430.056 | S5: 2030 х3.5 к 2025 | T5: 24565 | U5: 30829.075 | V5: 38998.78 | W5: 49918.438 | X5: 64644.378 | Y5: =T5*3.5 -> 85977.5 | AA5: 2030 х2 к 2025 | AB5: 7911.8422 | AC5: 8995.7646 | AD5: 10282.159 | AE5: 11803.918 | AF5: 13633.526 | AG5: =AB5*2 -> 15823.684 | AI5: =D5+L5+T5+AB5 -> 127193.87
B6: Прирост год к году, % | D6: 0.145 | E6: =E5/D5-1 -> 0.1462 | F6: =F5/E5-1 -> 0.1474 | G6: =G5/F5-1 -> 0.1486 | H6: =H5/G5-1 -> 0.1498 | I6: =I5/H5-1 -> 0.15149917 | L6: 0.144 | M6: 0.1454 | N6: 0.148 | O6: 0.1487 | P6: 0.15 | Q6: =Q5/P5-1 -> 0.15140064 | T6: 0.25 | U6: 0.255 | V6: 0.265 | W6: 0.28 | X6: 0.295 | Y6: =Y5/X5-1 -> 0.33000739 | AB6: 0.133 | AC6: 0.137 | AD6: 0.143 | AE6: 0.148 | AF6: 0.155 | AG6: =AG5/AF5-1 -> 0.16064506
B7: Чистая прибыль | D7: =D68 -> 14154.75 | E7: 18299.794 | F7: 22487.306 | G7: 27540.474 | H7: 33633.983 | I7: =I8*I5 -> 41201.6 | L7: =L68 -> 7103.256 | M7: 9652.2061 | N7: 12842.285 | O7: 17232.346 | P7: 21018.24 | Q7: =Q8*Q5 -> 25929.017 | T7: =T68 -> 627 | U7: 2343.0097 | V7: 5966.8133 | W7: 13877.326 | X7: 21009.423 | Y7: =Y8*Y5 -> 34391 | AB7: =AB68 -> 1161.98 | AC7: 1664.2165 | AD7: 2364.8966 | AE7: 3246.0776 | AF7: 4158.2254 | AG7: =AG8*AG5 -> 5538.2896
B8: Чистая прибыль, % | C8: 2030 не < 40% | D8: =D7/D5 -> 0.27483884 | E8: 0.31 | F8: 0.332 | G8: 0.354 | H8: 0.376 | I8: 0.4 | K8: 2030 не < 30% | L8: =L7/L5 -> 0.16437004 | M8: 0.195 | N8: 0.226 | O8: 0.264 | P8: 0.28 | Q8: 0.3 | S8: 2030 не < 40% | T8: =T7/T5 -> 0.02552412 | U8: 0.076 | V8: 0.153 | W8: 0.278 | X8: 0.325 | Y8: 0.4 | AA8: 2030 не < 35% | AB8: =AB7/AB5 -> 0.14686592 | AC8: 0.185 | AD8: 0.23 | AE8: 0.275 | AF8: 0.305 | AG8: 0.35
B10: Информация по компании А от смежных подразделений
D11: 2025 факт | E11: 2026 | F11: 2027 | G11: 2028 | H11: 2029 | I11: 2030
B12: Инфляция, % | D12: 0.055 | E12: 0.05 | F12: 0.05 | G12: 0.05 | H12: 0.05 | I12: 0.05
B13: Индексация ЗП, % | D13: 0.065 | E13: 0.06 | F13: 0.06 | G13: 0.06 | H13: 0.06 | I13: 0.06
B14: Доп. персонал в отдел разработки, штат. ед. | D14: - | E14: 1 | F14: 1 | G14: 1 | H14: 1 | I14: 1
B15: Средняя заработная плата потенциального персонала, руб. | D15: - | E15: 100000 | F15: 100000 | G15: 100000 | H15: 100000 | I15: 100000
B16: Соц. налоги на человека, % | D16: - | E16: 0.3 | F16: 0.3 | G16: 0.3 | H16: 0.3 | I16: 0.3
B17: Количество платежей и переводов, всего | D17: 27210.141 | E17: 31342.454 | F17: 36102.411 | G17: 41585.355 | H17: 47901.115 | I17: 55176.204
B18: Стоимость привлечения платежа/перевода, руб. | D18: - | E18: 136.5 | F18: 126 | G18: 115.5 | H18: 105 | I18: 94.5
B19: Количество активных (платящих) пользователей, чел. | D19: 75718.78
B21: Реестр внутригрупповых операций*, тыс. руб.
C22: 2025 план | D22: 2025 факт | E22: 2026 | F22: 2027 | G22: 2028 | H22: 2029 | I22: 2030
B23: Компания А оказывает услуги платёжного сервиса компании Б | C23: 110 | D23: 110 | E23: 115.5 | F23: 121 | G23: 126.5 | H23: 132 | I23: 137.5
B24: Компания А приобретает аутсорсинговые услуги для осуществления текущей деятельности сервиса платежей и переводов у компании Б | C24: 1100 | D24: 1100 | E24: 1210 | F24: 1320 | G24: 1430 | H24: 1540 | I24: 1650
B25: Компания Б оказывает аутсорсинговые услуги компании В | C25: 77 | D25: 77 | E25: 88 | F25: 99 | G25: 110 | H25: 121 | I25: 132
B26: Компания В приобретает услуги платёжного сервиса у компании А | C26: 22 | D26: 22 | E26: 23.1 | F26: 24.255 | G26: 25.46775 | H26: 26.741138 | I26: 28.078194
B27: Компания В приобретает программное обеспечение для осуществления текущей деятельности трейдинговой платформы у компании Б | C27: 1210 | D27: 1210 | E27: 1320 | F27: 1320 | G27: 1320 | H27: 1320 | I27: 1320
B28: Компания Г приобретает услуги платёжного сервиса у компании А | C28: 2.2 | D28: 2.2 | E28: 3.3 | F28: 3.3 | G28: 3.3 | H28: 3.3 | I28: 3.3
B29: Компания Г приобретает аутсорсинговые услуги у компании Б | C29: 1.1 | D29: 1.1 | E29: 2.2 | F29: 2.2 | G29: 2.2 | H29: 2.2 | I29: 2.2
B30: Компания Г получила штраф за нарушение договорных обязательств от компании Б | C30: 0 | D30: 10 | E30: 0 | F30: 0 | G30: 0 | H30: 0 | I30: 0
B31: Компания А в прошлом периоде предоставила беспроцентный заём компании В
B32: платёж в части основного долга | C32: 600 | D32: 600 | E32: 600 | F32: 0 | G32: 0 | H32: 0 | I32: 0
B33: остаток долга на 31.12.2025 | C33: 600 | D33: 600 | E33: 0 | F33: 0 | G33: 0 | H33: 0 | I33: 0
B35: *При взаиморасчётах между участниками группы по их основным видам деятельности, исполнение обязательств всеми сторонами-участниками происходит одновременно
B37: Отчётность участников Группы Stand alone
B39: Отчёт о прибылях и убытках, тыс. руб.
C40: А | K40: Б | S40: В | AA40: Г
C41: 2025 план | D41: 2025 факт | E41: 2026 | F41: 2027 | G41: 2028 | H41: 2029 | I41: 2030 | K41: 2025 план | L41: 2025 факт | M41: 2026 | N41: 2027 | O41: 2028 | P41: 2029 | Q41: 2030 | S41: 2025 план | T41: 2025 факт | U41: 2026 | V41: 2027 | W41: 2028 | X41: 2029 | Y41: 2030 | AA41: 2025 план | AB41: 2025 факт | AC41: 2026 | AD41: 2027 | AE41: 2028 | AF41: 2029 | AG41: 2030
B42: Выручка от реализации | C42: =SUM(C43:C47) -> 51450 | D42: =SUM(D43:D47) -> 51502 | E42: =($D$42/$D$17)*E17 -> 59323.437 | F42: =($D$42/$D$17)*F17 -> 68332.847 | G42: =($D$42/$D$17)*G17 -> 78710.69 | H42: =($D$42/$D$17)*H17 -> 90664.845 | I42: =($D$42/$D$17)*I17 -> 104434.77 | K42: =SUM(K43:K47) -> 42500 | L42: =SUM(L43:L47) -> 43215.028 | M42: =SUM(M43:M47) -> 51144.985 | N42: =SUM(N43:N47) -> 60531.073 | O42: =SUM(O43:O47) -> 71640.855 | P42: =SUM(P43:P47) -> 84791.094 | Q42: =SUM(Q43:Q47) -> 100356.8 | S42: =SUM(S43:S47) -> 23700 | T42: =SUM(T43:T47) -> 24565 | U42: =SUM(U43:U47) -> 29797.345 | V42: =SUM(V43:V47) -> 37246.681 | W42: =SUM(W43:W47) -> 47675.752 | X42: =SUM(X43:X47) -> 63408.75 | Y42: =SUM(Y43:Y47) -> 85601.813 | AA42: =SUM(AA43:AA47) -> 8500 | AB42: =SUM(AB43:AB47) -> 7911.8422 | AC42: =SUM(AC43:AC47) -> 8873.1311 | AD42: =SUM(AD43:AD47) -> 9951.2165 | AE42: =SUM(AE43:AE47) -> 11160.289 | AF42: =SUM(AF43:AF47) -> 12516.264 | AG42: =SUM(AG43:AG47) -> 14036.991
B43: Комиссии за обработку платежей и переводов | C43: 51450 | D43: 51502 | E43: =E42 -> 59323.437 | F43: =F42 -> 68332.847 | G43: =G42 -> 78710.69 | H43: =H42 -> 90664.845 | I43: =I42 -> 104434.77 | K43: 0 | L43: 0 | M43: 0 | N43: 0 | O43: 0 | P43: 0 | Q43: 0 | S43: 0 | T43: 0 | U43: 0 | V43: 0 | W43: 0 | X43: 0 | Y43: 0 | AA43: 0 | AB43: 0 | AC43: 0 | AD43: 0 | AE43: 0 | AF43: 0 | AG43: 0
B44: Разработка программного обеспечения | C44: 0 | D44: 0 | K44: 27500 | L44: 28089.768 | M44: 33145.926 | N44: 39112.193 | O44: 46152.388 | P44: 54459.818 | Q44: 64262.585 | S44: 0 | T44: 0 | U44: 0 | V44: 0 | W44: 0 | X44: 0 | Y44: 0 | AA44: 0 | AB44: 0 | AC44: 0 | AD44: 0 | AE44: 0 | AF44: 0 | AG44: 0
B45: Аутсорсинговые услуги | C45: 0 | D45: 0 | K45: 15000 | L45: 15125.26 | M45: 17999.059 | N45: 21418.88 | O45: 25488.468 | P45: 30331.276 | Q45: 36094.219 | S45: 0 | T45: 0 | U45: 0 | V45: 0 | W45: 0 | X45: 0 | Y45: 0 | AA45: 0 | AB45: 0 | AC45: 0 | AD45: 0 | AE45: 0 | AF45: 0 | AG45: 0
B46: Комиссии трейдинговой площадки | C46: 0 | D46: 0 | K46: 0 | L46: 0 | M46: 0 | N46: 0 | O46: 0 | P46: 0 | Q46: 0 | S46: 23700 | T46: 24565 | U46: 29797.345 | V46: 37246.681 | W46: 47675.752 | X46: 63408.75 | Y46: 85601.813 | AA46: 0 | AB46: 0 | AC46: 0 | AD46: 0 | AE46: 0 | AF46: 0 | AG46: 0
B47: Комиссии за услуги бронирования | C47: 0 | D47: 0 | K47: 0 | L47: 0 | M47: 0 | N47: 0 | O47: 0 | P47: 0 | Q47: 0 | S47: 0 | T47: 0 | U47: 0 | V47: 0 | W47: 0 | X47: 0 | Y47: 0 | AA47: 8500 | AB47: 7911.8422 | AC47: 8873.1311 | AD47: 9951.2165 | AE47: 11160.289 | AF47: 12516.264 | AG47: 14036.991
B48: Себестоимость реализации: | C48: =SUM(C49:C51) -> 17350 | D48: =SUM(D49:D51) -> 17365 | E48: =SUM(E49:E51) -> 19930.159 | F48: =SUM(F49:F51) -> 22647.391 | G48: =SUM(G49:G51) -> 25525.727 | H48: =SUM(H49:H51) -> 28574.739 | I48: =SUM(I49:I51) -> 31804.564 | K48: =SUM(K49:K51) -> 20300 | L48: =SUM(L49:L51) -> 20311.063 | M48: =SUM(M49:M51) -> 23322.149 | N48: =SUM(N49:N51) -> 26794.159 | O48: =SUM(O49:O51) -> 30798.762 | P48: =SUM(P49:P51) -> 35418.879 | Q48: =SUM(Q49:Q51) -> 40750.465 | S48: =SUM(S49:S51) -> 14950 | T48: =SUM(T49:T51) -> 15384 | U48: =SUM(U49:U51) -> 16634.6 | V48: =SUM(V49:V51) -> 18042.126 | W48: =SUM(W49:W51) -> 19636.466 | X48: =SUM(X49:X51) -> 21454.42 | Y48: =SUM(Y49:Y51) -> 23541.392 | AA48: =SUM(AA49:AA51) -> 2350 | AB48: =SUM(AB49:AB51) -> 2421.0911 | AC48: =SUM(AC49:AC51) -> 2569.643 | AD48: =SUM(AD49:AD51) -> 2729.6538 | AE48: =SUM(AE49:AE51) -> 2902.213 | AF48: =SUM(AF49:AF51) -> 3088.5279 | AG48: =SUM(AG49:AG51) -> 3289.9373
B49: Прямые расходы на персонал | C49: 13710 | D49: 13690.913 | E49: =($D$49*1.06)+($E$15*12)*1.3/1000 -> 16072.368 | F49: =(E49*1.06)+(F15*12)*1.3/1000 -> 18596.71 | G49: =(F49*1.06)+(G15*12)*1.3/1000 -> 21272.513 | H49: =(G49*1.06)+(H15*12)*1.3/1000 -> 24108.864 | I49: =(H49*1.06)+(I15*12)*1.3/1000 -> 27115.395 | K49: 16000 | L49: 16013.648 | M49: 18415.696 | N49: 21178.05 | O49: 24354.757 | P49: 28007.971 | Q49: 32209.167 | S49: 13350 | T49: 13540 | U49: 14352.4 | V49: 15213.544 | W49: 16126.357 | X49: 17093.938 | Y49: 18119.574 | AA49: 1800 | AB49: 1834.98 | AC49: 1917.5541 | AD49: 2003.844 | AE49: 2094.017 | AF49: 2188.2478 | AG49: 2286.7189
B50: Оборудование, лицензии и программное обеспечение | C50: 3450 | D50: 3484.7242 | E50: =D50*1.05 -> 3658.9604 | F50: =E50*1.05 -> 3841.9085 | G50: =F50*1.05 -> 4034.0039 | H50: =G50*1.05 -> 4235.7041 | I50: =H50*1.05 -> 4447.4893 | K50: 2900 | L50: 2979.0654 | M50: 3515.595 | N50: 4148.7537 | O50: 4895.9443 | P50: 5777.7038 | Q50: 6818.2683 | S50: 1500 | T50: 1724 | U50: 2155 | V50: 2693.75 | W50: 3367.1875 | X50: 4208.9844 | Y50: 5261.2305 | AA50: 500 | AB50: 531.66667 | AC50: 595.46667 | AD50: 666.92267 | AE50: 746.95339 | AF50: 836.58779 | AG50: 936.97833
B51: Прочие расходы | C51: 190 | D51: 189.36247 | E51: =D51*1.05 -> 198.83059 | F51: =E51*1.05 -> 208.77212 | G51: =F51*1.05 -> 219.21073 | H51: =G51*1.05 -> 230.17127 | I51: =H51*1.05 -> 241.67983 | K51: 1400 | L51: 1318.3494 | M51: 1390.8586 | N51: 1467.3558 | O51: 1548.0604 | P51: 1633.2037 | Q51: 1723.0299 | S51: 100 | T51: 120 | U51: 127.2 | V51: 134.832 | W51: 142.92192 | X51: 151.49724 | Y51: 160.58707 | AA51: 50 | AB51: 54.444444 | AC51: 56.622222 | AD51: 58.887111 | AE51: 61.242596 | AF51: 63.692299 | AG51: 66.239991
B52: Валовая прибыль | C52: =C42-C48 -> 34100 | D52: =D42-D48 -> 34137 | E52: =E42-E48 -> 39393.278 | F52: =F42-F48 -> 45685.456 | G52: =G42-G48 -> 53184.963 | H52: =H42-H48 -> 62090.106 | I52: =I42-I48 -> 72630.208 | K52: =K42-K48 -> 22200 | L52: =L42-L48 -> 22903.965 | M52: =M42-M48 -> 27822.836 | N52: =N42-N48 -> 33736.914 | O52: =O42-O48 -> 40842.093 | P52: =P42-P48 -> 49372.216 | Q52: =Q42-Q48 -> 59606.339 | S52: =S42-S48 -> 8750 | T52: =T42-T48 -> 9181 | U52: =U42-U48 -> 13162.745 | V52: =V42-V48 -> 19204.555 | W52: =W42-W48 -> 28039.286 | X52: =X42-X48 -> 41954.331 | Y52: =Y42-Y48 -> 62060.421 | AA52: =AA42-AA48 -> 6150 | AB52: =AB42-AB48 -> 5490.7511 | AC52: =AC42-AC48 -> 6303.4881 | AD52: =AD42-AD48 -> 7221.5627 | AE52: =AE42-AE48 -> 8258.0763 | AF52: =AF42-AF48 -> 9427.7365 | AG52: =AG42-AG48 -> 10747.053
B53: Операционные расходы | C53: =SUM(C54:C58) -> 15614 | D53: =SUM(D54:D58) -> 15549 | E53: =SUM(E54:E58) -> 16723.397 | F53: =SUM(F54:F58) -> 17694.808 | G53: =SUM(G54:G58) -> 18689.512 | H53: =SUM(H54:H58) -> 19698.538 | I53: =SUM(I54:I58) -> 20710.006 | K53: =SUM(K54:K58) -> 13878 | L53: =SUM(L54:L58) -> 14001.669 | M53: =SUM(M54:M58) -> 14840.865 | N53: =SUM(N54:N58) -> 15731.053 | O53: =SUM(O54:O58) -> 16675.378 | P53: =SUM(P54:P58) -> 17677.179 | Q53: =SUM(Q54:Q58) -> 18740.005 | S53: =SUM(S54:S58) -> 8749 | T53: =SUM(T54:T58) -> 9138 | U53: =SUM(U54:U58) -> 10277.43 | V53: =SUM(V54:V58) -> 11588.646 | W53: =SUM(W54:W58) -> 13100.363 | X53: =SUM(X54:X58) -> 14846.314 | Y53: =SUM(Y54:Y58) -> 17048.397 | AA53: =SUM(AA54:AA58) -> 3945 | AB53: =SUM(AB54:AB58) -> 3944.4444 | AC53: =SUM(AC54:AC58) -> 4136.4444 | AD53: =SUM(AD54:AD58) -> 4338.4894 | AE53: =SUM(AE54:AE58) -> 4551.1619 | AF53: =SUM(AF54:AF58) -> 4775.0825 | AG53: =SUM(AG54:AG58) -> 5010.9125
B54: Расходы на персонал | C54: 7400 | D54: 7405.1667 | E54: =D54*1.06 -> 7849.4767 | F54: =E54*1.06 -> 8320.4453 | G54: =F54*1.06 -> 8819.672 | H54: =G54*1.06 -> 9348.8523 | I54: =H54*1.06 -> 9909.7834 | K54: 4600 | L54: 4606.9184 | M54: 4929.4027 | N54: 5274.4609 | O54: 5643.6731 | P54: 6038.7303 | Q54: 6461.4414 | S54: 2700 | T54: 2715 | U54: 2905.05 | V54: 3108.4035 | W54: 3325.9917 | X54: 3558.8112 | Y54: 3807.9279 | AA54: 3180 | AB54: 3177.7778 | AC54: 3320.7778 | AD54: 3470.2128 | AE54: 3626.3724 | AF54: 3789.5591 | AG54: 3960.0893
B55: Аренда | C55: 864 | D55: 863.83333 | E55: =D55*1.05 -> 907.025 | F55: =E55*1.05 -> 952.37625 | G55: =F55*1.05 -> 999.99506 | H55: =G55*1.05 -> 1049.9948 | I55: =H55*1.05 -> 1102.4946 | K55: 778 | L55: 777.8705 | M55: 820.65338 | N55: 865.78931 | O55: 913.40773 | P55: 963.64515 | Q55: 1016.6456 | S55: 549 | T55: 549 | U55: 581.94 | V55: 616.8564 | W55: 653.86778 | X55: 693.09985 | Y55: 734.68584 | AA55: 200 | AB55: 200 | AC55: 208 | AD55: 216.32 | AE55: 224.9728 | AF55: 233.97171 | AG55: 243.33058
B56: Реклама и маркетинг | C56: 3800 | D56: 3767 | E56: =E17*E18/1000 -> 4278.245 | F56: =F17*F18/1000 -> 4548.9038 | G56: =G17*G18/1000 -> 4803.1085 | H56: =H17*H18/1000 -> 5029.617 | I56: =I17*I18/1000 -> 5214.1513 | K56: 6800 | L56: 6871.1894 | M56: 7249.1048 | N56: 7647.8056 | O56: 8068.4349 | P56: 8512.1988 | Q56: 8980.3698 | S56: 4400 | T56: 4700 | U56: 5546 | V56: 6544.28 | W56: 7722.2504 | X56: 9112.2555 | Y56: 10934.707 | AA56: 360 | AB56: 366.66667 | AC56: 399.66667 | AD56: 435.63667 | AE56: 474.84397 | AF56: 517.57992 | AG56: 564.16212
B57: Оборудование, лицензии и программное обеспечение | C57: 2350 | D57: 2331 | E57: =D57*1.05 -> 2447.55 | F57: =E57*1.05 -> 2569.9275 | G57: =F57*1.05 -> 2698.4239 | H57: =G57*1.05 -> 2833.3451 | I57: =H57*1.05 -> 2975.0123 | K57: 1500 | L57: 1555.741 | M57: 1641.3068 | N57: 1731.5786 | O57: 1826.8155 | P57: 1927.2903 | Q57: 2033.2913 | S57: 1000 | T57: 1024 | U57: 1085.44 | V57: 1150.5664 | W57: 1219.6004 | X57: 1292.7764 | Y57: 1370.343 | AA57: 200 | AB57: 196 | AC57: 203.84 | AD57: 211.9936 | AE57: 220.47334 | AF57: 229.29228 | AG57: 238.46397
B58: Прочие расходы | C58: 1200 | D58: 1182 | E58: =D58*1.05 -> 1241.1 | F58: =E58*1.05 -> 1303.155 | G58: =F58*1.05 -> 1368.3128 | H58: =G58*1.05 -> 1436.7284 | I58: =H58*1.05 -> 1508.5648 | J58: =I58*1.05 -> 1583.993 | K58: 200 | L58: 189.94969 | M58: 200.39692 | N58: 211.41875 | O58: 223.04679 | P58: 235.31436 | Q58: 248.25665 | S58: 100 | T58: 150 | U58: 159 | V58: 168.54 | W58: 178.6524 | X58: 189.37154 | Y58: 200.73384 | AA58: 5 | AB58: 4 | AC58: 4.16 | AD58: 4.3264 | AE58: 4.499456 | AF58: 4.6794342 | AG58: 4.8666116
B59: Операционная прибыль | C59: =C52-C53 -> 18486 | D59: =D52-D53 -> 18588 | E59: =E52-E53 -> 22669.881 | F59: =F52-F53 -> 27990.648 | G59: =G52-G53 -> 34495.45 | H59: =H52-H53 -> 42391.569 | I59: =I52-I53 -> 51920.202 | K59: =K52-K53 -> 8322 | L59: =L52-L53 -> 8902.2957 | M59: =M52-M53 -> 12981.972 | N59: =N52-N53 -> 18005.861 | O59: =O52-O53 -> 24166.715 | P59: =P52-P53 -> 31695.037 | Q59: =Q52-Q53 -> 40866.334 | S59: =S52-S53 -> 1 | T59: =T52-T53 -> 43 | U59: =U52-U53 -> 2885.315 | V59: =V52-V53 -> 7615.909 | W59: =W52-W53 -> 14938.923 | X59: =X52-X53 -> 27108.016 | Y59: =Y52-Y53 -> 45012.024 | AA59: =AA52-AA53 -> 2205 | AB59: =AB52-AB53 -> 1546.3067 | AC59: =AC52-AC53 -> 2167.0436 | AD59: =AD52-AD53 -> 2883.0732 | AE59: =AE52-AE53 -> 3706.9144 | AF59: =AF52-AF53 -> 4652.6541 | AG59: =AG52-AG53 -> 5736.1408
B60: Внереализационные доходы | C60: =SUM(C61:C62) -> 359 | D60: =SUM(D61:D62) -> 385 | E60: =SUM(E61:E62) -> 398.8 | F60: =SUM(F61:F62) -> 413.29 | G60: =SUM(G61:G62) -> 428.5045 | H60: =SUM(H61:H62) -> 444.47973 | I60: =SUM(I61:I62) -> 461.25371 | K60: =SUM(K61:K62) -> 619 | L60: =SUM(L61:L62) -> 668.71228 | M60: =SUM(M61:M62) -> 679.71228 | N60: =SUM(N61:N62) -> 691.31728 | O60: =SUM(O61:O62) -> 703.56055 | P60: =SUM(P61:P62) -> 716.47721 | Q60: =SUM(Q61:Q62) -> 730.10428 | S60: =SUM(S61:S62) -> 800 | T60: =SUM(T61:T62) -> 803 | U60: =SUM(U61:U62) -> 803.48 | V60: =SUM(V61:V62) -> 803.9888 | W60: =SUM(W61:W62) -> 804.52813 | X60: =SUM(X61:X62) -> 805.09982 | Y60: =SUM(Y61:Y62) -> 805.7058 | AA60: =SUM(AA61:AA62) -> 10 | AB60: =SUM(AB61:AB62) -> 15 | AC60: =SUM(AC61:AC62) -> 15.6 | AD60: =SUM(AD61:AD62) -> 16.224 | AE60: =SUM(AE61:AE62) -> 16.87296 | AF60: =SUM(AF61:AF62) -> 17.547878 | AG60: =SUM(AG61:AG62) -> 18.249794
B61: Инвестиционный доход | C61: 109 | D61: 109 | E61: 109 | F61: 109 | G61: 109 | H61: 109 | I61: 109 | K61: 469 | L61: 468.71228 | M61: 468.71228 | N61: 468.71228 | O61: 468.71228 | P61: 468.71228 | Q61: 468.71228 | S61: 795 | T61: 795 | U61: 795 | V61: 795 | W61: 795 | X61: 795 | Y61: 795 | AA61: 0 | AB61: 0 | AC61: 0 | AD61: 0 | AE61: 0 | AF61: 0 | AG61: 0
B62: Прочие доходы | C62: 250 | D62: 276 | E62: =D62*1.05 -> 289.8 | F62: =E62*1.05 -> 304.29 | G62: =F62*1.05 -> 319.5045 | H62: =G62*1.05 -> 335.47973 | I62: =H62*1.05 -> 352.25371 | K62: 150 | L62: 200 | M62: 211 | N62: 222.605 | O62: 234.84827 | P62: 247.76493 | Q62: 261.392 | S62: 5 | T62: 8 | U62: 8.48 | V62: 8.9888 | W62: 9.528128 | X62: 10.099816 | Y62: 10.705805 | AA62: 10 | AB62: 15 | AC62: 15.6 | AD62: 16.224 | AE62: 16.87296 | AF62: 17.547878 | AG62: 18.249794
B63: Внереализационные расходы | C63: =SUM(C64:C65) -> 101 | D63: =SUM(D64:D65) -> 100 | E63: =SUM(E64:E65) -> 102.45 | F63: =SUM(F64:F65) -> 54.0225 | G63: =SUM(G64:G65) -> 56.723625 | H63: =SUM(H64:H65) -> 59.559806 | I63: =SUM(I64:I65) -> 62.537797 | K63: =SUM(K64:K65) -> 80 | L63: =SUM(L64:L65) -> 100 | M63: =SUM(M64:M65) -> 105.5 | N63: =SUM(N64:N65) -> 111.3025 | O63: =SUM(O64:O65) -> 117.42414 | P63: =SUM(P64:P65) -> 123.88247 | Q63: =SUM(Q64:Q65) -> 130.696 | S63: =SUM(S64:S65) -> 5 | T63: =SUM(T64:T65) -> 10 | U63: =SUM(U64:U65) -> 10.6 | V63: =SUM(V64:V65) -> 11.236 | W63: =SUM(W64:W65) -> 11.91016 | X63: =SUM(X64:X65) -> 12.62477 | Y63: =SUM(Y64:Y65) -> 13.382256 | AA63: =SUM(AA64:AA65) -> 10 | AB63: =SUM(AB64:AB65) -> 12 | AC63: =SUM(AC64:AC65) -> 12.48 | AD63: =SUM(AD64:AD65) -> 12.9792 | AE63: =SUM(AE64:AE65) -> 13.498368 | AF63: =SUM(AF64:AF65) -> 14.038303 | AG63: =SUM(AG64:AG65) -> 14.599835
B64: Проценты уплаченные (аннуитет, полное погашение долга в конце 2026) | C64: 51 | D64: 51 | E64: =D64 -> 51 | F64: 0 | G64: 0 | H64: 0 | I64: 0 | K64: 0 | L64: 0 | M64: 0 | N64: 0 | O64: 0 | P64: 0 | Q64: 0 | S64: 0 | T64: 0 | U64: 0 | V64: 0 | W64: 0 | X64: 0 | Y64: 0 | AA64: 0 | AB64: 0 | AC64: 0 | AD64: 0 | AE64: 0 | AF64: 0 | AG64: 0
B65: Прочие расходы | C65: 50 | D65: 49 | E65: =D65*1.05 -> 51.45 | F65: =E65*1.05 -> 54.0225 | G65: =F65*1.05 -> 56.723625 | H65: =G65*1.05 -> 59.559806 | I65: =H65*1.05 -> 62.537797 | K65: 80 | L65: 100 | M65: 105.5 | N65: 111.3025 | O65: 117.42414 | P65: 123.88247 | Q65: 130.696 | S65: 5 | T65: 10 | U65: 10.6 | V65: 11.236 | W65: 11.91016 | X65: 12.62477 | Y65: 13.382256 | AA65: 10 | AB65: 12 | AC65: 12.48 | AD65: 12.9792 | AE65: 13.498368 | AF65: 14.038303 | AG65: 14.599835
B66: Прибыль до налогообложения | C66: =C59+C60-C63 -> 18744 | D66: =D59+D60-D63 -> 18873 | E66: =E59+E60-E63 -> 22966.231 | F66: =F59+F60-F63 -> 28349.916 | G66: =G59+G60-G63 -> 34867.231 | H66: =H59+H60-H63 -> 42776.489 | I66: =I59+I60-I63 -> 52318.918 | K66: =K59+K60-K63 -> 8861 | L66: =L59+L60-L63 -> 9471.008 | M66: =M59+M60-M63 -> 13556.184 | N66: =N59+N60-N63 -> 18585.876 | O66: =O59+O60-O63 -> 24752.852 | P66: =P59+P60-P63 -> 32287.631 | Q66: =Q59+Q60-Q63 -> 41465.743 | S66: =S59+S60-S63 -> 796 | T66: =T59+T60-T63 -> 836 | U66: =U59+U60-U63 -> 3678.195 | V66: =V59+V60-V63 -> 8408.6617 | W66: =W59+W60-W63 -> 15731.541 | X66: =X59+X60-X63 -> 27900.491 | Y66: =Y59+Y60-Y63 -> 45804.347 | AA66: =AA59+AA60-AA63 -> 2205 | AB66: =AB59+AB60-AB63 -> 1549.3067 | AC66: =AC59+AC60-AC63 -> 2170.1636 | AD66: =AD59+AD60-AD63 -> 2886.318 | AE66: =AE59+AE60-AE63 -> 3710.289 | AF66: =AF59+AF60-AF63 -> 4656.1637 | AG66: =AG59+AG60-AG63 -> 5739.7907
B67: Налог на прибыль | C67: =C66*25% -> 4686 | D67: =D66*25% -> 4718.25 | E67: =E66*25% -> 5741.5578 | F67: =F66*25% -> 7087.4789 | G67: =G66*25% -> 8716.8078 | H67: =H66*25% -> 10694.122 | I67: =I66*25% -> 13079.729 | K67: =K66*25% -> 2215.25 | L67: =L66*25% -> 2367.752 | M67: =M66*25% -> 3389.046 | N67: =N66*25% -> 4646.4689 | O67: =O66*25% -> 6188.2129 | P67: =P66*25% -> 8071.9078 | Q67: =Q66*25% -> 10366.436 | S67: =S66*25% -> 199 | T67: =T66*25% -> 209 | U67: =U66*25% -> 919.54875 | V67: =V66*25% -> 2102.1654 | W67: =W66*25% -> 3932.8853 | X67: =X66*25% -> 6975.1228 | Y67: =Y66*25% -> 11451.087 | AA67: =AA66*25% -> 551.25 | AB67: =AB66*25% -> 387.32667 | AC67: =AC66*25% -> 542.5409 | AD67: =AD66*25% -> 721.5795 | AE67: =AE66*25% -> 927.57224 | AF67: =AF66*25% -> 1164.0409 | AG67: =AG66*25% -> 1434.9477
A68: Check | B68: Чистая прибыль | C68: =C66-C67 -> 14058 | D68: =D66-D67 -> 14154.75 | E68: =E66-E67 -> 17224.673 | F68: =F66-F67 -> 21262.437 | G68: =G66-G67 -> 26150.424 | H68: =H66-H67 -> 32082.366 | I68: =I66-I67 -> 39239.188 | K68: =K66-K67 -> 6645.75 | L68: =L66-L67 -> 7103.256 | M68: =M66-M67 -> 10167.138 | N68: =N66-N67 -> 13939.407 | O68: =O66-O67 -> 18564.639 | P68: =P66-P67 -> 24215.724 | Q68: =Q66-Q67 -> 31099.307 | S68: =S66-S67 -> 597 | T68: =T66-T67 -> 627 | U68: =U66-U67 -> 2758.6462 | V68: =V66-V67 -> 6306.4963 | W68: =W66-W67 -> 11798.656 | X68: =X66-X67 -> 20925.368 | Y68: =Y66-Y67 -> 34353.26 | AA68: =AA66-AA67 -> 1653.75 | AB68: =AB66-AB67 -> 1161.98 | AC68: =AC66-AC67 -> 1627.6227 | AD68: =AD66-AD67 -> 2164.7385 | AE68: =AE66-AE67 -> 2782.7167 | AF68: =AF66-AF67 -> 3492.1228 | AG68: =AG66-AG67 -> 4304.843
B69: в т. ч. амортизация | C69: 1132 | D69: 1132 | E69: =D69*1.05 -> 1188.6 | F69: =E69*1.05 -> 1248.03 | G69: =F69*1.05 -> 1310.4315 | H69: =G69*1.05 -> 1375.9531 | I69: =H69*1.05 -> 1444.7507 | K69: 2494 | L69: 2493.8487 | M69: 1445 | N69: 2775.716 | O69: 2928.3804 | P69: 3089.4413 | Q69: 3259.3606 | S69: 628 | T69: 628 | U69: 665.68 | V69: 705.6208 | W69: 747.95805 | X69: 792.83553 | Y69: 840.40566 | AA69: 142 | AB69: 141.62944 | AC69: 147.29462 | AD69: 153.18641 | AE69: 159.31386 | AF69: 165.68642 | AG69: 172.31387
B70: EBITDA | C70: =C68+C67+C64-C61+C69 -> 19818 | D70: =D68+D67+D64-D61+D69 -> 19947 | E70: =E68+E67+E64-E61+E69 -> 24096.831 | F70: =F68+F67+F64-F61+F69 -> 29488.946 | G70: =G68+G67+G64-G61+G69 -> 36068.663 | H70: =H68+H67+H64-H61+H69 -> 44043.442 | I70: =I68+I67+I64-I61+I69 -> 53654.668 | K70: =K68+K67+K64-K61+K69 -> 10886 | L70: =L68+L67+L64-L61+L69 -> 11496.144 | M70: =M68+M67+M64-M61+M69 -> 14532.472 | N70: =N68+N67+N64-N61+N69 -> 20892.879 | O70: =O68+O67+O64-O61+O69 -> 27212.52 | P70: =P68+P67+P64-P61+P69 -> 34908.36 | Q70: =Q68+Q67+Q64-Q61+Q69 -> 44256.391 | S70: =S68+S67+S64-S61+S69 -> 629 | T70: =T68+T67+T64-T61+T69 -> 669 | U70: =U68+U67+U64-U61+U69 -> 3548.875 | V70: =V68+V67+V64-V61+V69 -> 8319.2825 | W70: =W68+W67+W64-W61+W69 -> 15684.499 | X70: =X68+X67+X64-X61+X69 -> 27898.327 | Y70: =Y68+Y67+Y64-Y61+Y69 -> 45849.753 | AA70: =AA68+AA67+AA64-AA61+AA69 -> 2347 | AB70: =AB68+AB67+AB64-AB61+AB69 -> 1690.9361 | AC70: =AC68+AC67+AC64-AC61+AC69 -> 2317.4582 | AD70: =AD68+AD67+AD64-AD61+AD69 -> 3039.5044 | AE70: =AE68+AE67+AE64-AE61+AE69 -> 3869.6028 | AF70: =AF68+AF67+AF64-AF61+AF69 -> 4821.8501 | AG70: =AG68+AG67+AG64-AG61+AG69 -> 5912.1046
B72: ОДДС, тыс. руб.
C73: А | K73: Б | S73: В | AA73: Г
C74: 2025 план | D74: 2025 факт | E74: 2026 | F74: 2027 | G74: 2028 | H74: 2029 | I74: 2030 | K74: 2025 план | L74: 2025 факт | M74: 2026 | N74: 2027 | O74: 2028 | P74: 2029 | Q74: 2030 | S74: 2025 план | T74: 2025 факт | U74: 2026 | V74: 2027 | W74: 2028 | X74: 2029 | Y74: 2030 | AA74: 2025 план | AB74: 2025 факт | AC74: 2026 | AD74: 2027 | AE74: 2028 | AF74: 2029 | AG74: 2030
B75: Остаток денежных средств на начало периода | C75: 9 | D75: 662.6 | E75: =D107 -> 8742.35 | F75: =E107 -> 10673.443 | G75: =F107 -> 13253.576 | H75: =G107 -> 15782.006 | I75: =H107 -> 17305.874 | K75: 791.2 | L75: 419.68907 | M75: =L107 -> 12536.758 | N75: =M107 -> 20000.7 | O75: =N107 -> 27453.85 | P75: =O107 -> 33764.424 | Q75: =P107 -> 39974.694 | S75: 273.2 | T75: 40.2 | U75: =T107 -> 1240.2 | V75: =U107 -> 4664.0262 | W75: =V107 -> 13507.343 | X75: =W107 -> 24578.257 | Y75: =X107 -> 34796.461 | AA75: 144 | AB75: 444.03722 | AC75: =AB107 -> 2946.3509 | AD75: =AC107 -> 5721.2682 | AE75: =AD107 -> 9039.1932 | AF75: =AE107 -> 12981.224 | AG75: =AF107 -> 17639.033
B77: Текущая (операционная) деятельность:
B78: Поступления, всего: | C78: =SUM(C79:C84) -> 55700 | D78: =SUM(D79:D84) -> 53772 | E78: =SUM(E79:E84) -> 59613.237 | F78: =SUM(F79:F84) -> 68637.137 | G78: =SUM(G79:G84) -> 79030.195 | H78: =SUM(H79:H84) -> 91000.325 | I78: =SUM(I79:I84) -> 104787.03 | K78: =SUM(K79:K84) -> 49950 | L78: =SUM(L79:L84) -> 50718.476 | M78: =SUM(M79:M84) -> 52086.33 | N78: =SUM(N79:N84) -> 61557.058 | O78: =SUM(O79:O84) -> 72759.421 | P78: =SUM(P79:P84) -> 86010.948 | Q78: =SUM(Q79:Q84) -> 101687.49 | S78: =SUM(S79:S84) -> 24955 | T78: =SUM(T79:T84) -> 25118 | U78: =SUM(U79:U84) -> 30405.325 | V78: =SUM(V79:V84) -> 39086.87 | W78: =SUM(W79:W84) -> 50209.58 | X78: =SUM(X79:X84) -> 65918.85 | Y78: =SUM(Y79:Y84) -> 87612.519 | AA78: =SUM(AA79:AA84) -> 10010 | AB78: =SUM(AB79:AB84) -> 9266.6576 | AC78: =SUM(AC79:AC84) -> 9888.7311 | AD78: =SUM(AD79:AD84) -> 10967.44 | AE78: =SUM(AE79:AE84) -> 12177.162 | AF78: =SUM(AF79:AF84) -> 13533.812 | AG78: =SUM(AG79:AG84) -> 15055.24
B79: Денежные средства, полученные за обработку платежей и переводов | C79: 51450 | D79: 51502 | E79: =E43 -> 59323.437 | F79: =F43 -> 68332.847 | G79: =G43 -> 78710.69 | H79: =H43 -> 90664.845 | I79: =I43 -> 104434.77 | K79: 0 | L79: 0 | M79: 0 | N79: 0 | O79: 0 | P79: 0 | Q79: 0 | S79: 0 | T79: 0 | U79: 0 | V79: 0 | W79: 0 | X79: 0 | Y79: 0 | AA79: 0 | AB79: 0 | AC79: 0 | AD79: 0 | AE79: 0 | AF79: 0 | AG79: 0
B80: Денежные средства, полученные за разработку программного обеспечения | C80: 0 | D80: 0 | E80: 0 | F80: 0 | G80: 0 | H80: 0 | I80: 0 | K80: 27500 | L80: 28089.768 | M80: 33145.926 | N80: 39112.193 | O80: 46152.388 | P80: 54459.818 | Q80: 64262.585 | S80: 0 | T80: 0 | U80: 0 | V80: 0 | W80: 0 | X80: 0 | Y80: 0 | AA80: 0 | AB80: 0 | AC80: 0 | AD80: 0 | AE80: 0 | AF80: 0 | AG80: 0
B81: Денежные средства, полученные от аутсорсинговых услуг | C81: 0 | D81: 0 | E81: 0 | F81: 0 | G81: 0 | H81: 0 | I81: 0 | K81: 15000 | L81: 15125.26 | M81: 17999.059 | N81: 21418.88 | O81: 25488.468 | P81: 30331.276 | Q81: 36094.219 | S81: 0 | T81: 0 | U81: 0 | V81: 0 | W81: 0 | X81: 0 | Y81: 0 | AA81: 0 | AB81: 0 | AC81: 0 | AD81: 0 | AE81: 0 | AF81: 0 | AG81: 0
B82: Денежные средства, полученные за услуги трейдинговой площадки | C82: 0 | D82: 0 | E82: 0 | F82: 0 | G82: 0 | H82: 0 | I82: 0 | K82: 0 | L82: 0 | M82: 0 | N82: 0 | O82: 0 | P82: 0 | Q82: 0 | S82: 23700 | T82: 24565 | U82: 29797.345 | V82: 37246.681 | W82: 47675.752 | X82: 63408.75 | Y82: 85601.813 | AA82: 0 | AB82: 0 | AC82: 0 | AD82: 0 | AE82: 0 | AF82: 0 | AG82: 0
B83: Денежные средства, полученные за услуги бронирования | C83: 0 | D83: 0 | E83: 0 | F83: 0 | G83: 0 | H83: 0 | I83: 0 | K83: 0 | L83: 0 | M83: 0 | N83: 0 | O83: 0 | P83: 0 | Q83: 0 | S83: 0 | T83: 0 | U83: 0 | V83: 0 | W83: 0 | X83: 0 | Y83: 0 | AA83: 8500 | AB83: 7911.8422 | AC83: 8873.1311 | AD83: 9951.2165 | AE83: 11160.289 | AF83: 12516.264 | AG83: 14036.991
B84: Прочие расчёты с контрагентами | C84: 4250 | D84: 2270 | E84: =E62+0 -> 289.8 | F84: =F62+0 -> 304.29 | G84: =G62+0 -> 319.5045 | H84: =H62+0 -> 335.47973 | I84: =I62+0 -> 352.25371 | K84: 7450 | L84: 7503.4483 | M84: 941.34483 | N84: 1025.9843 | O84: 1118.5655 | P84: 1219.8539 | Q84: 1330.6899 | S84: 1255 | T84: 553 | U84: 607.98 | V84: 1840.1888 | W84: 2533.8281 | X84: 2510.0998 | Y84: 2010.7058 | AA84: 1510 | AB84: 1354.8153 | AC84: 1015.6 | AD84: 1016.224 | AE84: 1016.873 | AF84: 1017.5479 | AG84: 1018.2498
B85: Выбытия, всего: | C85: =SUM(C86:C89) -> -34004 | D85: =SUM(D86:D89) -> -34332.417 | E85: =SUM(E86:E89) -> -40279.119 | F85: =SUM(F86:F89) -> -45213.628 | G85: =SUM(G86:G89) -> -50610.769 | H85: =SUM(H86:H89) -> -56535.462 | I85: =SUM(I86:I89) -> -63046.011 | K85: =SUM(K86:K89) -> -37981.25 | L85: =SUM(L86:L89) -> -38292.249 | M85: =SUM(M86:M89) -> -38270.448 | N85: =SUM(N86:N89) -> -43706.831 | O85: =SUM(O86:O89) -> -50004.152 | P85: =SUM(P86:P89) -> -57305.744 | Q85: =SUM(Q86:Q89) -> -65779.409 | S85: =SUM(S86:S89) -> -22726 | T85: =SUM(T86:T89) -> -23564 | U85: =SUM(U86:U89) -> -26594.559 | V85: =SUM(V86:V89) -> -30421.697 | W85: =SUM(W86:W89) -> -35279.798 | X85: =SUM(X86:X89) -> -41802.546 | Y85: =SUM(Y86:Y89) -> -50479.167 | AA85: =SUM(AA86:AA89) -> -6614.25 | AB85: =SUM(AB86:AB89) -> -6564.3439 | AC85: =SUM(AC86:AC89) -> -6905.8137 | AD85: =SUM(AD86:AD89) -> -7433.1955 | AE85: =SUM(AE86:AE89) -> -8010.1589 | AF85: =SUM(AF86:AF89) -> -8642.0314 | AG85: =SUM(AG86:AG89) -> -9334.7529
B86: Расчёты с персоналом | C86: -21110 | D86: -21096.08 | E86: =-(E54+E49) -> -23921.845 | F86: =-(F54+F49) -> -26917.155 | G86: =-(G54+G49) -> -30092.185 | H86: =-(H54+H49) -> -33457.716 | I86: =-(I54+I49) -> -37025.179 | K86: -20600 | L86: -20620.567 | M86: -23345.098 | N86: -26452.511 | O86: -29998.431 | P86: -34046.701 | Q86: -38670.608 | S86: -16050 | T86: -16255 | U86: -17257.45 | V86: -18321.947 | W86: -19452.348 | X86: -20652.749 | Y86: -21927.502 | AA86: -4980 | AB86: -5012.7578 | AC86: -5238.3319 | AD86: -5474.0568 | AE86: -5720.3894 | AF86: -5977.8069 | AG86: -6246.8082
B87: Оплата маркетинговых и коммерческих расходов | C87: -3800 | D87: -3767 | E87: =-E56 -> -4278.245 | F87: =-F56 -> -4548.9038 | G87: =-G56 -> -4803.1085 | H87: =-H56 -> -5029.617 | I87: =-I56 -> -5214.1513 | K87: -6800 | L87: -6871.1894 | M87: -7249.1048 | N87: -7647.8056 | O87: -8068.4349 | P87: -8512.1988 | Q87: -8980.3698 | S87: -4400 | T87: -4700 | U87: -5546 | V87: -6544.28 | W87: -7722.2504 | X87: -9112.2555 | Y87: -10934.707 | AA87: -360 | AB87: -366.66667 | AC87: -399.66667 | AD87: -435.63667 | AE87: -474.84397 | AF87: -517.57992 | AG87: -564.16212
B88: Уплаченный налог на прибыль | C88: -686 | D88: -971.25 | E88: =-E67 -> -5741.5578 | F88: =-F67 -> -7087.4789 | G88: =-G67 -> -8716.8078 | H88: =-H67 -> -10694.122 | I88: =-I67 -> -13079.729 | K88: -1795.25 | L88: -1945.4503 | M88: -3389.046 | N88: -4646.4689 | O88: -6188.2129 | P88: -8071.9078 | Q88: -10366.436 | S88: -199 | T88: -209 | U88: -919.54875 | V88: -2102.1654 | W88: -3932.8853 | X88: -6975.1228 | Y88: -11451.087 | AA88: -551.25 | AB88: -387.32667 | AC88: -542.5409 | AD88: -721.5795 | AE88: -927.57224 | AF88: -1164.0409 | AG88: -1434.9477
B89: Прочие расчёты с контрагентами | C89: -8408 | D89: -8498.0867 | E89: =-((E50+E51+E57+E58+E65)-E69)-(E124-D124) -> -6337.471 | F89: =-((F50+F51+F57+F58+F65)-F69)-(F124-E124) -> -6660.0902 | G89: =-((G50+G51+G57+G58+G65)-G69)-(G124-F124) -> -6998.6679 | H89: =-((H50+H51+H57+H58+H65)-H69)-(H124-G124) -> -7354.0074 | I89: =-((I50+I51+I57+I58+I65)-I69)-(I124-H124) -> -7726.9516 | K89: -8786 | L89: -8855.042 | M89: -4287.1986 | N89: -4960.0456 | O89: -5749.0732 | P89: -6674.9363 | Q89: -7761.9951 | S89: -2077 | T89: -2400 | U89: -2871.56 | V89: -3453.3036 | W89: -4172.3143 | X89: -5062.4188 | Y89: -6165.871 | AA89: -723 | AB89: -797.59278 | AC89: -725.27427 | AD89: -801.92257 | AE89: -887.35329 | AF89: -982.60369 | AG89: -1088.8349
B90: Сальдо денежных средств по текущей деятельности: | C90: =C78+C85 -> 21696 | D90: =D78+D85 -> 19439.583 | E90: =E78+E85 -> 19334.118 | F90: =F78+F85 -> 23423.508 | G90: =G78+G85 -> 28419.426 | H90: =H78+H85 -> 34464.862 | I90: =I78+I85 -> 41741.015 | K90: =K78+K85 -> 11968.75 | L90: =L78+L85 -> 12426.228 | M90: =M78+M85 -> 13815.883 | N90: =N78+N85 -> 17850.227 | O90: =O78+O85 -> 22755.269 | P90: =P78+P85 -> 28705.204 | Q90: =Q78+Q85 -> 35908.085 | S90: =S78+S85 -> 2229 | T90: =T78+T85 -> 1554 | U90: =U78+U85 -> 3810.7662 | V90: =V78+V85 -> 8665.1735 | W90: =W78+W85 -> 14929.782 | X90: =X78+X85 -> 24116.304 | Y90: =Y78+Y85 -> 37133.352 | AA90: =AA78+AA85 -> 3395.75 | AB90: =AB78+AB85 -> 2702.3137 | AC90: =AC78+AC85 -> 2982.9173 | AD90: =AD78+AD85 -> 3534.2449 | AE90: =AE78+AE85 -> 4167.0034 | AF90: =AF78+AF85 -> 4891.7809 | AG90: =AG78+AG85 -> 5720.4875
B92: Инвестиционная деятельность:
B93: Дивиденды полученные | C93: 109 | D93: 109 | E93: =E61 -> 109 | F93: =F61 -> 109 | G93: =G61 -> 109 | H93: =H61 -> 109 | I93: =I61 -> 109 | K93: 469 | L93: 468.71228 | M93: 468.71228 | N93: 468.71228 | O93: 468.71228 | P93: 468.71228 | Q93: 468.71228 | S93: 795 | T93: 795 | U93: 795 | V93: 795 | W93: 795 | X93: 795 | Y93: 795 | AA93: 0 | AB93: 0 | AC93: 0 | AD93: 0 | AE93: 0 | AF93: 0 | AG93: 0
B94: Проценты полученные | C94: 0 | D94: 0 | E94: =D94 -> 0 | F94: =E94 -> 0 | G94: =F94 -> 0 | H94: =G94 -> 0 | I94: =H94 -> 0 | K94: 0 | L94: 0 | M94: 0 | N94: 0 | O94: 0 | P94: 0 | Q94: 0 | S94: 0 | T94: 0 | U94: 0 | V94: 0 | W94: 0 | X94: 0 | Y94: 0 | AA94: 0 | AB94: 0 | AC94: 0 | AD94: 0 | AE94: 0 | AF94: 0 | AG94: 0
B95: Проценты уплаченные | C95: =-C64 -> -51 | D95: =-D64 -> -51 | E95: =-E64 -> -51 | F95: 0 | G95: =F95 -> 0 | H95: =G95 -> 0 | I95: =H95 -> 0 | K95: 0 | L95: 0 | M95: 0 | N95: 0 | O95: 0 | P95: 0 | Q95: 0 | S95: 0 | T95: 0 | U95: 0 | V95: 0 | W95: 0 | X95: 0 | Y95: 0 | AA95: 0 | AB95: 0 | AC95: 0 | AD95: 0 | AE95: 0 | AF95: 0 | AG95: 0
B96: Сальдо денежных средств по инвестиционной деятельности: | C96: =SUM(C93:C95) -> 58 | D96: =SUM(D93:D95) -> 58 | E96: =SUM(E93:E95) -> 58 | F96: =SUM(F93:F95) -> 109 | G96: =SUM(G93:G95) -> 109 | H96: =SUM(H93:H95) -> 109 | I96: =SUM(I93:I95) -> 109 | K96: =SUM(K93:K95) -> 469 | L96: =SUM(L93:L95) -> 468.71228 | M96: =SUM(M93:M95) -> 468.71228 | N96: =SUM(N93:N95) -> 468.71228 | O96: =SUM(O93:O95) -> 468.71228 | P96: =SUM(P93:P95) -> 468.71228 | Q96: =SUM(Q93:Q95) -> 468.71228 | S96: =SUM(S93:S95) -> 795 | T96: =SUM(T93:T95) -> 795 | U96: =SUM(U93:U95) -> 795 | V96: =SUM(V93:V95) -> 795 | W96: =SUM(W93:W95) -> 795 | X96: =SUM(X93:X95) -> 795 | Y96: =SUM(Y93:Y95) -> 795 | AA96: =SUM(AA93:AA95) -> 0 | AB96: =SUM(AB93:AB95) -> 0 | AC96: =SUM(AC93:AC95) -> 0 | AD96: =SUM(AD93:AD95) -> 0 | AE96: =SUM(AE93:AE95) -> 0 | AF96: =SUM(AF93:AF95) -> 0 | AG96: =SUM(AG93:AG95) -> 0
B99: Финансовая деятельность:
B100: Денежные средства, полученные по кредиту (тело) | C100: 600 | D100: 600 | E100: =E32 -> 600 | F100: 0 | G100: 0 | H100: 0 | I100: 0 | K100: 0 | L100: 0 | M100: 0 | N100: 0 | O100: 0 | P100: 0 | Q100: 0 | S100: 0 | T100: 0 | U100: 0 | V100: 0 | W100: 0 | X100: 0 | Y100: 0 | AA100: 0 | AB100: 0 | AC100: 0 | AD100: 0 | AE100: 0 | AF100: 0 | AG100: 0
B101: Денежные средства, уплаченные за аренду | C101: -864 | D101: -863.83333 | E101: =-E55 -> -907.025 | F101: =-F55 -> -952.37625 | G101: =-G55 -> -999.99506 | H101: =-H55 -> -1049.9948 | I101: =-I55 -> -1102.4946 | K101: -778 | L101: -777.8705 | M101: -820.65338 | N101: -865.78931 | O101: -913.40773 | P101: -963.64515 | Q101: -1016.6456 | S101: -549 | T101: -549 | U101: -581.94 | V101: -616.8564 | W101: -653.86778 | X101: -693.09985 | Y101: -734.68584 | AA101: -200 | AB101: -200 | AC101: -208 | AD101: -216.32 | AE101: -224.9728 | AF101: -233.97171 | AG101: -243.33058
B102: Денежные средства, уплаченные по кредиту (тело) | C102: -1154 | D102: -1154 | E102: =D102 -> -1154 | F102: 0 | G102: 0 | H102: 0 | I102: 0 | K102: 0 | L102: 0 | M102: 0 | N102: 0 | O102: 0 | P102: 0 | Q102: 0 | S102: -600 | T102: -600 | U102: -600 | V102: 0 | W102: 0 | X102: 0 | Y102: 0 | AA102: 0 | AB102: 0 | AC102: 0 | AD102: 0 | AE102: 0 | AF102: 0 | AG102: 0
B103: Денежные средства, уплаченные в качестве дивидендов | C103: -7000 | D103: -10000 | E103: =-E144 -> -16000 | F103: =-F144 -> -20000 | G103: =-G144 -> -25000 | H103: =-H144 -> -32000 | I103: =-I144 -> -39000 | K103: 0 | L103: 0 | M103: -6000 | N103: -10000 | O103: -16000 | P103: -22000 | Q103: -29000 | S103: 0 | T103: 0 | U103: 0 | V103: 0 | W103: -4000 | X103: -14000 | Y103: -29000 | AA103: 0 | AB103: 0 | AC103: 0 | AD103: 0 | AE103: 0 | AF103: 0 | AG103: -1000
B104: Сальдо денежных средств по финансовой деятельности: | C104: =SUM(C100:C103) -> -8418 | D104: =SUM(D100:D103) -> -11417.833 | E104: =SUM(E100:E103) -> -17461.025 | F104: =SUM(F100:F103) -> -20952.376 | G104: =SUM(G100:G103) -> -25999.995 | H104: =SUM(H100:H103) -> -33049.995 | I104: =SUM(I100:I103) -> -40102.495 | K104: =SUM(K100:K103) -> -778 | L104: =SUM(L100:L103) -> -777.8705 | M104: =SUM(M100:M103) -> -6820.6534 | N104: =SUM(N100:N103) -> -10865.789 | O104: =SUM(O100:O103) -> -16913.408 | P104: =SUM(P100:P103) -> -22963.645 | Q104: =SUM(Q100:Q103) -> -30016.646 | S104: =SUM(S100:S103) -> -1149 | T104: =SUM(T100:T103) -> -1149 | U104: =SUM(U100:U103) -> -1181.94 | V104: =SUM(V100:V103) -> -616.8564 | W104: =SUM(W100:W103) -> -4653.8678 | X104: =SUM(X100:X103) -> -14693.1 | Y104: =SUM(Y100:Y103) -> -29734.686 | AA104: =SUM(AA100:AA103) -> -200 | AB104: =SUM(AB100:AB103) -> -200 | AC104: =SUM(AC100:AC103) -> -208 | AD104: =SUM(AD100:AD103) -> -216.32 | AE104: =SUM(AE100:AE103) -> -224.9728 | AF104: =SUM(AF100:AF103) -> -233.97171 | AG104: =SUM(AG100:AG103) -> -1243.3306
B105: Денежный поток, итого | C105: =C90+C96+C104 -> 13336 | D105: =D90+D96+D104 -> 8079.75 | E105: =E90+E96+E104 -> 1931.0934 | F105: =F90+F96+F104 -> 2580.1321 | G105: =G90+G96+G104 -> 2528.4305 | H105: =H90+H96+H104 -> 1523.8676 | I105: =I90+I96+I104 -> 1747.5206 | K105: =K90+K96+K104 -> 11659.75 | L105: =L90+L96+L104 -> 12117.069 | M105: =M90+M96+M104 -> 7463.9414 | N105: =N90+N96+N104 -> 7453.1498 | O105: =O90+O96+O104 -> 6310.5739 | P105: =P90+P96+P104 -> 6210.2708 | Q105: =Q90+Q96+Q104 -> 6360.1518 | S105: =S90+S96+S104 -> 1875 | T105: =T90+T96+T104 -> 1200 | U105: =U90+U96+U104 -> 3423.8262 | V105: =V90+V96+V104 -> 8843.3171 | W105: =W90+W96+W104 -> 11070.914 | X105: =X90+X96+X104 -> 10218.204 | Y105: =Y90+Y96+Y104 -> 8193.6661 | AA105: =AA90+AA96+AA104 -> 3195.75 | AB105: =AB90+AB96+AB104 -> 2502.3137 | AC105: =AC90+AC96+AC104 -> 2774.9173 | AD105: =AD90+AD96+AD104 -> 3317.9249 | AE105: =AE90+AE96+AE104 -> 3942.0306 | AF105: =AF90+AF96+AF104 -> 4657.8092 | AG105: =AG90+AG96+AG104 -> 4477.1569
A107: Check | B107: Остаток денежных средств на конец периода | C107: =C75+C105 -> 13345 | D107: =D75+D105 -> 8742.35 | E107: =E75+E105 -> 10673.443 | F107: =F75+F105 -> 13253.576 | G107: =G105+G75 -> 15782.006 | H107: =H75+H105 -> 17305.874 | I107: =I75+I105 -> 19053.394 | K107: =K75+K105 -> 12450.95 | L107: =L75+L105 -> 12536.758 | M107: =M75+M105 -> 20000.7 | N107: =N75+N105 -> 27453.85 | O107: =O75+O105 -> 33764.424 | P107: =P75+P105 -> 39974.694 | Q107: =Q75+Q105 -> 46334.846 | S107: =S75+S105 -> 2148.2 | T107: =T75+T105 -> 1240.2 | U107: =U75+U105 -> 4664.0262 | V107: =V75+V105 -> 13507.343 | W107: =W75+W105 -> 24578.257 | X107: =X75+X105 -> 34796.461 | Y107: =Y75+Y105 -> 42990.127 | AA107: =AA75+AA105 -> 3339.75 | AB107: =AB75+AB105 -> 2946.3509 | AC107: =AC75+AC105 -> 5721.2682 | AD107: =AD75+AD105 -> 9039.1932 | AE107: =AE75+AE105 -> 12981.224 | AF107: =AF75+AF105 -> 17639.033 | AG107: =AG75+AG105 -> 22116.19
B110: Управленческий баланс*, тыс. руб.
C111: А | K111: Б | S111: В | AA111: Г
C112: 31.12.25 план | D112: 31.12.25 факт | E112: 31.12.26 | F112: 31.12.27 | G112: 31.12.28 | H112: 31.12.29 | I112: 31.12.30 | K112: 31.12.25 план | L112: 31.12.25 факт | M112: 31.12.26 | N112: 31.12.27 | O112: 31.12.28 | P112: 31.12.29 | Q112: 31.12.30 | S112: 31.12.25 план | T112: 31.12.25 факт | U112: 31.12.26 | V112: 31.12.27 | W112: 31.12.28 | X112: 31.12.29 | Y112: 31.12.30 | AA112: 31.12.25 план | AB112: 31.12.25 факт | AC112: 31.12.26 | AD112: 31.12.27 | AE112: 31.12.28 | AF112: 31.12.29 | AG112: 31.12.30
B113: АКТИВЫ | C113: =C114+C123 -> 66691.8 | D113: =D114+D123 -> 64982.35 | E113: =E114+E123 -> 65053.023 | F113: =F114+F123 -> 66315.46 | G113: =G114+G123 -> 67465.884 | H113: =H114+H123 -> 67548.25 | I113: =I114+I123 -> 67787.438 | K113: =K114+K123 -> 53576.95 | L113: =L114+L123 -> 53768.641 | M113: =M114+M123 -> 58666.124 | N113: =N114+N123 -> 63408.91 | O113: =O114+O123 -> 66857.266 | P113: =P114+P123 -> 70045.078 | Q113: =Q114+Q123 -> 73213.683 | S113: =S114+S123 -> 16911.2 | T113: =T114+T123 -> 16086.2 | U113: =U114+U123 -> 18844.346 | V113: =V114+V123 -> 26982.043 | W113: =W114+W123 -> 37304.998 | X113: =X114+X123 -> 46730.367 | Y113: =Y114+Y123 -> 54083.627 | AA113: =AA114+AA123 -> 4995.75 | AB113: =AB114+AB123 -> 4633.1731 | AC113: =AC114+AC123 -> 7260.7958 | AD113: =AD114+AD123 -> 10425.534 | AE113: =AE114+AE123 -> 14208.251 | AF113: =AF114+AF123 -> 18700.374 | AG113: =AG114+AG123 -> 23005.217
B114: Внеоборотные активы: | C114: =SUM(C115:C118) -> 51046.8 | D114: =SUM(D115:D118) -> 53846 | E114: =SUM(E115:E118) -> 52057.4 | F114: =SUM(F115:F118) -> 50809.37 | G114: =SUM(G115:G118) -> 49498.939 | H114: =SUM(H115:H118) -> 48122.985 | I114: =SUM(I115:I118) -> 46678.235 | K114: =SUM(K115:K118) -> 35926 | L114: =SUM(L115:L118) -> 36026.097 | M114: =SUM(M115:M118) -> 33395.087 | N114: =SUM(N115:N118) -> 30619.371 | O114: =SUM(O115:O118) -> 27690.99 | P114: =SUM(P115:P118) -> 24601.549 | Q114: =SUM(Q115:Q118) -> 21342.189 | S114: =SUM(S115:S118) -> 14763 | T114: =SUM(T115:T118) -> 14846 | U114: =SUM(U115:U118) -> 14180.32 | V114: =SUM(V115:V118) -> 13474.699 | W114: =SUM(W115:W118) -> 12726.741 | X114: =SUM(X115:X118) -> 11933.906 | Y114: =SUM(Y115:Y118) -> 11093.5 | AA114: =SUM(AA115:AA118) -> 1556 | AB114: =SUM(AB115:AB118) -> 1545.7111 | AC114: =SUM(AC115:AC118) -> 1398.4165 | AD114: =SUM(AD115:AD118) -> 1245.2301 | AE114: =SUM(AE115:AE118) -> 1085.9162 | AF114: =SUM(AF115:AF118) -> 920.2298 | AG114: =SUM(AG115:AG118) -> 747.91593
...

Sheet Консолидация--->

Sheet ОДДС
A1: ОДДС, тыс. руб. | B1: Консолидация по группе | AV1: А | BD1: Б | BL1: В | BT1: Г
B2: 2025 план | C2: ВГО 1 | D2: ВГО 2 | E2: ВГО 3 | F2: ВГО 4 | G2: ВГО 5 | H2: А--->В беспроцентный заём | I2: 2025 факт | J2: ВГО 1 | K2: ВГО 2 | L2: ВГО 3 | M2: ВГО 4 | N2: ВГО 5 | O2: А--->В беспроцентный заём | P2: 2026 | Q2: ВГО 1 | R2: ВГО 2 | S2: ВГО 3 | T2: ВГО 4 | U2: ВГО 5 | V2: А--->В беспроцентный заём | W2: 2027 | X2: ВГО 1 | Y2: ВГО 2 | Z2: ВГО 3 | AA2: ВГО 4 | AB2: ВГО 5 | AC2: 2028 | AD2: ВГО 1 | AE2: ВГО 2 | AF2: ВГО 3 | AG2: ВГО 4 | AH2: ВГО 5 | AI2: 2029 | AJ2: ВГО 1 | AK2: ВГО 2 | AL2: ВГО 3 | AM2: ВГО 4 | AN2: ВГО 5 | AO2: 2030 | AP2: ВГО 1 | AQ2: ВГО 2 | AR2: ВГО 3 | AS2: ВГО 4 | AT2: ВГО 5 | AV2: 2025 план | AW2: 2025 факт | AX2: 2026 | AY2: 2027 | AZ2: 2028 | BA2: 2029 | BB2: 2030 | BD2: 2025 план | BE2: 2025 факт | BF2: 2026 | BG2: 2027 | BH2: 2028 | BI2: 2029 | BJ2: 2030 | BL2: 2025 план | BM2: 2025 факт | BN2: 2026 | BO2: 2027 | BP2: 2028 | BQ2: 2029 | BR2: 2030 | BT2: 2025 план | BU2: 2025 факт | BV2: 2026 | BW2: 2027 | BX2: 2028 | BY2: 2029 | BZ2: 2030
A3: Остаток денежных средств на начало периода | B3: =(AV3+BD3+BL3) -> 1073.4 | I3: =(AW3+BE3+BM3) -> 1122.4891 | P3: =(AX3+BF3+BN3) -> 22519.308 | W3: =(AY3+BG3+BO3) -> 35338.17 | AC3: =(AZ3+BH3+BP3) -> 54214.769 | AI3: =BA3+BI3+BQ3 -> 74124.687 | AO3: =BB3+BJ3+BR3 -> 92077.029 | AV3: 9 | AW3: 662.6 | AX3: 8742.35 | AY3: 10673.443 | AZ3: 13253.576 | BA3: 15782.006 | BB3: 17305.874 | BD3: 791.2 | BE3: 419.68907 | BF3: =BE35 -> 12536.758 | BG3: =BF35 -> 20000.7 | BH3: =BG35 -> 27453.85 | BI3: =BH35 -> 33764.424 | BJ3: =BI35 -> 39974.694 | BL3: 273.2 | BM3: 40.2 | BN3: =BM35 -> 1240.2 | BO3: =BN35 -> 4664.0262 | BP3: =BO35 -> 13507.343 | BQ3: =BP35 -> 24578.257 | BR3: =BQ35 -> 34796.461 | BT3: 144 | BU3: 444.03722 | BV3: =BU35 -> 2946.3509 | BW3: =BV35 -> 5721.2682 | BX3: =BW35 -> 9039.1932 | BY3: =BX35 -> 12981.224 | BZ3: =BY35 -> 17639.033
A5: Текущая (операционная) деятельность:
A6: Поступления, всего: | B6: =SUM(B7:B12) -> 128086 | I6: =SUM(I7:I12) -> 127089.48 | P6: =SUM(P7:P12) -> 139348.29 | W6: =SUM(W7:W12) -> 166396.81 | AC6: =SUM(AC7:AC12) -> 198987.23 | AI6: =SUM(AI7:AI12) -> 239790.38 | AO6: =SUM(AO7:AO12) -> 290819.46 | AV6: 55700 | AW6: 53772 | AX6: 59613.237 | AY6: 68637.137 | AZ6: 79030.195 | BA6: 91000.325 | BB6: 104787.03 | BD6: =SUM(BD7:BD12) -> 49950 | BE6: =SUM(BE7:BE12) -> 50718.476 | BF6: =SUM(BF7:BF12) -> 52086.33 | BG6: =SUM(BG7:BG12) -> 61557.058 | BH6: =SUM(BH7:BH12) -> 72759.421 | BI6: =SUM(BI7:BI12) -> 86010.948 | BJ6: =SUM(BJ7:BJ12) -> 101687.49 | BL6: =SUM(BL7:BL12) -> 24955 | BM6: =SUM(BM7:BM12) -> 25118 | BN6: =SUM(BN7:BN12) -> 30405.325 | BO6: =SUM(BO7:BO12) -> 39086.87 | BP6: =SUM(BP7:BP12) -> 50209.58 | BQ6: =SUM(BQ7:BQ12) -> 65918.85 | BR6: =SUM(BR7:BR12) -> 87612.519 | BT6: =SUM(BT7:BT12) -> 10010 | BU6: =SUM(BU7:BU12) -> 9266.6576 | BV6: =SUM(BV7:BV12) -> 9888.7311 | BW6: =SUM(BW7:BW12) -> 10967.44 | BX6: =SUM(BX7:BX12) -> 12177.162 | BY6: =SUM(BY7:BY12) -> 13533.812 | BZ6: =SUM(BZ7:BZ12) -> 15055.24
A7: Денежные средства, полученные за обработку платежей и переводов | B7: =(AV7+BD7+BL7)+SUM(C7:H7) -> 51318 | C7: =-Вводные!C23 -> -110 | F7: =-Вводные!C26 -> -22 | I7: =(AW7+BE7+BM7)+SUM(J7:O7) -> 51370 | J7: =-Вводные!D23 -> -110 | M7: =-Вводные!D26 -> -22 | P7: =(AX7+BF7+BN7)+SUM(Q7:U7) -> 59184.837 | Q7: =-Вводные!E23 -> -115.5 | T7: =-Вводные!E26 -> -23.1 | W7: =(AY7+BG7+BO7)+SUM(X7:AB7) -> 68187.592 | X7: =-Вводные!F23 -> -121 | AA7: =-Вводные!F26 -> -24.255 | AC7: =(AZ7+BH7+BP7)+SUM(AD7:AH7) -> 78558.722 | AD7: =-Вводные!G23 -> -126.5 | AG7: =-Вводные!G26 -> -25.46775 | AI7: =(BA7+BI7+BQ7)+SUM(AJ7:AN7) -> 90506.104 | AJ7: =-Вводные!H23 -> -132 | AM7: =-Вводные!H26 -> -26.741138 | AO7: =(BB7+BJ7+BR7)+SUM(AP7:AT7) -> 104269.19 | AP7: =-Вводные!I23 -> -137.5 | AS7: =-Вводные!I26 -> -28.078194 | AV7: 51450 | AW7: 51502 | AX7: 59323.437 | AY7: 68332.847 | AZ7: 78710.69 | BA7: 90664.845 | BB7: 104434.77 | BD7: 0 | BE7: 0 | BF7: 0 | BG7: 0 | BH7: 0 | BI7: 0 | BJ7: 0 | BL7: 0 | BM7: 0 | BN7: 0 | BO7: 0 | BP7: 0 | BQ7: 0 | BR7: 0 | BT7: 0 | BU7: 0 | BV7: 0 | BW7: 0 | BX7: 0 | BY7: 0 | BZ7: 0
A8: Денежные средства, полученные за разработку программного обеспечения | B8: =(AV8+BD8+BL8)+SUM(C8:H8) -> 26290 | G8: =-Вводные!C27 -> -1210 | I8: =(AW8+BE8+BM8)+SUM(J8:O8) -> 26879.768 | N8: =-Вводные!D27 -> -1210 | P8: =(AX8+BF8+BN8)+SUM(Q8:U8) -> 31825.926 | U8: =-Вводные!E27 -> -1320 | W8: =(AY8+BG8+BO8)+SUM(X8:AB8) -> 37792.193 | AB8: =-Вводные!F27 -> -1320 | AC8: =(AZ8+BH8+BP8)+SUM(AD8:AH8) -> 44832.388 | AH8: =-Вводные!G27 -> -1320 | AI8: =(BA8+BI8+BQ8)+SUM(AJ8:AN8) -> 53139.818 | AN8: =-Вводные!H27 -> -1320 | AO8: =(BB8+BJ8+BR8)+SUM(AP8:AT8) -> 62942.585 | AT8: =-Вводные!I27 -> -1320 | AV8: 0 | AW8: 0 | AX8: 0 | AY8: 0 | AZ8: 0 | BA8: 0 | BB8: 0 | BD8: 27500 | BE8: 28089.768 | BF8: 33145.926 | BG8: 39112.193 | BH8: 46152.388 | BI8: 54459.818 | BJ8: 64262.585 | BL8: 0 | BM8: 0 | BN8: 0 | BO8: 0 | BP8: 0 | BQ8: 0 | BR8: 0 | BT8: 0 | BU8: 0 | BV8: 0 | BW8: 0 | BX8: 0 | BY8: 0 | BZ8: 0
A9: Денежные средства, полученные от аутсорсинговых услуг | B9: =(AV9+BD9+BL9)+SUM(C9:H9) -> 13823 | D9: =-Вводные!C24 -> -1100 | E9: =-Вводные!C25 -> -77 | I9: =(AW9+BE9+BM9)+SUM(J9:O9) -> 13948.26 | K9: =-Вводные!D24 -> -1100 | L9: =-Вводные!D25 -> -77 | P9: =(AX9+BF9+BN9)+SUM(Q9:U9) -> 16701.059 | R9: =-Вводные!E24 -> -1210 | S9: =-Вводные!E25 -> -88 | W9: =(AY9+BG9+BO9)+SUM(X9:AB9) -> 19999.88 | Y9: =-Вводные!F24 -> -1320 | Z9: =-Вводные!F25 -> -99 | AC9: =(AZ9+BH9+BP9)+SUM(AD9:AH9) -> 23948.468 | AE9: =-Вводные!G24 -> -1430 | AF9: =-Вводные!G25 -> -110 | AI9: =(BA9+BI9+BQ9)+SUM(AJ9:AN9) -> 28670.276 | AK9: =-Вводные!H24 -> -1540 | AL9: =-Вводные!H25 -> -121 | AO9: =(BB9+BJ9+BR9)+SUM(AP9:AT9) -> 34312.219 | AQ9: =-Вводные!I24 -> -1650 | AR9: =-Вводные!I25 -> -132 | AV9: 0 | AW9: 0 | AX9: 0 | AY9: 0 | AZ9: 0 | BA9: 0 | BB9: 0 | BD9: 15000 | BE9: 15125.26 | BF9: 17999.059 | BG9: 21418.88 | BH9: 25488.468 | BI9: 30331.276 | BJ9: 36094.219 | BL9: 0 | BM9: 0 | BN9: 0 | BO9: 0 | BP9: 0 | BQ9: 0 | BR9: 0 | BT9: 0 | BU9: 0 | BV9: 0 | BW9: 0 | BX9: 0 | BY9: 0 | BZ9: 0
A10: Денежные средства, полученные за услуги трейдинговой площадки | B10: =(AV10+BD10+BL10) -> 23700 | I10: =(AW10+BE10+BM10) -> 24565 | P10: =(AX10+BF10+BN10) -> 29797.345 | W10: =(AY10+BG10+BO10) -> 37246.681 | AC10: =(AZ10+BH10+BP10) -> 47675.752 | AI10: =BA10+BI10+BQ10 -> 63408.75 | AO10: =BB10+BJ10+BR10 -> 85601.813 | AV10: 0 | AW10: 0 | AX10: 0 | AY10: 0 | AZ10: 0 | BA10: 0 | BB10: 0 | BD10: 0 | BE10: 0 | BF10: 0 | BG10: 0 | BH10: 0 | BI10: 0 | BJ10: 0 | BL10: 23700 | BM10: 24565 | BN10: 29797.345 | BO10: 37246.681 | BP10: 47675.752 | BQ10: 63408.75 | BR10: 85601.813 | BT10: 0 | BU10: 0 | BV10: 0 | BW10: 0 | BX10: 0 | BY10: 0 | BZ10: 0
A11: Денежные средства, полученные за услуги бронирования | B11: =(AV11+BD11+BL11) -> 0 | I11: =(AW11+BE11+BM11) -> 0 | P11: =(AX11+BF11+BN11) -> 0 | W11: =(AY11+BG11+BO11) -> 0 | AC11: =(AZ11+BH11+BP11) -> 0 | AI11: =BA11+BI11+BQ11 -> 0 | AO11: =BB11+BJ11+BR11 -> 0 | AV11: 0 | AW11: 0 | AX11: 0 | AY11: 0 | AZ11: 0 | BA11: 0 | BB11: 0 | BD11: 0 | BE11: 0 | BF11: 0 | BG11: 0 | BH11: 0 | BI11: 0 | BJ11: 0 | BL11: 0 | BM11: 0 | BN11: 0 | BO11: 0 | BP11: 0 | BQ11: 0 | BR11: 0 | BT11: 8500 | BU11: 7911.8422 | BV11: 8873.1311 | BW11: 9951.2165 | BX11: 11160.289 | BY11: 12516.264 | BZ11: 14036.991
A12: Прочие расчёты с контрагентами | B12: =(AV12+BD12+BL12) -> 12955 | I12: =(AW12+BE12+BM12) -> 10326.448 | P12: =(AX12+BF12+BN12) -> 1839.1248 | W12: =(AY12+BG12+BO12) -> 3170.4631 | AC12: =(AZ12+BH12+BP12) -> 3971.8981 | AI12: =BA12+BI12+BQ12 -> 4065.4334 | AO12: =BB12+BJ12+BR12 -> 3693.6494 | AV12: 4250 | AW12: 2270 | AX12: 289.8 | AY12: 304.29 | AZ12: 319.5045 | BA12: 335.47973 | BB12: 352.25371 | BD12: 7450 | BE12: 7503.4483 | BF12: 941.34483 | BG12: 1025.9843 | BH12: 1118.5655 | BI12: 1219.8539 | BJ12: 1330.6899 | BL12: 1255 | BM12: 553 | BN12: 607.98 | BO12: 1840.1888 | BP12: 2533.8281 | BQ12: 2510.0998 | BR12: 2010.7058 | BT12: 1510 | BU12: 1354.8153 | BV12: 1015.6 | BW12: 1016.224 | BX12: 1016.873 | BY12: 1017.5479 | BZ12: 1018.2498
A13: Выбытия, всего: | B13: =SUM(B14:B17) -> -92192.25 | I13: =SUM(I14:I17) -> -93669.665 | P13: =SUM(P14:P17) -> -102387.53 | W13: =SUM(W14:W17) -> -116457.9 | AC13: =SUM(AC14:AC17) -> -132882.75 | AI13: =SUM(AI14:AI17) -> -152504.01 | AO13: =SUM(AO14:AO17) -> -176037.01 | AV13: -34004 | AW13: -34332.417 | AX13: -40279.119 | AY13: -45213.628 | AZ13: -50610.769 | BA13: -56535.462 | BB13: -63046.011 | BD13: =SUM(BD14:BD17) -> -37981.25 | BE13: =SUM(BE14:BE17) -> -38292.249 | BF13: =SUM(BF14:BF17) -> -38270.448 | BG13: =SUM(BG14:BG17) -> -43706.831 | BH13: =SUM(BH14:BH17) -> -50004.152 | BI13: =SUM(BI14:BI17) -> -57305.744 | BJ13: =SUM(BJ14:BJ17) -> -65779.409 | BL13: =SUM(BL14:BL17) -> -22726 | BM13: =SUM(BM14:BM17) -> -23564 | BN13: =SUM(BN14:BN17) -> -26594.559 | BO13: =SUM(BO14:BO17) -> -30421.697 | BP13: =SUM(BP14:BP17) -> -35279.798 | BQ13: =SUM(BQ14:BQ17) -> -41802.546 | BR13: =SUM(BR14:BR17) -> -50479.167 | BT13: =SUM(BT14:BT17) -> -6614.25 | BU13: =SUM(BU14:BU17) -> -6564.3439 | BV13: =SUM(BV14:BV17) -> -6905.8137 | BW13: =SUM(BW14:BW17) -> -7433.1955 | BX13: =SUM(BX14:BX17) -> -8010.1589 | BY13: =SUM(BY14:BY17) -> -8642.0314 | BZ13: =SUM(BZ14:BZ17) -> -9334.7529
A14: Расчёты с персоналом | B14: =(AV14+BD14+BL14) -> -57760 | I14: =(AW14+BE14+BM14) -> -57971.647 | P14: =(AX14+BF14+BN14) -> -64524.393 | W14: =(AY14+BG14+BO14) -> -71691.614 | AC14: =(AZ14+BH14+BP14) -> -79542.964 | AI14: =BA14+BI14+BQ14 -> -88157.166 | AO14: =BB14+BJ14+BR14 -> -97623.289 | AV14: -21110 | AW14: -21096.08 | AX14: -23921.845 | AY14: -26917.155 | AZ14: -30092.185 | BA14: -33457.716 | BB14: -37025.179 | BD14: -20600 | BE14: -20620.567 | BF14: -23345.098 | BG14: -26452.511 | BH14: -29998.431 | BI14: -34046.701 | BJ14: -38670.608 | BL14: -16050 | BM14: -16255 | BN14: -17257.45 | BO14: -18321.947 | BP14: -19452.348 | BQ14: -20652.749 | BR14: -21927.502 | BT14: -4980 | BU14: -5012.7578 | BV14: -5238.3319 | BW14: -5474.0568 | BX14: -5720.3894 | BY14: -5977.8069 | BZ14: -6246.8082
A15: Оплата маркетинговых и коммерческих расходов | B15: =(AV15+BD15+BL15) -> -15000 | I15: =(AW15+BE15+BM15) -> -15338.189 | P15: =(AX15+BF15+BN15) -> -17073.35 | W15: =(AY15+BG15+BO15) -> -18740.989 | AC15: =(AZ15+BH15+BP15) -> -20593.794 | AI15: =BA15+BI15+BQ15 -> -22654.071 | AO15: =BB15+BJ15+BR15 -> -25129.228 | AV15: -3800 | AW15: -3767 | AX15: -4278.245 | AY15: -4548.9038 | AZ15: -4803.1085 | BA15: -5029.617 | BB15: -5214.1513 | BD15: -6800 | BE15: -6871.1894 | BF15: -7249.1048 | BG15: -7647.8056 | BH15: -8068.4349 | BI15: -8512.1988 | BJ15: -8980.3698 | BL15: -4400 | BM15: -4700 | BN15: -5546 | BO15: -6544.28 | BP15: -7722.2504 | BQ15: -9112.2555 | BR15: -10934.707 | BT15: -360 | BU15: -366.66667 | BV15: -399.66667 | BW15: -435.63667 | BX15: -474.84397 | BY15: -517.57992 | BZ15: -564.16212
A16: Уплаченный налог на прибыль | B16: =(AV16+BD16+BL16) -> -2680.25 | I16: =(AW16+BE16+BM16) -> -3125.7003 | P16: =(AX16+BF16+BN16) -> -10050.153 | W16: =(AY16+BG16+BO16) -> -13836.113 | AC16: =(AZ16+BH16+BP16) -> -18837.906 | AI16: =BA16+BI16+BQ16 -> -25741.153 | AO16: =BB16+BJ16+BR16 -> -34897.252 | AV16: -686 | AW16: -971.25 | AX16: -5741.5578 | AY16: -7087.4789 | AZ16: -8716.8078 | BA16: -10694.122 | BB16: -13079.729 | BD16: -1795.25 | BE16: -1945.4503 | BF16: -3389.046 | BG16: -4646.4689 | BH16: -6188.2129 | BI16: -8071.9078 | BJ16: -10366.436 | BL16: -199 | BM16: -209 | BN16: -919.54875 | BO16: -2102.1654 | BP16: -3932.8853 | BQ16: -6975.1228 | BR16: -11451.087 | BT16: -551.25 | BU16: -387.32667 | BV16: -542.5409 | BW16: -721.5795 | BX16: -927.57224 | BY16: -1164.0409 | BZ16: -1434.9477
A17: Прочие расчёты с контрагентами | B17: =(AV17+BD17+BL17)+SUM(C17:H17) -> -16752 | C17: =Вводные!C23 -> 110 | D17: =Вводные!C24 -> 1100 | E17: =Вводные!C25 -> 77 | F17: =Вводные!C26 -> 22 | G17: =Вводные!C27 -> 1210 | I17: =(AW17+BE17+BM17)+SUM(J17:O17) -> -17234.129 | J17: =Вводные!C23 -> 110 | K17: =Вводные!C24 -> 1100 | L17: =Вводные!C25 -> 77 | M17: =Вводные!D26 -> 22 | N17: =Вводные!D27 -> 1210 | P17: =(AX17+BF17+BN17)+SUM(Q17:U17) -> -10739.63 | Q17: =Вводные!E23 -> 115.5 | R17: =Вводные!E24 -> 1210 | S17: =Вводные!E25 -> 88 | T17: =Вводные!E26 -> 23.1 | U17: =Вводные!E27 -> 1320 | W17: =(AY17+BG17+BO17)+SUM(X17:AB17) -> -12189.184 | X17: =Вводные!F23 -> 121 | Y17: =Вводные!F24 -> 1320 | Z17: =Вводные!F25 -> 99 | AA17: =Вводные!F26 -> 24.255 | AB17: =Вводные!F27 -> 1320 | AC17: =(AZ17+BH17+BP17)+SUM(AD17:AH17) -> -13908.088 | AD17: =Вводные!G23 -> 126.5 | AE17: =Вводные!G24 -> 1430 | AF17: =Вводные!G25 -> 110 | AG17: =Вводные!G26 -> 25.46775 | AH17: =Вводные!G27 -> 1320 | AI17: =(BA17+BI17+BQ17)+SUM(AJ17:AN17) -> -15951.621 | AJ17: =Вводные!H23 -> 132 | AK17: =Вводные!H24 -> 1540 | AL17: =Вводные!H25 -> 121 | AM17: =Вводные!H26 -> 26.741138 | AN17: =Вводные!H27 -> 1320 | AO17: =(BB17+BJ17+BR17)+SUM(AP17:AT17) -> -18387.239 | AP17: =Вводные!I23 -> 137.5 | AQ17: =Вводные!I24 -> 1650 | AR17: =Вводные!I25 -> 132 | AS17: =Вводные!I26 -> 28.078194 | AT17: =Вводные!I27 -> 1320 | AV17: -8408 | AW17: -8498.0867 | AX17: -6337.471 | AY17: -6660.0902 | AZ17: -6998.6679 | BA17: -7354.0074 | BB17: -7726.9516 | BD17: -8786 | BE17: -8855.042 | BF17: -4287.1986 | BG17: -4960.0456 | BH17: -5749.0732 | BI17: -6674.9363 | BJ17: -7761.9951 | BL17: -2077 | BM17: -2400 | BN17: -2871.56 | BO17: -3453.3036 | BP17: -4172.3143 | BQ17: -5062.4188 | BR17: -6165.871 | BT17: -723 | BU17: -797.59278 | BV17: -725.27427 | BW17: -801.92257 | BX17: -887.35329 | BY17: -982.60369 | BZ17: -1088.8349
A18: Сальдо денежных средств по текущей деятельности: | B18: =B6+B13 -> 35893.75 | I18: =I6+I13 -> 33419.811 | P18: =P6+P13 -> 36960.767 | W18: =W6+W13 -> 49938.909 | AC18: =AC6+AC13 -> 66104.477 | AI18: =AI6+AI13 -> 87286.37 | AO18: =AO6+AO13 -> 114782.45 | AV18: 21696 | AW18: 19439.583 | AX18: 19334.118 | AY18: 23423.508 | AZ18: 28419.426 | BA18: 34464.862 | BB18: 41741.015 | BD18: =BD6+BD13 -> 11968.75 | BE18: =BE6+BE13 -> 12426.228 | BF18: =BF6+BF13 -> 13815.883 | BG18: =BG6+BG13 -> 17850.227 | BH18: =BH6+BH13 -> 22755.269 | BI18: =BI6+BI13 -> 28705.204 | BJ18: =BJ6+BJ13 -> 35908.085 | BL18: =BL6+BL13 -> 2229 | BM18: =BM6+BM13 -> 1554 | BN18: =BN6+BN13 -> 3810.7662 | BO18: =BO6+BO13 -> 8665.1735 | BP18: =BP6+BP13 -> 14929.782 | BQ18: =BQ6+BQ13 -> 24116.304 | BR18: =BR6+BR13 -> 37133.352 | BT18: =BT6+BT13 -> 3395.75 | BU18: =BU6+BU13 -> 2702.3137 | BV18: =BV6+BV13 -> 2982.9173 | BW18: =BW6+BW13 -> 3534.2449 | BX18: =BX6+BX13 -> 4167.0034 | BY18: =BY6+BY13 -> 4891.7809 | BZ18: =BZ6+BZ13 -> 5720.4875
A20: Инвестиционная деятельность: | AI20: =BA20+BI20+BQ20 -> 0 | AO20: =BB20+BJ20+BR20 -> 0
A21: Дивиденды полученные | B21: =(AV21+BD21+BL21) -> 1373 | I21: =(AW21+BE21+BM21) -> 1372.7123 | P21: =(AX21+BF21+BN21) -> 1372.7123 | W21: =(AY21+BG21+BO21) -> 1372.7123 | AC21: =AZ21+BH21+BP21 -> 1372.7123 | AI21: =BA21+BI21+BQ21 -> 1372.7123 | AO21: =BB21+BJ21+BR21 -> 1372.7123 | AV21: 109 | AW21: 109 | AX21: 109 | AY21: 109 | AZ21: 109 | BA21: 109 | BB21: 109 | BD21: 469 | BE21: 468.71228 | BF21: 468.71228 | BG21: 468.71228 | BH21: 468.71228 | BI21: 468.71228 | BJ21: 468.71228 | BL21: 795 | BM21: 795 | BN21: 795 | BO21: 795 | BP21: 795 | BQ21: 795 | BR21: 795 | BT21: 0 | BU21: 0 | BV21: 0 | BW21: 0 | BX21: 0 | BY21: 0 | BZ21: 0
A22: Проценты полученные | B22: =(AV22+BD22+BL22) -> 0 | I22: =(AW22+BE22+BM22) -> 0 | P22: =(AX22+BF22+BN22) -> 0 | W22: =(AY22+BG22+BO22) -> 0 | AC22: =AZ22+BH22+BP22 -> 0 | AI22: =BA22+BI22+BQ22 -> 0 | AO22: =BB22+BJ22+BR22 -> 0 | AV22: 0 | AW22: 0 | AX22: 0 | AY22: 0 | AZ22: 0 | BA22: 0 | BB22: 0 | BD22: 0 | BE22: 0 | BF22: 0 | BG22: 0 | BH22: 0 | BI22: 0 | BJ22: 0 | BL22: 0 | BM22: 0 | BN22: 0 | BO22: 0 | BP22: 0 | BQ22: 0 | BR22: 0 | BT22: 0 | BU22: 0 | BV22: 0 | BW22: 0 | BX22: 0 | BY22: 0 | BZ22: 0
A23: Проценты уплаченные | B23: =(AV23+BD23+BL23) -> -51 | I23: =(AW23+BE23+BM23) -> -51 | P23: =(AX23+BF23+BN23) -> -51 | W23: =(AY23+BG23+BO23) -> 0 | AC23: =AZ23+BH23+BP23 -> 0 | AI23: =BA23+BI23+BQ23 -> 0 | AO23: =BB23+BJ23+BR23 -> 0 | AV23: -51 | AW23: -51 | AX23: -51 | AY23: 0 | AZ23: 0 | BA23: 0 | BB23: 0 | BD23: 0 | BE23: 0 | BF23: 0 | BG23: 0 | BH23: 0 | BI23: 0 | BJ23: 0 | BL23: 0 | BM23: 0 | BN23: 0 | BO23: 0 | BP23: 0 | BQ23: 0 | BR23: 0 | BT23: 0 | BU23: 0 | BV23: 0 | BW23: 0 | BX23: 0 | BY23: 0 | BZ23: 0
A24: Сальдо денежных средств по инвестиционной деятельности: | B24: =SUM(B21:B23) -> 1322 | I24: =SUM(I21:I23) -> 1321.7123 | P24: =SUM(P21:P23) -> 1321.7123 | W24: =SUM(W21:W23) -> 1372.7123 | AC24: =SUM(AC21:AC23) -> 1372.7123 | AI24: =SUM(AI20:AI23) -> 1372.7123 | AO24: =SUM(AO20:AO23) -> 1372.7123 | AV24: 58 | AW24: 58 | AX24: 58 | AY24: 109 | AZ24: 109 | BA24: 109 | BB24: 109 | BD24: =SUM(BD21:BD23) -> 469 | BE24: =SUM(BE21:BE23) -> 468.71228 | BF24: =SUM(BF21:BF23) -> 468.71228 | BG24: =SUM(BG21:BG23) -> 468.71228 | BH24: =SUM(BH21:BH23) -> 468.71228 | BI24: =SUM(BI21:BI23) -> 468.71228 | BJ24: =SUM(BJ21:BJ23) -> 468.71228 | BL24: =SUM(BL21:BL23) -> 795 | BM24: =SUM(BM21:BM23) -> 795 | BN24: =SUM(BN21:BN23) -> 795 | BO24: =SUM(BO21:BO23) -> 795 | BP24: =SUM(BP21:BP23) -> 795 | BQ24: =SUM(BQ21:BQ23) -> 795 | BR24: =SUM(BR21:BR23) -> 795 | BT24: =SUM(BT21:BT23) -> 0 | BU24: =SUM(BU21:BU23) -> 0 | BV24: =SUM(BV21:BV23) -> 0 | BW24: =SUM(BW21:BW23) -> 0 | BX24: =SUM(BX21:BX23) -> 0 | BY24: =SUM(BY21:BY23) -> 0 | BZ24: =SUM(BZ21:BZ23) -> 0
A27: Финансовая деятельность:
A28: Денежные средства, полученные по кредиту (тело) | B28: =(AV28+BD28+BL28)+H28 -> 0 | H28: =-Вводные!C32 -> -600 | I28: =(AW28+BE28+BM28)+O28 -> 0 | O28: =-Вводные!D33 -> -600 | P28: =(AX28+BF28+BN28)+V28 -> 0 | V28: =-Вводные!E32 -> -600 | W28: =(AY28+BG28+BO28) -> 0 | AC28: =AZ28+BH28+BP28 -> 0 | AI28: =BA28+BI28+BQ28 -> 0 | AO28: =BB28+BJ28+BR28 -> 0 | AV28: 600 | AW28: 600 | AX28: 600 | AY28: 0 | AZ28: 0 | BA28: 0 | BB28: 0 | BD28: 0 | BE28: 0 | BF28: 0 | BG28: 0 | BH28: 0 | BI28: 0 | BJ28: 0 | BL28: 0 | BM28: 0 | BN28: 0 | BO28: 0 | BP28: 0 | BQ28: 0 | BR28: 0 | BT28: 0 | BU28: 0 | BV28: 0 | BW28: 0 | BX28: 0 | BY28: 0 | BZ28: 0
A29: Денежные средства, уплаченные за аренду | B29: =(AV29+BD29+BL29) -> -2191 | I29: =(AW29+BE29+BM29) -> -2190.7038 | P29: =(AX29+BF29+BN29) -> -2309.6184 | W29: =(AY29+BG29+BO29) -> -2435.022 | AC29: =AZ29+BH29+BP29 -> -2567.2706 | AI29: =BA29+BI29+BQ29 -> -2706.7398 | AO29: =BB29+BJ29+BR29 -> -2853.826 | AV29: -864 | AW29: -863.83333 | AX29: -907.025 | AY29: -952.37625 | AZ29: -999.99506 | BA29: -1049.9948 | BB29: -1102.4946 | BD29: -778 | BE29: -777.8705 | BF29: -820.65338 | BG29: -865.78931 | BH29: -913.40773 | BI29: -963.64515 | BJ29: -1016.6456 | BL29: -549 | BM29: -549 | BN29: -581.94 | BO29: -616.8564 | BP29: -653.86778 | BQ29: -693.09985 | BR29: -734.68584 | BT29: -200 | BU29: -200 | BV29: -208 | BW29: -216.32 | BX29: -224.9728 | BY29: -233.97171 | BZ29: -243.33058
A30: Денежные средства, уплаченные по кредиту (тело) | B30: =(AV30+BD30+BL30)+H30 -> -1154 | H30: =Вводные!C33 -> 600 | I30: =(AW30+BE30+BM30)+O30 -> -1154 | O30: =Вводные!D32 -> 600 | P30: =(AX30+BF30+BN30)+V30 -> -1154 | V30: =Вводные!E32 -> 600 | W30: =(AY30+BG30+BO30) -> 0 | AC30: =AZ30+BH30+BP30 -> 0 | AI30: =BA30+BI30+BQ30 -> 0 | AO30: =BB30+BJ30+BR30 -> 0 | AV30: -1154 | AW30: -1154 | AX30: -1154 | AY30: 0 | AZ30: 0 | BA30: 0 | BB30: 0 | BD30: 0 | BE30: 0 | BF30: 0 | BG30: 0 | BH30: 0 | BI30: 0 | BJ30: 0 | BL30: -600 | BM30: -600 | BN30: -600 | BO30: 0 | BP30: 0 | BQ30: 0 | BR30: 0 | BT30: 0 | BU30: 0 | BV30: 0 | BW30: 0 | BX30: 0 | BY30: 0 | BZ30: 0
A31: Денежные средства, уплаченные в качестве дивидендов | B31: =(AV31+BD31+BL31) -> -7000 | I31: =(AW31+BE31+BM31) -> -10000 | P31: =(AX31+BF31+BN31) -> -22000 | W31: =(AY31+BG31+BO31) -> -30000 | AC31: =AZ31+BH31+BP31 -> -45000 | AI31: =BA31+BI31+BQ31 -> -68000 | AO31: =BB31+BJ31+BR31 -> -97000 | AV31: -7000 | AW31: -10000 | AX31: -16000 | AY31: -20000 | AZ31: -25000 | BA31: -32000 | BB31: -39000 | BD31: 0 | BE31: 0 | BF31: -6000 | BG31: -10000 | BH31: -16000 | BI31: -22000 | BJ31: -29000 | BL31: 0 | BM31: 0 | BN31: 0 | BO31: 0 | BP31: -4000 | BQ31: -14000 | BR31: -29000 | BT31: 0 | BU31: 0 | BV31: 0 | BW31: 0 | BX31: 0 | BY31: 0 | BZ31: -1000
A32: Сальдо денежных средств по финансовой деятельности: | B32: =SUM(B28:B31) -> -10345 | I32: =SUM(I28:I31) -> -13344.704 | P32: =SUM(P28:P31) -> -25463.618 | W32: =SUM(W28:W31) -> -32435.022 | AC32: =SUM(AC28:AC31) -> -47567.271 | AI32: =SUM(AI28:AI31) -> -70706.74 | AO32: =SUM(AO28:AO31) -> -99853.826 | AV32: -8418 | AW32: -11417.833 | AX32: -17461.025 | AY32: -20952.376 | AZ32: -25999.995 | BA32: -33049.995 | BB32: -40102.495 | BD32: =SUM(BD28:BD31) -> -778 | BE32: =SUM(BE28:BE31) -> -777.8705 | BF32: =SUM(BF28:BF31) -> -6820.6534 | BG32: =SUM(BG28:BG31) -> -10865.789 | BH32: =SUM(BH28:BH31) -> -16913.408 | BI32: =SUM(BI28:BI31) -> -22963.645 | BJ32: =SUM(BJ28:BJ31) -> -30016.646 | BL32: =SUM(BL28:BL31) -> -1149 | BM32: =SUM(BM28:BM31) -> -1149 | BN32: =SUM(BN28:BN31) -> -1181.94 | BO32: =SUM(BO28:BO31) -> -616.8564 | BP32: =SUM(BP28:BP31) -> -4653.8678 | BQ32: =SUM(BQ28:BQ31) -> -14693.1 | BR32: =SUM(BR28:BR31) -> -29734.686 | BT32: =SUM(BT28:BT31) -> -200 | BU32: =SUM(BU28:BU31) -> -200 | BV32: =SUM(BV28:BV31) -> -208 | BW32: =SUM(BW28:BW31) -> -216.32 | BX32: =SUM(BX28:BX31) -> -224.9728 | BY32: =SUM(BY28:BY31) -> -233.97171 | BZ32: =SUM(BZ28:BZ31) -> -1243.3306
A33: Денежный поток, итого | B33: =B18+B24+B32 -> 26870.75 | I33: =I18+I24+I32 -> 21396.819 | P33: =P18+P24+P32 -> 12818.861 | W33: =W18+W24+W32 -> 18876.599 | AC33: =AC18+AC24+AC32 -> 19909.918 | AI33: =AI18+AI24+AI32 -> 17952.342 | AO33: =AO18+AO24+AO32 -> 16301.338 | AV33: 13336 | AW33: 8079.75 | AX33: 1931.0934 | AY33: 2580.1321 | AZ33: 2528.4305 | BA33: 1523.8676 | BB33: 1747.5206 | BD33: =BD18+BD24+BD32 -> 11659.75 | BE33: =BE18+BE24+BE32 -> 12117.069 | BF33: =BF18+BF24+BF32 -> 7463.9414 | BG33: =BG18+BG24+BG32 -> 7453.1498 | BH33: =BH18+BH24+BH32 -> 6310.5739 | BI33: =BI18+BI24+BI32 -> 6210.2708 | BJ33: =BJ18+BJ24+BJ32 -> 6360.1518 | BL33: =BL18+BL24+BL32 -> 1875 | BM33: =BM18+BM24+BM32 -> 1200 | BN33: =BN18+BN24+BN32 -> 3423.8262 | BO33: =BO18+BO24+BO32 -> 8843.3171 | BP33: =BP18+BP24+BP32 -> 11070.914 | BQ33: =BQ18+BQ24+BQ32 -> 10218.204 | BR33: =BR18+BR24+BR32 -> 8193.6661 | BT33: =BT18+BT24+BT32 -> 3195.75 | BU33: =BU18+BU24+BU32 -> 2502.3137 | BV33: =BV18+BV24+BV32 -> 2774.9173 | BW33: =BW18+BW24+BW32 -> 3317.9249 | BX33: =BX18+BX24+BX32 -> 3942.0306 | BY33: =BY18+BY24+BY32 -> 4657.8092 | BZ33: =BZ18+BZ24+BZ32 -> 4477.1569
A35: Остаток денежных средств на конец периода | B35: =B3+B33 -> 27944.15 | I35: =I3+I33 -> 22519.308 | P35: =P3+P33 -> 35338.17 | W35: =W3+W33 -> 54214.769 | AC35: =AC3+AC33 -> 74124.687 | AI35: =AI3+AI33 -> 92077.029 | AO35: =AO3+AO33 -> 108378.37 | AV35: 13345 | AW35: 8742.35 | AX35: 10673.443 | AY35: 13253.576 | AZ35: 15782.006 | BA35: 17305.874 | BB35: 19053.394 | BD35: =BD3+BD33 -> 12450.95 | BE35: =BE3+BE33 -> 12536.758 | BF35: =BF3+BF33 -> 20000.7 | BG35: =BG3+BG33 -> 27453.85 | BH35: =BH3+BH33 -> 33764.424 | BI35: =BI3+BI33 -> 39974.694 | BJ35: =BJ3+BJ33 -> 46334.846 | BL35: =BL3+BL33 -> 2148.2 | BM35: =BM3+BM33 -> 1240.2 | BN35: =BN3+BN33 -> 4664.0262 | BO35: =BO3+BO33 -> 13507.343 | BP35: =BP3+BP33 -> 24578.257 | BQ35: =BQ3+BQ33 -> 34796.461 | BR35: =BR3+BR33 -> 42990.127 | BT35: =BT3+BT33 -> 3339.75 | BU35: =BU3+BU33 -> 2946.3509 | BV35: =BV3+BV33 -> 5721.2682 | BW35: =BW3+BW33 -> 9039.1932 | BX35: =BX3+BX33 -> 12981.224 | BY35: =BY3+BY33 -> 17639.033 | BZ35: =BZ3+BZ33 -> 22116.19

Sheet ОПУ
A1: Отчёт о прибылях и убытках, тыс. руб. | B1: Консолидация по группе | AZ1: А | BH1: Б | BP1: В | BX1: Г
B2: 2025 план | C2: ВГО 1 | D2: ВГО 2 | E2: ВГО 3 | F2: ВГО 4 | G2: ВГО 5 | H2: Доля ЧП от Г | I2: 2025 факт | J2: ВГО 1 | K2: ВГО 2 | L2: ВГО 3 | M2: ВГО 4 | N2: ВГО 5 | O2: Доля ЧП от Г | P2: 2026 | Q2: ВГО 1 | R2: ВГО 2 | S2: ВГО 3 | T2: ВГО 4 | U2: ВГО 5 | V2: Доля ЧП от Г | W2: 2027 | X2: ВГО 1 | Y2: ВГО 2 | Z2: ВГО 3 | AA2: ВГО 4 | AB2: ВГО 5 | AC2: Доля ЧП от Г | AD2: 2028 | AE2: ВГО 1 | AF2: ВГО 2 | AG2: ВГО 3 | AH2: ВГО 4 | AI2: ВГО 5 | AJ2: Доля ЧП от Г | AK2: 2029 | AL2: ВГО 1 | AM2: ВГО 2 | AN2: ВГО 3 | AO2: ВГО 4 | AP2: ВГО 5 | AQ2: Доля ЧП от Г | AR2: 2030 | AS2: ВГО 1 | AT2: ВГО 2 | AU2: ВГО 3 | AV2: ВГО 4 | AW2: ВГО 5 | AX2: Доля ЧП от Г | AZ2: 2025 план | BA2: 2025 факт | BB2: 2026 | BC2: 2027 | BD2: 2028 | BE2: 2029 | BF2: 2030 | BH2: 2025 план | BI2: 2025 факт | BJ2: 2026 | BK2: 2027 | BL2: 2028 | BM2: 2029 | BN2: 2030 | BP2: 2025 план | BQ2: 2025 факт | BR2: 2026 | BS2: 2027 | BT2: 2028 | BU2: 2029 | BV2: 2030 | BX2: 2025 план | BY2: 2025 факт | BZ2: 2026 | CA2: 2027 | CB2: 2028 | CC2: 2029 | CD2: 2030
A3: Выручка от реализации | B3: =SUM(B4:B8) -> 115131 | I3: =SUM(I4:I8) -> 116763.03 | P3: =SUM(P4:P8) -> 137509.17 | W3: =SUM(W4:W8) -> 163226.35 | AD3: =SUM(AD4:AD8) -> 195015.33 | AK3: =SUM(AK4:AK8) -> 235724.95 | AR3: =SUM(AR4:AR8) -> 287125.81 | AZ3: 51450 | BA3: 51502 | BB3: 59323.437 | BC3: 68332.847 | BD3: 78710.69 | BE3: 90664.845 | BF3: 104434.77 | BH3: 42500 | BI3: 43215.028 | BJ3: 51144.985 | BK3: 60531.073 | BL3: 71640.855 | BM3: 84791.094 | BN3: 100356.8 | BP3: 23700 | BQ3: 24565 | BR3: 29797.345 | BS3: 37246.681 | BT3: 47675.752 | BU3: 63408.75 | BV3: 85601.813 | BX3: 8500 | BY3: 7911.8422 | BZ3: 8873.1311 | CA3: 9951.2165 | CB3: 11160.289 | CC3: 12516.264 | CD3: 14036.991
A4: Комиссии за обработку платежей и переводов | B4: =(AZ4+BH4+BP4)+SUM(C4:H4) -> 51318 | C4: =-Вводные!D23 -> -110 | F4: =-Вводные!D26 -> -22 | I4: =(BA4+BI4+BQ4)+SUM(J4:N4) -> 51370 | J4: =-Вводные!D23 -> -110 | M4: =-Вводные!D26 -> -22 | P4: =(BB4+BJ4+BR4)+SUM(Q4:V4) -> 59184.837 | Q4: =-Вводные!E23 -> -115.5 | T4: =-Вводные!E26 -> -23.1 | W4: =(BC4+BK4+BS4)+SUM(X4:AC4) -> 68187.592 | X4: =-Вводные!F23 -> -121 | AA4: =-Вводные!F26 -> -24.255 | AD4: =(BD4+BL4+BT4)+SUM(AE4:AJ4) -> 78558.722 | AE4: =-Вводные!G23 -> -126.5 | AH4: =-Вводные!G26 -> -25.46775 | AK4: =(BE4+BM4+BU4)+SUM(AL4:AQ4) -> 90506.104 | AL4: =-Вводные!H23 -> -132 | AO4: =-Вводные!H26 -> -26.741138 | AR4: =(BF4+BN4+BV4)+SUM(AS4:AX4) -> 104269.19 | AS4: =-Вводные!I23 -> -137.5 | AV4: =-Вводные!I26 -> -28.078194 | AZ4: 51450 | BA4: 51502 | BB4: 59323.437 | BC4: 68332.847 | BD4: 78710.69 | BE4: 90664.845 | BF4: 104434.77 | BH4: 0 | BI4: 0 | BJ4: 0 | BK4: 0 | BL4: 0 | BM4: 0 | BN4: 0 | BP4: 0 | BQ4: 0 | BR4: 0 | BS4: 0 | BT4: 0 | BU4: 0 | BV4: 0 | BX4: 0 | BY4: 0 | BZ4: 0 | CA4: 0 | CB4: 0 | CC4: 0 | CD4: 0
A5: Разработка программного обеспечения | B5: =(AZ5+BH5+BP5)+SUM(C5:H5) -> 26290 | G5: =-Вводные!D27 -> -1210 | I5: =(BA5+BI5+BQ5)+SUM(J5:O5) -> 26879.768 | N5: =-Вводные!D27 -> -1210 | P5: =(BB5+BJ5+BR5)+SUM(Q5:V5) -> 31825.926 | U5: =-Вводные!E27 -> -1320 | W5: =(BC5+BK5+BS5)+SUM(X5:AC5) -> 37792.193 | AB5: =-Вводные!F27 -> -1320 | AD5: =(BD5+BL5+BT5)+SUM(AE5:AJ5) -> 44832.388 | AI5: =-Вводные!G27 -> -1320 | AK5: =(BE5+BM5+BU5)+SUM(AL5:AQ5) -> 53139.818 | AP5: =-Вводные!H27 -> -1320 | AR5: =(BF5+BN5+BV5)+SUM(AS5:AX5) -> 62942.585 | AW5: =-Вводные!I27 -> -1320 | AZ5: 0 | BA5: 0 | BH5: 27500 | BI5: 28089.768 | BJ5: 33145.926 | BK5: 39112.193 | BL5: 46152.388 | BM5: 54459.818 | BN5: 64262.585 | BP5: 0 | BQ5: 0 | BR5: 0 | BS5: 0 | BT5: 0 | BU5: 0 | BV5: 0 | BX5: 0 | BY5: 0 | BZ5: 0 | CA5: 0 | CB5: 0 | CC5: 0 | CD5: 0
A6: Аутсорсинговые услуги | B6: =(AZ6+BH6+BP6)+SUM(C6:H6) -> 13823 | D6: =-Вводные!D24 -> -1100 | E6: =-Вводные!D25 -> -77 | I6: =(BA6+BI6+BQ6)+SUM(J6:O6) -> 13948.26 | K6: =-Вводные!D24 -> -1100 | L6: =-Вводные!D25 -> -77 | P6: =(BB6+BJ6+BR6)+SUM(Q6:V6) -> 16701.059 | R6: =-Вводные!E24 -> -1210 | S6: =-Вводные!E25 -> -88 | W6: =(BC6+BK6+BS6)+SUM(X6:AC6) -> 19999.88 | Y6: =-Вводные!F24 -> -1320 | Z6: =-Вводные!F25 -> -99 | AD6: =(BD6+BL6+BT6)+SUM(AE6:AJ6) -> 23948.468 | AF6: =-Вводные!G24 -> -1430 | AG6: =-Вводные!G25 -> -110 | AK6: =(BE6+BM6+BU6)+SUM(AL6:AQ6) -> 28670.276 | AM6: =-Вводные!H24 -> -1540 | AN6: =-Вводные!H25 -> -121 | AR6: =(BF6+BN6+BV6)+SUM(AS6:AX6) -> 34312.219 | AT6: =-Вводные!I24 -> -1650 | AU6: =-Вводные!I25 -> -132 | AZ6: 0 | BA6: 0 | BH6: 15000 | BI6: 15125.26 | BJ6: 17999.059 | BK6: 21418.88 | BL6: 25488.468 | BM6: 30331.276 | BN6: 36094.219 | BP6: 0 | BQ6: 0 | BR6: 0 | BS6: 0 | BT6: 0 | BU6: 0 | BV6: 0 | BX6: 0 | BY6: 0 | BZ6: 0 | CA6: 0 | CB6: 0 | CC6: 0 | CD6: 0
A7: Комиссии трейдинговой площадки | B7: =(AZ7+BH7+BP7)+SUM(C7:H7) -> 23700 | I7: =(BA7+BI7+BQ7)+SUM(J7:O7) -> 24565 | P7: =(BB7+BJ7+BR7)+SUM(Q7:V7) -> 29797.345 | W7: =(BC7+BK7+BS7)+SUM(X7:AC7) -> 37246.681 | AD7: =(BD7+BL7+BT7)+SUM(AE7:AJ7) -> 47675.752 | AK7: =(BE7+BM7+BU7)+SUM(AL7:AQ7) -> 63408.75 | AR7: =(BF7+BN7+BV7) -> 85601.813 | AZ7: 0 | BA7: 0 | BH7: 0 | BI7: 0 | BJ7: 0 | BK7: 0 | BL7: 0 | BM7: 0 | BN7: 0 | BP7: 23700 | BQ7: 24565 | BR7: 29797.345 | BS7: 37246.681 | BT7: 47675.752 | BU7: 63408.75 | BV7: 85601.813 | BX7: 0 | BY7: 0 | BZ7: 0 | CA7: 0 | CB7: 0 | CC7: 0 | CD7: 0
A8: Комиссии за услуги бронирования | B8: =(AZ8+BH8+BP8)+SUM(C8:H8) -> 0 | I8: =(BA8+BI8+BQ8)+SUM(J8:O8) -> 0 | P8: =(BB8+BJ8+BR8)+SUM(Q8:V8) -> 0 | W8: =(BC8+BK8+BS8) -> 0 | AD8: =(BD8+BL8+BT8) -> 0 | AK8: =(BE8+BM8+BU8) -> 0 | AR8: =(BF8+BN8+BV8) -> 0 | AZ8: 0 | BA8: 0 | BH8: 0 | BI8: 0 | BJ8: 0 | BK8: 0 | BL8: 0 | BM8: 0 | BN8: 0 | BP8: 0 | BQ8: 0 | BR8: 0 | BS8: 0 | BT8: 0 | BU8: 0 | BV8: 0 | BX8: 8500 | BY8: 7911.8422 | BZ8: 8873.1311 | CA8: 9951.2165 | CB8: 11160.289 | CC8: 12516.264 | CD8: 14036.991
A9: Себестоимость реализации: | B9: =SUM(B10:B12) -> 50290 | I9: =SUM(I10:I12) -> 50750.063 | P9: =SUM(P10:P12) -> 57356.908 | W9: =SUM(W10:W12) -> 64843.676 | AD9: =SUM(AD10:AD12) -> 73210.956 | AK9: =SUM(AK10:AK12) -> 82588.037 | AR9: =SUM(AR10:AR12) -> 93126.421 | AZ9: 17350 | BA9: 17365 | BB9: 19930.159 | BC9: 22647.391 | BD9: 25525.727 | BE9: 28574.739 | BF9: 31804.564 | BH9: 20300 | BI9: 20311.063 | BJ9: 23322.149 | BK9: 26794.159 | BL9: 30798.762 | BM9: 35418.879 | BN9: 40750.465 | BP9: 14950 | BQ9: 15384 | BR9: 16634.6 | BS9: 18042.126 | BT9: 19636.466 | BU9: 21454.42 | BV9: 23541.392 | BX9: 2350 | BY9: 2421.0911 | BZ9: 2569.643 | CA9: 2729.6538 | CB9: 2902.213 | CC9: 3088.5279 | CD9: 3289.9373
A10: Прямые расходы на персонал | B10: =(AZ10+BH10+BP10)+SUM(C10:H10) -> 41960 | D10: =-Вводные!D24 -> -1100 | I10: =(BA10+BI10+BQ10)+SUM(J10:O10) -> 42144.562 | K10: =-Вводные!D24 -> -1100 | P10: =(BB10+BJ10+BR10)+SUM(Q10:V10) -> 47630.464 | R10: =-Вводные!E24 -> -1210 | W10: =(BC10+BK10+BS10)+SUM(X10:AC10) -> 53668.304 | Y10: =-Вводные!F24 -> -1320 | AD10: =(BD10+BL10+BT10)+SUM(AE10:AJ10) -> 60323.627 | AF10: =-Вводные!G24 -> -1430 | AK10: =(BE10+BM10+BU10)+SUM(AL10:AQ10) -> 67670.773 | AM10: =-Вводные!H24 -> -1540 | AR10: =(BF10+BN10+BV10)+SUM(AS10:AX10) -> 75794.136 | AT10: =-Вводные!I24 -> -1650 | AZ10: 13710 | BA10: 13690.913 | BB10: 16072.368 | BC10: 18596.71 | BD10: 21272.513 | BE10: 24108.864 | BF10: 27115.395 | BH10: 16000 | BI10: 16013.648 | BJ10: 18415.696 | BK10: 21178.05 | BL10: 24354.757 | BM10: 28007.971 | BN10: 32209.167 | BP10: 13350 | BQ10: 13540 | BR10: 14352.4 | BS10: 15213.544 | BT10: 16126.357 | BU10: 17093.938 | BV10: 18119.574 | BX10: 1800 | BY10: 1834.98 | BZ10: 1917.5541 | CA10: 2003.844 | CB10: 2094.017 | CC10: 2188.2478 | CD10: 2286.7189
A11: Оборудование, лицензии и программное обеспечение | B11: =(AZ11+BH11+BP11)+SUM(C11:H11) -> 6640 | G11: =-Вводные!D27 -> -1210 | I11: =(BA11+BI11+BQ11)+SUM(J11:O11) -> 6977.7896 | N11: =-Вводные!D27 -> -1210 | P11: =(BB11+BJ11+BR11)+SUM(Q11:V11) -> 8009.5555 | U11: =-Вводные!E27 -> -1320 | W11: =(BC11+BK11+BS11)+SUM(X11:AC11) -> 9364.4122 | AB11: =-Вводные!F27 -> -1320 | AD11: =(BD11+BL11+BT11)+SUM(AE11:AJ11) -> 10977.136 | AI11: =-Вводные!G27 -> -1320 | AK11: =(BE11+BM11+BU11)+SUM(AL11:AQ11) -> 12902.392 | AP11: =-Вводные!H27 -> -1320 | AR11: =(BF11+BN11+BV11)+SUM(AS11:AX11) -> 15206.988 | AW11: =-Вводные!I27 -> -1320 | AZ11: 3450 | BA11: 3484.7242 | BB11: 3658.9604 | BC11: 3841.9085 | BD11: 4034.0039 | BE11: 4235.7041 | BF11: 4447.4893 | BH11: 2900 | BI11: 2979.0654 | BJ11: 3515.595 | BK11: 4148.7537 | BL11: 4895.9443 | BM11: 5777.7038 | BN11: 6818.2683 | BP11: 1500 | BQ11: 1724 | BR11: 2155 | BS11: 2693.75 | BT11: 3367.1875 | BU11: 4208.9844 | BV11: 5261.2305 | BX11: 500 | BY11: 531.66667 | BZ11: 595.46667 | CA11: 666.92267 | CB11: 746.95339 | CC11: 836.58779 | CD11: 936.97833
A12: Прочие расходы | B12: =(AZ12+BH12+BP12)+SUM(C12:H12) -> 1690 | I12: =(BA12+BI12+BQ12)+SUM(J12:O12) -> 1627.7118 | P12: =(BB12+BJ12+BR12)+SUM(Q12:V12) -> 1716.8892 | W12: =(BC12+BK12+BS12) -> 1810.9599 | AD12: =(BD12+BL12+BT12) -> 1910.193 | AK12: =(BE12+BM12+BU12) -> 2014.8722 | AR12: =(BF12+BN12+BV12) -> 2125.2968 | AZ12: 190 | BA12: 189.36247 | BB12: 198.83059 | BC12: 208.77212 | BD12: 219.21073 | BE12: 230.17127 | BF12: 241.67983 | BH12: 1400 | BI12: 1318.3494 | BJ12: 1390.8586 | BK12: 1467.3558 | BL12: 1548.0604 | BM12: 1633.2037 | BN12: 1723.0299 | BP12: 100 | BQ12: 120 | BR12: 127.2 | BS12: 134.832 | BT12: 142.92192 | BU12: 151.49724 | BV12: 160.58707 | BX12: 50 | BY12: 54.444444 | BZ12: 56.622222 | CA12: 58.887111 | CB12: 61.242596 | CC12: 63.692299 | CD12: 66.239991
A13: Валовая прибыль | B13: =B3-B9 -> 64841 | I13: =I3-I9 -> 66012.965 | P13: =P3-P9 -> 80152.259 | W13: =W3-W9 -> 98382.67 | AD13: =AD3-AD9 -> 121804.37 | AK13: =AK3-AK9 -> 153136.91 | AR13: =AR3-AR9 -> 193999.39 | AZ13: 34100 | BA13: 34137 | BB13: 39393.278 | BC13: 45685.456 | BD13: 53184.963 | BE13: 62090.106 | BF13: 72630.208 | BH13: 22200 | BI13: 22903.965 | BJ13: 27822.836 | BK13: 33736.914 | BL13: 40842.093 | BM13: 49372.216 | BN13: 59606.339 | BP13: 8750 | BQ13: 9181 | BR13: 13162.745 | BS13: 19204.555 | BT13: 28039.286 | BU13: 41954.331 | BV13: 62060.421 | BX13: 6150 | BY13: 5490.7511 | BZ13: 6303.4881 | CA13: 7221.5627 | CB13: 8258.0763 | CC13: 9427.7365 | CD13: 10747.053
A14: Операционные расходы | B14: =SUM(B15:B19) -> 38032 | I14: =SUM(I15:I19) -> 38479.669 | P14: =SUM(P15:P19) -> 41615.091 | W14: =SUM(W15:W19) -> 44770.252 | AD14: =SUM(AD15:AD19) -> 48203.285 | AK14: =SUM(AK15:AK19) -> 51942.29 | AR14: =SUM(AR15:AR19) -> 56200.83 | AZ14: 15614 | BA14: 15549 | BB14: 16723.397 | BC14: 17694.808 | BD14: 18689.512 | BE14: 19698.538 | BF14: 20710.006 | BH14: 13878 | BI14: 14001.669 | BJ14: 14840.865 | BK14: 15731.053 | BL14: 16675.378 | BM14: 17677.179 | BN14: 18740.005 | BP14: 8749 | BQ14: 9138 | BR14: 10277.43 | BS14: 11588.646 | BT14: 13100.363 | BU14: 14846.314 | BV14: 17048.397 | BX14: 3945 | BY14: 3944.4444 | BZ14: 4136.4444 | CA14: 4338.4894 | CB14: 4551.1619 | CC14: 4775.0825 | CD14: 5010.9125
A15: Расходы на персонал | B15: =(AZ15+BH15+BP15)+SUM(C15:H15) -> 14623 | E15: =-Вводные!D25 -> -77 | I15: =(BA15+BI15+BQ15)+SUM(J15:O15) -> 14650.085 | L15: =-Вводные!D25 -> -77 | P15: =(BB15+BJ15+BR15)+SUM(Q15:V15) -> 15595.929 | S15: =-Вводные!E25 -> -88 | W15: =(BC15+BK15+BS15)+SUM(X15:AC15) -> 16604.31 | Z15: =-Вводные!F25 -> -99 | AD15: =(BD15+BL15+BT15)+SUM(AE15:AJ15) -> 17679.337 | AG15: =-Вводные!G25 -> -110 | AK15: =(BE15+BM15+BU15)+SUM(AL15:AQ15) -> 18825.394 | AN15: =-Вводные!H25 -> -121 | AR15: =(BF15+BN15+BV15)+SUM(AS15:AX15) -> 20047.153 | AU15: =-Вводные!I25 -> -132 | AZ15: 7400 | BA15: 7405.1667 | BB15: 7849.4767 | BC15: 8320.4453 | BD15: 8819.672 | BE15: 9348.8523 | BF15: 9909.7834 | BH15: 4600 | BI15: 4606.9184 | BJ15: 4929.4027 | BK15: 5274.4609 | BL15: 5643.6731 | BM15: 6038.7303 | BN15: 6461.4414 | BP15: 2700 | BQ15: 2715 | BR15: 2905.05 | BS15: 3108.4035 | BT15: 3325.9917 | BU15: 3558.8112 | BV15: 3807.9279 | BX15: 3180 | BY15: 3177.7778 | BZ15: 3320.7778 | CA15: 3470.2128 | CB15: 3626.3724 | CC15: 3789.5591 | CD15: 3960.0893
A16: Аренда | B16: =(AZ16+BH16+BP16)+SUM(C16:H16) -> 2191 | I16: =(BA16+BI16+BQ16)+SUM(J16:O16) -> 2190.7038 | P16: =(BB16+BJ16+BR16)+SUM(Q16:V16) -> 2309.6184 | W16: =(BC16+BK16+BS16) -> 2435.022 | AD16: =(BD16+BL16+BT16) -> 2567.2706 | AK16: =(BE16+BM16+BU16) -> 2706.7398 | AR16: =(BF16+BN16+BV16) -> 2853.826 | AZ16: 864 | BA16: 863.83333 | BB16: 907.025 | BC16: 952.37625 | BD16: 999.99506 | BE16: 1049.9948 | BF16: 1102.4946 | BH16: 778 | BI16: 777.8705 | BJ16: 820.65338 | BK16: 865.78931 | BL16: 913.40773 | BM16: 963.64515 | BN16: 1016.6456 | BP16: 549 | BQ16: 549 | BR16: 581.94 | BS16: 616.8564 | BT16: 653.86778 | BU16: 693.09985 | BV16: 734.68584 | BX16: 200 | BY16: 200 | BZ16: 208 | CA16: 216.32 | CB16: 224.9728 | CC16: 233.97171 | CD16: 243.33058
A17: Реклама и маркетинг | B17: =(AZ17+BH17+BP17)+SUM(C17:H17) -> 15000 | I17: =(BA17+BI17+BQ17)+SUM(J17:O17) -> 15338.189 | P17: =(BB17+BJ17+BR17)+SUM(Q17:V17) -> 17073.35 | W17: =(BC17+BK17+BS17) -> 18740.989 | AD17: =(BD17+BL17+BT17) -> 20593.794 | AK17: =(BE17+BM17+BU17) -> 22654.071 | AR17: =(BF17+BN17+BV17) -> 25129.228 | AZ17: 3800 | BA17: 3767 | BB17: 4278.245 | BC17: 4548.9038 | BD17: 4803.1085 | BE17: 5029.617 | BF17: 5214.1513 | BH17: 6800 | BI17: 6871.1894 | BJ17: 7249.1048 | BK17: 7647.8056 | BL17: 8068.4349 | BM17: 8512.1988 | BN17: 8980.3698 | BP17: 4400 | BQ17: 4700 | BR17: 5546 | BS17: 6544.28 | BT17: 7722.2504 | BU17: 9112.2555 | BV17: 10934.707 | BX17: 360 | BY17: 366.66667 | BZ17: 399.66667 | CA17: 435.63667 | CB17: 474.84397 | CC17: 517.57992 | CD17: 564.16212
A18: Оборудование, лицензии и программное обеспечение | B18: =(AZ18+BH18+BP18)+SUM(C18:H18) -> 4850 | I18: =(BA18+BI18+BQ18)+SUM(J18:O18) -> 4910.741 | P18: =(BB18+BJ18+BR18)+SUM(Q18:V18) -> 5174.2968 | W18: =(BC18+BK18+BS18) -> 5452.0725 | AD18: =(BD18+BL18+BT18) -> 5744.8397 | AK18: =(BE18+BM18+BU18) -> 6053.4118 | AR18: =(BF18+BN18+BV18) -> 6378.6466 | AZ18: 2350 | BA18: 2331 | BB18: 2447.55 | BC18: 2569.9275 | BD18: 2698.4239 | BE18: 2833.3451 | BF18: 2975.0123 | BH18: 1500 | BI18: 1555.741 | BJ18: 1641.3068 | BK18: 1731.5786 | BL18: 1826.8155 | BM18: 1927.2903 | BN18: 2033.2913 | BP18: 1000 | BQ18: 1024 | BR18: 1085.44 | BS18: 1150.5664 | BT18: 1219.6004 | BU18: 1292.7764 | BV18: 1370.343 | BX18: 200 | BY18: 196 | BZ18: 203.84 | CA18: 211.9936 | CB18: 220.47334 | CC18: 229.29228 | CD18: 238.46397
A19: Прочие расходы | B19: =(AZ19+BH19+BP19)+SUM(C19:H19) -> 1368 | C19: =-Вводные!D23 -> -110 | F19: =-Вводные!D26 -> -22 | I19: =(BA19+BI19+BQ19)+SUM(J19:O19) -> 1389.9497 | J19: =-Вводные!D23 -> -110 | L19: =-Вводные!D26 -> -22 | P19: =(BB19+BJ19+BR19)+SUM(Q19:V19) -> 1461.8969 | Q19: =-Вводные!E23 -> -115.5 | S19: =-Вводные!E26 -> -23.1 | W19: =(BC19+BK19+BS19)+SUM(X19:AC19) -> 1537.8588 | X19: =-Вводные!F23 -> -121 | Z19: =-Вводные!F26 -> -24.255 | AD19: =(BD19+BL19+BT19)+SUM(AE19:AJ19) -> 1618.0442 | AE19: =-Вводные!G23 -> -126.5 | AG19: =-Вводные!G26 -> -25.46775 | AK19: =(BE19+BM19+BU19)+SUM(AL19:AQ19) -> 1702.6732 | AL19: =-Вводные!H23 -> -132 | AN19: =-Вводные!H26 -> -26.741138 | AR19: =(BF19+BN19+BV19)+SUM(AS19:AX19) -> 1791.9771 | AS19: =-Вводные!I23 -> -137.5 | AU19: =-Вводные!I26 -> -28.078194 | AZ19: 1200 | BA19: 1182 | BB19: 1241.1 | BC19: 1303.155 | BD19: 1368.3128 | BE19: 1436.7284 | BF19: 1508.5648 | BH19: 200 | BI19: 189.94969 | BJ19: 200.39692 | BK19: 211.41875 | BL19: 223.04679 | BM19: 235.31436 | BN19: 248.25665 | BP19: 100 | BQ19: 150 | BR19: 159 | BS19: 168.54 | BT19: 178.6524 | BU19: 189.37154 | BV19: 200.73384 | BX19: 5 | BY19: 4 | BZ19: 4.16 | CA19: 4.3264 | CB19: 4.499456 | CC19: 4.6794342 | CD19: 4.8666116
A20: Операционная прибыль | B20: =B13-B14 -> 26809 | I20: =I13-I14 -> 27533.296 | P20: =P13-P14 -> 38537.168 | W20: =W13-W14 -> 53612.418 | AD20: =AD13-AD14 -> 73601.089 | AK20: =AK13-AK14 -> 101194.62 | AR20: =AR13-AR14 -> 137798.56 | AZ20: 18486 | BA20: 18588 | BB20: 22669.881 | BC20: 27990.648 | BD20: 34495.45 | BE20: 42391.569 | BF20: 51920.202 | BH20: 8322 | BI20: 8902.2957 | BJ20: 12981.972 | BK20: 18005.861 | BL20: 24166.715 | BM20: 31695.037 | BN20: 40866.334 | BP20: 1 | BQ20: 43 | BR20: 2885.315 | BS20: 7615.909 | BT20: 14938.923 | BU20: 27108.016 | BV20: 45012.024 | BX20: 2205 | BY20: 1546.3067 | BZ20: 2167.0436 | CA20: 2883.0732 | CB20: 3706.9144 | CC20: 4652.6541 | CD20: 5736.1408
A21: Внереализационные доходы | B21: =SUM(B22:B24) -> 2274.125 | I21: =SUM(I22:I24) -> 2205.3063 | P21: =SUM(P22:P24) -> 2370.2791 | W21: =SUM(W22:W24) -> 2558.0176 | AD21: =SUM(AD22:AD24) -> 2771.4082 | AK21: =SUM(AK22:AK24) -> 3013.6936 | AR21: =SUM(AR22:AR24) -> 3288.5167 | AZ21: 359 | BA21: 385 | BB21: 398.8 | BC21: 413.29 | BD21: 428.5045 | BE21: 444.47973 | BF21: 461.25371 | BH21: 619 | BI21: 668.71228 | BJ21: 679.71228 | BK21: 691.31728 | BL21: 703.56055 | BM21: 716.47721 | BN21: 730.10428 | BP21: 800 | BQ21: 803 | BR21: 803.48 | BS21: 803.9888 | BT21: 804.52813 | BU21: 805.09982 | BV21: 805.7058 | BX21: 10 | BY21: 15 | BZ21: 15.6 | CA21: 16.224 | CB21: 16.87296 | CC21: 17.547878 | CD21: 18.249794
A22: Инвестиционный доход | B22: =(AZ22+BH22+BP22)+SUM(C22:H22) -> 1373 | I22: =(BA22+BI22+BQ22)+SUM(J22:O22) -> 1372.7123 | P22: =(BB22+BJ22+BR22)+SUM(Q22:V22) -> 1372.7123 | W22: =(BC22+BK22+BS22) -> 1372.7123 | AD22: =(BD22+BL22+BT22) -> 1372.7123 | AK22: =(BE22+BM22+BU22) -> 1372.7123 | AR22: =(BF22+BN22+BV22) -> 1372.7123 | AZ22: 109 | BA22: 109 | BB22: 109 | BC22: 109 | BD22: 109 | BE22: 109 | BF22: 109 | BH22: 469 | BI22: 468.71228 | BJ22: 468.71228 | BK22: 468.71228 | BL22: 468.71228 | BM22: 468.71228 | BN22: 468.71228 | BP22: 795 | BQ22: 795 | BR22: 795 | BS22: 795 | BT22: 795 | BU22: 795 | BV22: 795 | BX22: 0 | BY22: 0 | BZ22: 0 | CA22: 0 | CB22: 0 | CC22: 0 | CD22: 0
A23: Прочие доходы | B23: =(AZ23+BH23+BP23)+SUM(C23:H23) -> 405 | I23: =(BA23+BI23+BQ23)+SUM(J23:O23) -> 484 | P23: =(BB23+BJ23+BR23)+SUM(Q23:V23) -> 509.28 | W23: =(BC23+BK23+BS23) -> 535.8838 | AD23: =(BD23+BL23+BT23) -> 563.8809 | AK23: =(BE23+BM23+BU23) -> 593.34447 | AR23: =(BF23+BN23+BV23) -> 624.35152 | AZ23: 250 | BA23: 276 | BB23: 289.8 | BC23: 304.29 | BD23: 319.5045 | BE23: 335.47973 | BF23: 352.25371 | BH23: 150 | BI23: 200 | BJ23: 211 | BK23: 222.605 | BL23: 234.84827 | BM23: 247.76493 | BN23: 261.392 | BP23: 5 | BQ23: 8 | BR23: 8.48 | BS23: 8.9888 | BT23: 9.528128 | BU23: 10.099816 | BV23: 10.705805 | BX23: 10 | BY23: 15 | BZ23: 15.6 | CA23: 16.224 | CB23: 16.87296 | CC23: 17.547878 | CD23: 18.249794
A24: Доля прибыли ассоциированной компании | B24: =H24 -> 496.125 | H24: =BX30*30% -> 496.125 | I24: =O24 -> 348.594 | O24: =BY30*30% -> 348.594 | P24: =V24 -> 488.28681 | V24: =BZ30*30% -> 488.28681 | W24: =AC24 -> 649.42155 | AC24: =CA30*30% -> 649.42155 | AD24: =AJ24 -> 834.81501 | AJ24: =CB30*30% -> 834.81501 | AK24: =AQ24 -> 1047.6368 | AQ24: =CC30*30% -> 1047.6368 | AR24: =AX24 -> 1291.4529 | AX24: =CD30*30% -> 1291.4529
A25: Внереализационные расходы | B25: =SUM(B26:B27) -> 186 | I25: =SUM(I26:I27) -> 210 | P25: =SUM(P26:P27) -> 218.55 | W25: =SUM(W26:W27) -> 176.561 | AD25: =SUM(AD26:AD27) -> 186.05792 | AK25: =SUM(AK26:AK27) -> 196.06704 | AR25: =SUM(AR26:AR27) -> 206.61605 | AZ25: 101 | BA25: 100 | BB25: 102.45 | BC25: 54.0225 | BD25: 56.723625 | BE25: 59.559806 | BF25: 62.537797 | BH25: 80 | BI25: 100 | BJ25: 105.5 | BK25: 111.3025 | BL25: 117.42414 | BM25: 123.88247 | BN25: 130.696 | BP25: 5 | BQ25: 10 | BR25: 10.6 | BS25: 11.236 | BT25: 11.91016 | BU25: 12.62477 | BV25: 13.382256 | BX25: 10 | BY25: 12 | BZ25: 12.48 | CA25: 12.9792 | CB25: 13.498368 | CC25: 14.038303 | CD25: 14.599835
A26: Проценты уплаченные (аннуитет, полное погашение долга в конце 2026) | B26: =AZ26+BH26+BP26 -> 51 | I26: =(BA26+BI26+BQ26)+SUM(J26:O26) -> 51 | P26: =(BB26+BJ26+BR26)+SUM(Q26:V26) -> 51 | W26: =(BC26+BK26+BS26) -> 0 | AD26: =(BD26+BL26+BT26) -> 0 | AK26: =(BE26+BM26+BU26) -> 0 | AR26: =(BF26+BN26+BV26) -> 0 | AZ26: 51 | BA26: 51 | BB26: 51 | BC26: 0 | BD26: 0 | BE26: 0 | BF26: 0 | BH26: 0 | BI26: 0 | BJ26: 0 | BK26: 0 | BL26: 0 | BM26: 0 | BN26: 0 | BP26: 0 | BQ26: 0 | BR26: 0 | BS26: 0 | BT26: 0 | BU26: 0 | BV26: 0 | BX26: 0 | BY26: 0 | BZ26: 0 | CA26: 0 | CB26: 0 | CC26: 0 | CD26: 0
A27: Прочие расходы | B27: =AZ27+BH27+BP27 -> 135 | I27: =(BA27+BI27+BQ27)+SUM(J27:O27) -> 159 | P27: =(BB27+BJ27+BR27)+SUM(Q27:V27) -> 167.55 | W27: =(BC27+BK27+BS27) -> 176.561 | AD27: =(BD27+BL27+BT27) -> 186.05792 | AK27: =(BE27+BM27+BU27) -> 196.06704 | AR27: =(BF27+BN27+BV27) -> 206.61605 | AZ27: 50 | BA27: 49 | BB27: 51.45 | BC27: 54.0225 | BD27: 56.723625 | BE27: 59.559806 | BF27: 62.537797 | BH27: 80 | BI27: 100 | BJ27: 105.5 | BK27: 111.3025 | BL27: 117.42414 | BM27: 123.88247 | BN27: 130.696 | BP27: 5 | BQ27: 10 | BR27: 10.6 | BS27: 11.236 | BT27: 11.91016 | BU27: 12.62477 | BV27: 13.382256 | BX27: 10 | BY27: 12 | BZ27: 12.48 | CA27: 12.9792 | CB27: 13.498368 | CC27: 14.038303 | CD27: 14.599835
A28: Прибыль до налогообложения | B28: =B20+B21-B25 -> 28897.125 | I28: =I20+I21-I25 -> 29528.602 | P28: =P20+P21-P25 -> 40688.897 | W28: =W20+W21-W25 -> 55993.874 | AD28: =AD20+AD21-AD25 -> 76186.439 | AK28: =AK20+AK21-AK25 -> 104012.25 | AR28: =AR20+AR21-AR25 -> 140880.46 | AZ28: 18744 | BA28: 18873 | BB28: 22966.231 | BC28: 28349.916 | BD28: 34867.231 | BE28: 42776.489 | BF28: 52318.918 | BH28: 8861 | BI28: 9471.008 | BJ28: 13556.184 | BK28: 18585.876 | BL28: 24752.852 | BM28: 32287.631 | BN28: 41465.743 | BP28: 796 | BQ28: 836 | BR28: 3678.195 | BS28: 8408.6617 | BT28: 15731.541 | BU28: 27900.491 | BV28: 45804.347 | BX28: 2205 | BY28: 1549.3067 | BZ28: 2170.1636 | CA28: 2886.318 | CB28: 3710.289 | CC28: 4656.1637 | CD28: 5739.7907
A29: Налог на прибыль | B29: =AZ29+BH29+BP29 -> 7100.25 | I29: =BA29+BI29+BQ29 -> 7295.002 | P29: =(BB29+BJ29+BR29) -> 10050.153 | W29: =(BC29+BK29+BS29) -> 13836.113 | AD29: =(BD29+BL29+BT29) -> 18837.906 | AK29: =(BE29+BM29+BU29) -> 25741.153 | AR29: =(BF29+BN29+BV29) -> 34897.252 | AZ29: 4686 | BA29: 4718.25 | BB29: 5741.5578 | BC29: 7087.4789 | BD29: 8716.8078 | BE29: 10694.122 | BF29: 13079.729 | BH29: 2215.25 | BI29: 2367.752 | BJ29: 3389.046 | BK29: 4646.4689 | BL29: 6188.2129 | BM29: 8071.9078 | BN29: 10366.436 | BP29: 199 | BQ29: 209 | BR29: 919.54875 | BS29: 2102.1654 | BT29: 3932.8853 | BU29: 6975.1228 | BV29: 11451.087 | BX29: 551.25 | BY29: 387.32667 | BZ29: 542.5409 | CA29: 721.5795 | CB29: 927.57224 | CC29: 1164.0409 | CD29: 1434.9477
A30: Чистая прибыль | B30: =B28-B29 -> 21796.875 | I30: =I28-I29 -> 22233.6 | P30: =P28-P29 -> 30638.744 | W30: =W28-W29 -> 42157.761 | AD30: =AD28-AD29 -> 57348.533 | AK30: =AK28-AK29 -> 78271.095 | AR30: =AR28-AR29 -> 105983.21 | AZ30: 14058 | BA30: 14154.75 | BB30: 17224.673 | BC30: 21262.437 | BD30: 26150.424 | BE30: 32082.366 | BF30: 39239.188 | BH30: 6645.75 | BI30: 7103.256 | BJ30: 10167.138 | BK30: 13939.407 | BL30: 18564.639 | BM30: 24215.724 | BN30: 31099.307 | BP30: 597 | BQ30: 627 | BR30: 2758.6462 | BS30: 6306.4963 | BT30: 11798.656 | BU30: 20925.368 | BV30: 34353.26 | BX30: 1653.75 | BY30: 1161.98 | BZ30: 1627.6227 | CA30: 2164.7385 | CB30: 2782.7167 | CC30: 3492.1228 | CD30: 4304.843
A31: принадлежащей группе | B31: =B30-B32 -> 20893.5 | I31: =I30-I32 -> 21272.474 | P31: =P30-P32 -> 28518.572 | W31: =W30-W32 -> 38241.222 | AD31: =AD30-AD32 -> 50772.607 | AK31: =AK30-AK32 -> 67479.375 | AR31: =AR30-AR32 -> 89131.974
A32: принадлежащей неконтролируещей доли | B32: =(BH30*10%)+(BP30*40%) -> 903.375 | I32: =(BI30*10%)+(BQ30*40%) -> 961.1256 | P32: =(BJ30*10%)+(BR30*40%) -> 2120.1723 | W32: =(BK30*10%)+(BS30*40%) -> 3916.5392 | AD32: =(BL30*10%)+(BT30*40%) -> 6575.9262 | AK32: =(BM30*10%)+(BU30*40%) -> 10791.72 | AR32: =(BN30*10%)+(BV30*40%) -> 16851.235
A33: в т. ч. амортизация | B33: =AZ33+BH33+BP33 -> 4254 | I33: =BA33+BI33+BQ33 -> 4253.8487 | P33: =(BB33+BJ33+BR33) -> 3299.28 | W33: =(BC33+BK33+BS33) -> 4729.3668 | AD33: =(BD33+BL33+BT33) -> 4986.7699 | AK33: =(BE33+BM33+BU33) -> 5258.2299 | AR33: =(BF33+BN33+BV33) -> 5544.517 | AZ33: 1132 | BA33: 1132 | BB33: 1188.6 | BC33: 1248.03 | BD33: 1310.4315 | BE33: 1375.9531 | BF33: 1444.7507 | BH33: 2494 | BI33: 2493.8487 | BJ33: 1445 | BK33: 2775.716 | BL33: 2928.3804 | BM33: 3089.4413 | BN33: 3259.3606 | BP33: 628 | BQ33: 628 | BR33: 665.68 | BS33: 705.6208 | BT33: 747.95805 | BU33: 792.83553 | BV33: 840.40566 | BX33: 142 | BY33: 141.62944 | BZ33: 147.29462 | CA33: 153.18641 | CB33: 159.31386 | CC33: 165.68642 | CD33: 172.31387
A34: EBITDA | B34: =B30+B29+B26-B22+B33 -> 31829.125 | I34: =I30+I29+I26-I22+I33 -> 32460.738 | P34: =P30+P29+P26-P22+P33 -> 42666.465 | W34: =W30+W29+W26-W22+W33 -> 59350.529 | AD34: =AD30+AD29+AD26-AD22+AD33 -> 79800.497 | AK34: =AK30+AK29+AK26-AK22+AK33 -> 107897.77 | AR34: =AR30+AR29+AR26-AR22+AR33 -> 145052.26 | AZ34: 19818 | BA34: 19947 | BB34: 24096.831 | BC34: 29488.946 | BD34: 36068.663 | BE34: 44043.442 | BF34: 53654.668 | BH34: 10886 | BI34: 11496.144 | BJ34: 14532.472 | BK34: 20892.879 | BL34: 27212.52 | BM34: 34908.36 | BN34: 44256.391 | BP34: 629 | BQ34: 669 | BR34: 3548.875 | BS34: 8319.2825 | BT34: 15684.499 | BU34: 27898.327 | BV34: 45849.753 | BX34: 2347 | BY34: 1690.9361 | BZ34: 2317.4582 | CA34: 3039.5044 | CB34: 3869.6028 | CC34: 4821.8501 | CD34: 5912.1046

Sheet Баланс
A1: Управленческий баланс*, тыс. руб. | B1: Консолидация по группе | AZ1: А | BH1: Б | BP1: В | BX1: Г
B2: 2025 план | C2: Неконтролирующая доля меньшиства | D2: Нераспределенная прибыль | E2: Акционерный капитал | F2: Беспроцентный заём | G2: Инвестиции в компанию Г | H2: Инвестиции в дочернии компании | I2: 2025 факт | J2: Без контроля доля меньшиства | K2: Нераспределнная прибыль | L2: Акционерный капитал | M2: Беспроцентный заём | N2: Инвестиции в компанию Г | O2: Инвестиции в дочернии компании | P2: 2026 | Q2: Без контроля доля меньшиства | R2: Нераспределнная прибыль | S2: Акционерный капитал | T2: Беспроцентный заём | U2: Инвестиции в компанию Г | V2: Инвестиции в дочернии компании | W2: 2027 | X2: Без контроля доля меньшиства | Y2: Нераспределнная прибыль | Z2: Акционерный капитал | AA2: Беспроцентный заём | AB2: Инвестиции в компанию Г | AC2: Инвестиции в дочернии компании | AD2: 2028 | AE2: Без контроля доля меньшиства | AF2: Нераспределнная прибыль | AG2: Акционерный капитал | AH2: Беспроцентный заём | AI2: Инвестиции в компанию Г | AJ2: Инвестиции в дочернии компании | AK2: 2029 | AL2: Без контроля доля меньшиства | AM2: Нераспределнная прибыль | AN2: Акционерный капитал | AO2: Беспроцентный заём | AP2: Инвестиции в компанию Г | AQ2: Инвестиции в дочернии компании | AR2: 2030 | AS2: Без контроля доля меньшиства | AT2: Нераспределнная прибыль | AU2: Акционерный капитал | AV2: Беспроцентный заём | AW2: Инвестиции в компанию Г | AX2: Инвестиции в дочернии компании | AZ2: 31.12.25 план | BA2: 31.12.25 факт | BB2: 31.12.26 | BC2: 31.12.27 | BD2: 31.12.28 | BE2: 31.12.29 | BF2: 31.12.30 | BH2: 31.12.25 план | BI2: 31.12.25 факт | BJ2: 31.12.26 | BK2: 31.12.27 | BL2: 31.12.28 | BM2: 31.12.29 | BN2: 31.12.30 | BP2: 31.12.25 план | BQ2: 31.12.25 факт | BR2: 31.12.26 | BS2: 31.12.27 | BT2: 31.12.28 | BU2: 31.12.29 | BV2: 31.12.30 | BX2: 31.12.25 план | BY2: 31.12.25 факт | BZ2: 31.12.26 | CA2: 31.12.27 | CB2: 31.12.28 | CC2: 31.12.29 | CD2: 31.12.30
A3: АКТИВЫ | B3: =B4+B13 -> 133757.88 | I3: =I4+I13 -> 131344.52 | P3: =P4+P13 -> 140159.11 | W3: =W4+W13 -> 154951.45 | AD3: =AD4+AD13 -> 170708 | AK3: =AK4+AK13 -> 184451.18 | AR3: =AR4+AR13 -> 196203.69 | AZ3: =AZ4+AZ13 -> 66691.8 | BA3: =BA4+BA13 -> 64982.35 | BB3: =BB4+BB13 -> 65053.023 | BC3: =BC4+BC13 -> 66315.46 | BD3: =BD4+BD13 -> 67465.884 | BE3: =BE4+BE13 -> 67548.25 | BF3: =BF4+BF13 -> 67787.438 | BH3: 53576.95 | BI3: 53768.641 | BJ3: 58666.124 | BK3: 63408.91 | BL3: 66857.266 | BM3: 70045.078 | BN3: 73213.683 | BP3: 16911.2 | BQ3: 16086.2 | BR3: 18844.346 | BS3: 26982.043 | BT3: 37304.998 | BU3: 46730.367 | BV3: 54083.627 | BX3: 4995.75 | BY3: 4633.1731 | BZ3: 7260.7958 | CA3: 10425.534 | CB3: 14208.251 | CC3: 18700.374 | CD3: 23005.217
A4: Внеоборотные активы: | B4: =SUM(B5:B8) -> 98313.725 | I4: =SUM(I5:I8) -> 101225.42 | P4: =SUM(P5:P8) -> 97228.421 | W4: =SUM(W5:W8) -> 93148.476 | AD4: =SUM(AD5:AD8) -> 88996.521 | AK4: =SUM(AK5:AK8) -> 84785.928 | AR4: =SUM(AR5:AR8) -> 80232.864 | AZ4: =SUM(AZ5:AZ8) -> 51046.8 | BA4: =SUM(BA5:BA8) -> 53846 | BB4: =SUM(BB5:BB8) -> 52057.4 | BC4: =SUM(BC5:BC8) -> 50809.37 | BD4: =SUM(BD5:BD8) -> 49498.939 | BE4: =SUM(BE5:BE8) -> 48122.985 | BF4: =SUM(BF5:BF8) -> 46678.235 | BH4: 35926 | BI4: 36026.097 | BJ4: 33395.087 | BK4: 30619.371 | BL4: 27690.99 | BM4: 24601.549 | BN4: 21342.189 | BP4: 14763 | BQ4: 14846 | BR4: 14180.32 | BS4: 13474.699 | BT4: 12726.741 | BU4: 11933.906 | BV4: 11093.5 | BX4: 1556 | BY4: 1545.7111 | BZ4: 1398.4165 | CA4: 1245.2301 | CB4: 1085.9162 | CC4: 920.2298 | CD4: 747.91593
A5: Основные средства | B5: =(AZ5+BH5+BP5) -> 47888.8 | I5: =BA5+BI5+BQ5 -> 47551.903 | P5: =BB5+BJ5+BR5 -> 45842.69 | W5: =BC5+BK5+BS5 -> 43698.147 | AD5: =BD5+BL5+BT5 -> 41281.946 | AK5: =BE5+BM5+BU5 -> 38850.514 | AR5: =BF5+BN5+BV5 -> 36603.729 | AZ5: 36499.8 | BA5: 36163 | BB5: 35721.818 | BC5: 34810.267 | BD5: 33593.846 | BE5: 32330.861 | BF5: 31224.22 | BH5: 3826 | BI5: 3825.9034 | BJ5: 3067.8814 | BK5: 2310.5331 | BL5: 1554.6225 | BM5: 799.99908 | BN5: 45.545514 | BP5: 7563 | BQ5: 7563 | BR5: 7052.991 | BS5: 6577.3473 | BT5: 6133.4774 | BU5: 5719.6542 | BV5: 5333.9634 | BX5: 926 | BY5: 925.15556 | BZ5: 778.74482 | CA5: 626.4043 | CB5: 467.89994 | CC5: 302.98822 | CD5: 131.41574
A6: Нематериальные активы | B6: =(AZ6+BH6+BP6) -> 48090 | I6: =BA6+BI6+BQ6 -> 51423.194 | P6: =BB6+BJ6+BR6 -> 48047.116 | W6: =BC6+BK6+BS6 -> 45462.293 | AD6: =BD6+BL6+BT6 -> 42891.724 | AK6: =BE6+BM6+BU6 -> 40064.926 | AR6: =BF6+BN6+BV6 -> 36767.194 | AZ6: 9990 | BA6: 13126 | BB6: 11778.582 | BC6: 11442.103 | BD6: 11348.093 | BE6: 11235.125 | BF6: 10897.014 | BH6: 31600 | BI6: 31700.194 | BJ6: 29827.205 | BK6: 27808.838 | BL6: 25636.368 | BM6: 23301.55 | BN6: 20796.643 | BP6: 6500 | BQ6: 6597 | BR6: 6441.329 | BS6: 6211.3519 | BT6: 5907.2637 | BU6: 5528.2514 | BV6: 5073.5366 | BX6: 30 | BY6: 20.555556 | BZ6: 19.671667 | CA6: 18.825785 | CB6: 18.016276 | CC6: 17.241576 | CD6: 16.500189
A7: Финансовые вложения | B7: =(AZ7+BH7+BP7)+G7 -> 1642 | G7: =-Вводные!C32 -> -600 | I7: =BA7+BI7+BQ7+N7 -> 1628 | N7: =G7 -> -600 | P7: =BB7+BJ7+BR7 -> 2228 | W7: =BC7+BK7+BS7 -> 2228 | AD7: =BD7+BL7+BT7 -> 2228 | AK7: =BE7+BM7+BU7 -> 2228 | AR7: =BF7+BN7+BV7 -> 2228 | AZ7: 1042 | BA7: 1042 | BB7: 1042 | BC7: 1042 | BD7: 1042 | BE7: 1042 | BF7: 1042 | BH7: 500 | BI7: 500 | BJ7: 500 | BK7: 500 | BL7: 500 | BM7: 500 | BN7: 500 | BP7: 700 | BQ7: 686 | BR7: 686 | BS7: 686 | BT7: 686 | BU7: 686 | BV7: 686 | BX7: 600 | BY7: 600 | BZ7: 600 | CA7: 600 | CB7: 600 | CC7: 600 | CD7: 600
A8: Инвестиции в дочерние и ассоциированные компании | B8: =SUM(B9:B11) -> 692.925 | I8: =SUM(I9:I11) -> 622.32721 | P8: =SUM(P9:P11) -> 1110.614 | W8: =SUM(W9:W11) -> 1760.0356 | AD8: =SUM(AD9:AD11) -> 2594.8506 | AK8: =SUM(AK9:AK11) -> 3642.4874 | AR8: =SUM(AR9:AR11) -> 4633.9403 | AZ8: 3515 | BA8: 3515 | BB8: 3515 | BC8: 3515 | BD8: 3515 | BE8: 3515 | BF8: 3515 | BH8: 0 | BI8: 0 | BJ8: 0 | BK8: 0 | BL8: 0 | BM8: 0 | BN8: 0 | BP8: 0 | BQ8: 0 | BR8: 0 | BS8: 0 | BT8: 0 | BU8: 0 | BV8: 0 | BX8: 0 | BY8: 0 | BZ8: 0 | CA8: 0 | CB8: 0 | CC8: 0 | CD8: 0
A9: в т. ч. в компанию Б | B9: =(AZ9+BH9+BP9)+SUM(C9:H9) -> 0 | H9: =-B97 -> -2000 | I9: =BA9+BI9+BQ9+O9 -> 0 | O9: =H9 -> -2000 | P9: =BB9+BJ9+BR9+V9 -> 0 | V9: =O9 -> -2000 | W9: =BC9+BK9+AC9 -> 0 | AC9: =V9 -> -2000 | AD9: =BD9+BL9+BT9+AJ9 -> 0 | AJ9: =AC9 -> -2000 | AK9: =BE9+BM9+BU9+AQ9 -> 0 | AQ9: =AJ9 -> -2000 | AR9: =BF9+BN9+BV9+AX9 -> 0 | AX9: =AQ9 -> -2000 | AZ9: 2000 | BA9: 2000 | BB9: 2000 | BC9: 2000 | BD9: 2000 | BE9: 2000 | BF9: 2000 | BH9: 0 | BI9: 0 | BJ9: 0 | BK9: 0 | BL9: 0 | BM9: 0 | BN9: 0 | BP9: 0 | BQ9: 0 | BR9: 0 | BS9: 0 | BT9: 0 | BU9: 0 | BV9: 0 | BX9: 0 | BY9: 0 | BZ9: 0 | CA9: 0 | CB9: 0 | CC9: 0 | CD9: 0
A10: в т. ч. в компанию В | B10: =(AZ10+BH10+BP10)+SUM(C10:H10) -> 0 | H10: =-B98 -> -1500 | I10: =BA10+BI10+BQ10+O10 -> 0 | O10: =H10 -> -1500 | P10: =BB10+BJ10+BR10+V10 -> 0 | V10: =O10 -> -1500 | W10: =BC10+BK10+AC10 -> 0 | AC10: =V10 -> -1500 | AD10: =BD10+BL10+BT10+AJ10 -> 0 | AJ10: =AC10 -> -1500 | AK10: =BE10+BM10+BU10+AQ10 -> 0 | AQ10: =AJ10 -> -1500 | AR10: =BF10+BN10+BV10+AX10 -> 0 | AX10: =AQ10 -> -1500 | AZ10: 1500 | BA10: 1500 | BB10: 1500 | BC10: 1500 | BD10: 1500 | BE10: 1500 | BF10: 1500 | BH10: 0 | BI10: 0 | BJ10: 0 | BK10: 0 | BL10: 0 | BM10: 0 | BN10: 0 | BP10: 0 | BQ10: 0 | BR10: 0 | BS10: 0 | BT10: 0 | BU10: 0 | BV10: 0 | BX10: 0 | BY10: 0 | BZ10: 0 | CA10: 0 | CB10: 0 | CC10: 0 | CD10: 0
A11: в т. ч. в компанию Г | B11: =(AZ11+BH11+BP11)+SUM(C11:H11) -> 692.925 | G11: =B99 -> 692.925 | H11: =-B96 -> -15 | I11: =BA11+BI11+BQ11+O11+N11 -> 622.32721 | N11: =C99 -> 622.32721 | O11: =H11 -> -15 | P11: =U11 -> 1110.614 | U11: =D99 -> 1110.614 | V11: =O11 -> -15 | W11: =BC11+BK11+BS11+AB11+AC11 -> 1760.0356 | AB11: =E99 -> 1760.0356 | AC11: =V11 -> -15 | AD11: =BD11+BL11+BT11+AJ11+AI11 -> 2594.8506 | AI11: =F99 -> 2594.8506 | AJ11: =AC11 -> -15 | AK11: =BE11+BM11+BU11+AQ11+AP11 -> 3642.4874 | AP11: =G99 -> 3642.4874 | AQ11: =AJ11 -> -15 | AR11: =BF11+BN11+BV11+AX11+AW11 -> 4633.9403 | AW11: =H99 -> 4633.9403 | AX11: =AQ11 -> -15 | AZ11: 15 | BA11: 15 | BB11: 15 | BC11: 15 | BD11: 15 | BE11: 15 | BF11: 15 | BH11: 0 | BI11: 0 | BJ11: 0 | BK11: 0 | BL11: 0 | BM11: 0 | BN11: 0 | BP11: 0 | BQ11: 0 | BR11: 0 | BS11: 0 | BT11: 0 | BU11: 0 | BV11: 0 | BX11: 0 | BY11: 0 | BZ11: 0 | CA11: 0 | CB11: 0 | CC11: 0 | CD11: 0
A13: Оборотные активы: | B13: =(AZ13+BH13+BP13) -> 35444.15 | I13: =BA13+BI13+BQ13 -> 30119.094 | P13: =BB13+BJ13+BR13 -> 42930.687 | W13: =BC13+BK13+BS13 -> 61802.972 | AD13: =BD13+BL13+BT13 -> 81711.478 | AK13: =BE13+BM13+BU13 -> 99665.255 | AR13: =BF13+BN13+BV13 -> 115970.83 | AZ13: =SUM(AZ14:AZ15) -> 15645 | BA13: =SUM(BA14:BA15) -> 11136.35 | BB13: =SUM(BB14:BB15) -> 12995.623 | BC13: =SUM(BC14:BC15) -> 15506.09 | BD13: =SUM(BD14:BD15) -> 17966.945 | BE13: =SUM(BE14:BE15) -> 19425.265 | BF13: =SUM(BF14:BF15) -> 21109.204 | BH13: 17650.95 | BI13: 17742.544 | BJ13: 25271.037 | BK13: 32789.539 | BL13: 39166.275 | BM13: 45443.529 | BN13: 51871.494 | BP13: 2148.2 | BQ13: 1240.2 | BR13: 4664.0262 | BS13: 13507.343 | BT13: 24578.257 | BU13: 34796.461 | BV13: 42990.127 | BX13: 3439.75 | BY13: 3087.462 | BZ13: 5862.3793 | CA13: 9180.3043 | CB13: 13122.335 | CC13: 17780.144 | CD13: 22257.301
A14: Дебиторская задолженность | B14: =(AZ14+BH14+BP14) -> 7500 | I14: =BA14+BI14+BQ14 -> 7599.7853 | P14: =BB14+BJ14+BR14 -> 7592.5171 | W14: =BC14+BK14+BS14 -> 7588.2038 | AD14: =BD14+BL14+BT14 -> 7586.7909 | AK14: =BE14+BM14+BU14 -> 7588.2257 | AR14: =BF14+BN14+BV14 -> 7592.4576 | AZ14: 2300 | BA14: 2394 | BB14: 2322.18 | BC14: 2252.5146 | BD14: 2184.9392 | BE14: 2119.391 | BF14: 2055.8093 | BH14: 5200 | BI14: 5205.7853 | BJ14: 5270.3371 | BK14: 5335.6892 | BL14: 5401.8518 | BM14: 5468.8347 | BN14: 5536.6483 | BP14: 0 | BQ14: 0 | BR14: 0 | BS14: 0 | BT14: 0 | BU14: 0 | BV14: 0 | BX14: 100 | BY14: 141.11111 | BZ14: 141.11111 | CA14: 141.11111 | CB14: 141.11111 | CC14: 141.11111 | CD14: 141.11111
A15: Денежные средства | B15: =(AZ15+BH15+BP15) -> 27944.15 | I15: =BA15+BI15+BQ15 -> 22519.308 | P15: =BB15+BJ15+BR15 -> 35338.17 | W15: =BC15+BK15+BS15 -> 54214.769 | AD15: =BD15+BL15+BT15 -> 74124.687 | AK15: =BE15+BM15+BU15 -> 92077.029 | AR15: =BF15+BN15+BV15 -> 108378.37 | AZ15: 13345 | BA15: 8742.35 | BB15: 10673.443 | BC15: 13253.576 | BD15: 15782.006 | BE15: 17305.874 | BF15: 19053.394 | BH15: 12450.95 | BI15: 12536.758 | BJ15: 20000.7 | BK15: 27453.85 | BL15: 33764.424 | BM15: 39974.694 | BN15: 46334.846 | BP15: 2148.2 | BQ15: 1240.2 | BR15: 4664.0262 | BS15: 13507.343 | BT15: 24578.257 | BU15: 34796.461 | BV15: 42990.127 | BX15: 3339.75 | BY15: 2946.3509 | BZ15: 5721.2682 | CA15: 9039.1932 | CB15: 12981.224 | CC15: 17639.033 | CD15: 22116.19
A17: ПАССИВЫ | B17: =B18+B26 -> 133757.88 | I17: =I18+I26 -> 131344.52 | P17: =P18+P26 -> 140159.11 | W17: =W18+W26 -> 154951.45 | AD17: =AD18+AD26 -> 170708 | AK17: =AK18+AK26 -> 184451.18 | AR17: =AR18+AR26 -> 196203.69 | AZ17: =AZ18+AZ26 -> 66691.8 | BA17: =BA18+BA26 -> 64982.35 | BB17: =BB18+BB26 -> 65053.023 | BC17: =BC18+BC26 -> 66315.46 | BD17: =BD18+BD26 -> 67465.884 | BE17: =BE18+BE26 -> 67548.25 | BF17: =BF18+BF26 -> 67787.438 | BH17: 53576.95 | BI17: 53768.641 | BJ17: 58666.124 | BK17: 63408.91 | BL17: 66857.266 | BM17: 70045.078 | BN17: 73213.683 | BP17: 16911.2 | BQ17: 16086.2 | BR17: 18844.346 | BS17: 26982.043 | BT17: 37304.998 | BU17: 46730.367 | BV17: 54083.627 | BX17: 4995.75 | BY17: 4633.1731 | BZ17: 7260.7958 | CA17: 10425.534 | CB17: 14208.251 | CC17: 18700.374 | CD17: 23005.217
A18: Собственные средства: | B18: =B19 -> 103497.88 | I18: =I19 -> 104042.77 | P18: =P19 -> 112681.51 | W18: =W19 -> 124839.27 | AD18: =AD19 -> 137187.81 | AK18: =AK19 -> 147458.9 | AR18: =AR19 -> 156142.11 | AZ18: =AZ19 -> 57401.8 | BA18: =BA19 -> 57951.35 | BB18: =BB19 -> 59176.023 | BC18: =BC19 -> 60438.46 | BD18: =BD19 -> 61588.884 | BE18: =BE19 -> 61671.25 | BF18: =BF19 -> 61910.438 | BH18: 37356.95 | BI18: 37542.891 | BJ18: 41710.029 | BK18: 45649.436 | BL18: 48214.075 | BM18: 50429.798 | BN18: 52529.105 | BP18: 11561.2 | BQ18: 11441.2 | BR18: 14199.846 | BS18: 20506.343 | BT18: 28304.998 | BU18: 35230.367 | BV18: 40583.627 | BX18: 3495.75 | BY18: 3293.3578 | BZ18: 4920.9805 | CA18: 7085.719 | CB18: 9868.4358 | CC18: 13360.558 | CD18: 16665.401
A19: Собственный капитал | B19: =SUM(B20:B25) -> 103497.88 | I19: =SUM(I20:I25) -> 104042.77 | P19: =SUM(P20:P25) -> 112681.51 | W19: =SUM(W20:W25) -> 124839.27 | AD19: =SUM(AD20:AD25) -> 137187.81 | AK19: =SUM(AK20:AK25) -> 147458.9 | AR19: =SUM(AR20:AR25) -> 156142.11 | AZ19: =SUM(AZ20:AZ22) -> 57401.8 | BA19: =SUM(BA20:BA22) -> 57951.35 | BB19: =SUM(BB20:BB22) -> 59176.023 | BC19: =SUM(BC20:BC22) -> 60438.46 | BD19: =SUM(BD20:BD22) -> 61588.884 | BE19: =SUM(BE20:BE22) -> 61671.25 | BF19: =SUM(BF20:BF22) -> 61910.438 | BH19: 37356.95 | BI19: 37542.891 | BJ19: 41710.029 | BK19: 45649.436 | BL19: 48214.075 | BM19: 50429.798 | BN19: 52529.105 | BP19: 11561.2 | BQ19: 11441.2 | BR19: 14199.846 | BS19: 20506.343 | BT19: 28304.998 | BU19: 35230.367 | BV19: 40583.627 | BX19: 3495.75 | BY19: 3293.3578 | BZ19: 4920.9805 | CA19: 7085.719 | CB19: 9868.4358 | CC19: 13360.558 | CD19: 16665.401
A20: Акционерный капитал* | B20: =(AZ20+BH20+BP20)+E20 -> 30001 | E20: =-(B46+B50) -> -27031 | I20: =BA20+BI20+BQ20+L20 -> 30001 | L20: =-(C46+C50) -> -27031.345 | P20: =BB20+BJ20+BR20+S20 -> 30001 | S20: =-(D46+D50) -> -27031.345 | W20: =BC20+BK20+BS20+Z20 -> 30001 | Z20: =-(E46+E50) -> -27031.345 | AD20: =BD20+BL20+BT20+AG20 -> 30001 | AG20: =-(F46+F50) -> -27031.345 | AK20: =BE20+BM20+BU20+AN20 -> 30001 | AN20: =-(G46+G50) -> -27031.345 | AR20: =BF20+BN20+BV20+AU20 -> 30001 | AU20: =-(H46+H50) -> -27031.345 | AZ20: 30001 | BA20: 30001 | BB20: 30001 | BC20: 30001 | BD20: 30001 | BE20: 30001 | BF20: 30001 | BH20: 20030 | BI20: 20030.345 | BJ20: 20030.345 | BK20: 20030.345 | BL20: 20030.345 | BM20: 20030.345 | BN20: 20030.345 | BP20: 7001 | BQ20: 7001 | BR20: 7001 | BS20: 7001 | BT20: 7001 | BU20: 7001 | BV20: 7001 | BX20: 6 | BY20: 5.5555556 | BZ20: 5.5555556 | CA20: 5.5555556 | CB20: 5.5555556 | CC20: 5.5555556 | CD20: 5.5555556
A21: Фонды и резервы | B21: =(AZ21+BH21+BP21) -> 24730 | I21: =BA21+BI21+BQ21+L21 -> 24727.483 | P21: =BB21+BJ21+BR21 -> 24727.483 | W21: =BC21+BK21+BS21 -> 24727.483 | AD21: =BD21+BL21+BT21 -> 24727.483 | AK21: =BE21+BM21+BU21 -> 24727.483 | AR21: =BF21+BN21+BV21 -> 24727.483 | AZ21: 19960 | BA21: 19953 | BB21: 19953 | BC21: 19953 | BD21: 19953 | BE21: 19953 | BF21: 19953 | BH21: 1270 | BI21: 1274.4828 | BJ21: 1274.4828 | BK21: 1274.4828 | BL21: 1274.4828 | BM21: 1274.4828 | BN21: 1274.4828 | BP21: 3500 | BQ21: 3500 | BR21: 3500 | BS21: 3500 | BT21: 3500 | BU21: 3500 | BV21: 3500 | BX21: 1200 | BY21: 1233.3333 | BZ21: 1233.3333 | CA21: 1233.3333 | CB21: 1233.3333 | CC21: 1233.3333 | CD21: 1233.3333
A22: Нераспределённая прибыль | B22: =D22 -> 41933.7 | D22: =B93+(-B68)+(-B63) -> 41933.7 | I22: =K22 -> 42510.965 | K22: =C93+-C63+-C68 -> 42510.965 | P22: =R22 -> 49629.537 | R22: =D93+(-D63)+(-D68) -> 49629.537 | W22: =Y22 -> 58870.759 | Y22: =E93+(-E63)+(-E68) -> 58870.759 | AD22: =AF22 -> 67843.366 | AF22: =F93+(-F63)+(-F68) -> 67843.366 | AK22: =AM22 -> 75122.741 | AM22: =G93+(-G63)+(-G68) -> 75122.741 | AR22: =AT22 -> 81454.715 | AT22: =H93+(-H63)+(-H68) -> 81454.715 | AZ22: =SUM(AZ23:AZ24) -> 7440.8 | BA22: =SUM(BA23:BA24) -> 7997.35 | BB22: =SUM(BB23:BB24) -> 9222.0234 | BC22: =SUM(BC23:BC24) -> 10484.46 | BD22: =SUM(BD23:BD24) -> 11634.884 | BE22: =SUM(BE23:BE24) -> 11717.25 | BF22: =SUM(BF23:BF24) -> 11956.438 | BH22: 16056.95 | BI22: 16238.063 | BJ22: 20405.201 | BK22: 24344.608 | BL22: 26909.247 | BM22: 29124.97 | BN22: 31224.277 | BP22: 1060.2 | BQ22: 940.2 | BR22: 3698.8462 | BS22: 10005.343 | BT22: 17803.998 | BU22: 24729.367 | BV22: 30082.627 | BX22: 2289.75 | BY22: 2054.4689 | BZ22: 3682.0916 | CA22: 5846.8301 | CB22: 8629.5469 | CC22: 12121.67 | CD22: 15426.513
A23: в т. ч. на дату приобретения дочерних и ассоциированных компаний | B23: =(AZ23+BH23+BP23)+D23 -> 0 | D23: =-(B43+B47+B51) -> -1491 | I23: =BA23+BI23+BQ23+K23 -> 0 | K23: =-C43+-C47+-C51 -> -1491.3255 | P23: =BB23+BJ23+BR23+R23 -> 0 | R23: =-(D43+D47+D51) -> -1491.3255 | W23: =BC23+BK23+BS23+Y23 -> 0 | Y23: =-(E43+E47+E51) -> -1491.3255 | AD23: =BD23+BL23+BT23+AF23 -> 0 | AF23: =-(E43+E47+E51) -> -1491.3255 | AK23: =BE23+BM23+BU23+AM23 -> 0 | AM23: =-(G43+G47+G51) -> -1491.3255 | AR23: =BF23+BN23+BV23+AT23 -> 0 | AT23: =-(H43+H47+H51) -> -1491.3255 | AZ23: 917 | BA23: 917.168 | BB23: 917.168 | BC23: 917.168 | BD23: 917.168 | BE23: 917.168 | BF23: 917.168 | BH23: 562 | BI23: 562.15747 | BJ23: 562.15747 | BK23: 562.15747 | BL23: 562.15747 | BM23: 562.15747 | BN23: 562.15747 | BP23: 12 | BQ23: 12 | BR23: 12 | BS23: 12 | BT23: 12 | BU23: 12 | BV23: 12 | BX23: 30 | BY23: 30.044843 | BZ23: 30.044843 | CA23: 30.044843 | CB23: 30.044843 | CC23: 30.044843 | CD23: 30.044843
A24: в т. ч. после приобретения дочерних и ассоциированных компаний | B24: =AZ24+BH24+BP24+D24 -> 0 | D24: =-(AZ24+BH24+BP24) -> -23066.95 | I24: =BA24+BI24+BQ24+K24 -> 0 | K24: =-(BA24+BI24+BQ24) -> -23684.288 | P24: =BB24+BJ24+BR24+R24 -> 0 | R24: =-(BB24+BJ24+BR24) -> -31834.746 | W24: =BC24+BK24+BS24+Y24 -> 0 | Y24: =-(BC24+BK24+BS24) -> -43343.085 | AD24: =BD24+BL24+BT24+AF24 -> 0 | AF24: =-(BD24+BL24+BT24) -> -54856.804 | AK24: =BE24+BM24+BU24+AM24 -> 0 | AM24: =-(BE24+BM24+BU24) -> -64080.262 | AR24: =BF24+BN24+BV24+AT24 -> 0 | AT24: =-(BF24+BN24+BV24) -> -71772.017 | AZ24: 6523.8 | BA24: 7080.182 | BB24: 8304.8554 | BC24: 9567.2922 | BD24: 10717.716 | BE24: 10800.082 | BF24: 11039.27 | BH24: 15494.95 | BI24: 15675.906 | BJ24: 19843.044 | BK24: 23782.451 | BL24: 26347.089 | BM24: 28562.813 | BN24: 30662.12 | BP24: 1048.2 | BQ24: 928.2 | BR24: 3686.8462 | BS24: 9993.3426 | BT24: 17791.998 | BU24: 24717.367 | BV24: 30070.627 | BX24: 2259.75 | BY24: 2024.424 | BZ24: 3652.0467 | CA24: 5816.7852 | CB24: 8599.502 | CC24: 12091.625 | CD24: 15396.468
A25: Неконтролирующая доля меньшинства | B25: =C25 -> 6833.175 | C25: =B83 -> 6833.175 | I25: =J25 -> 6803.3208 | J25: =C83 -> 6803.3208 | P25: =Q25 -> 8323.4931 | Q25: =D83 -> 8323.4931 | W25: =X25 -> 11240.032 | X25: =E83 -> 11240.032 | AD25: =AE25 -> 14615.959 | AE25: =F83 -> 14615.959 | AK25: =AL25 -> 17607.678 | AL25: =G83 -> 17607.678 | AR25: =AS25 -> 19958.913 | AS25: =H83 -> 19958.913
A26: Привлечённые средства: | B26: =B27+B30 -> 30260 | I26: =I27+I30 -> 27301.75 | P26: =BB26+BJ26+BR26 -> 27477.595 | W26: =BC26+BK26+BS26 -> 30112.174 | AD26: =BD26+BL26+BT26 -> 33520.191 | AK26: =BE26+BM26+BU26 -> 36992.28 | AR26: =BF26+BN26+BV26 -> 40061.578 | AZ26: =AZ27+AZ30 -> 9290 | BA26: =BA27+BA30 -> 7031 | BB26: =BB27+BB30 -> 5877 | BC26: =BC27+BC30 -> 5877 | BD26: =BD27+BD30 -> 5877 | BE26: =BE27+BE30 -> 5877 | BF26: =BF27+BF30 -> 5877 | BH26: 16220 | BI26: 16225.75 | BJ26: 16956.095 | BK26: 17759.474 | BL26: 18643.191 | BM26: 19615.28 | BN26: 20684.578 | BP26: 5350 | BQ26: 4645 | BR26: 4644.5 | BS26: 6475.7 | BT26: 9000 | BU26: 11500 | BV26: 13500 | BX26: 1500 | BY26: 1339.8153 | BZ26: 2339.8153 | CA26: 3339.8153 | CB26: 4339.8153 | CC26: 5339.8153 | CD26: 6339.8153
A27: Долгосрочные обязательства | B27: =SUM(B28:B29) -> 13290 | I27: =SUM(I28:I29) -> 13290 | P27: =BB27+BJ27+BR27 -> 12136 | W27: =BC27+BK27+BS27 -> 12136 | AD27: =BD27+BL27+BT27 -> 12136 | AK27: =BE27+BM27+BU27 -> 12136 | AR27: =BF27+BN27+BV27 -> 12136 | AZ27: =SUM(AZ28:AZ29) -> 1290 | BA27: =SUM(BA28:BA29) -> 1290 | BB27: =SUM(BB28:BB29) -> 136 | BC27: =SUM(BC28:BC29) -> 136 | BD27: =SUM(BD28:BD29) -> 136 | BE27: =SUM(BE28:BE29) -> 136 | BF27: =SUM(BF28:BF29) -> 136 | BH27: 8500 | BI27: 8500 | BJ27: 8500 | BK27: 8500 | BL27: 8500 | BM27: 8500 | BN27: 8500 | BP27: 4100 | BQ27: 4100 | BR27: 3500 | BS27: 3500 | BT27: 3500 | BU27: 3500 | BV27: 3500 | BX27: 0 | BY27: 0 | BZ27: 0 | CA27: 0 | CB27: 0 | CC27: 0 | CD27: 0
A28: Кредиты и заёмы свыше года | B28: =(AZ28+BH28+BP28)+G28 -> 1154 | G28: =-600 -> -600 | I28: =BA28+BI28+BQ28+N28 -> 1154 | N28: =G28 -> -600 | P28: =BB28+BJ28+BR28 -> 0 | W28: =BC28+BK28+BS28 -> 0 | AD28: =BD28+BL28+BT28 -> 0 | AK28: =BE28+BM28+BU28 -> 0 | AR28: =BF28+BN28+BV28 -> 0 | AZ28: 1154 | BA28: 1154 | BB28: 0 | BC28: 0 | BD28: 0 | BE28: 0 | BF28: 0 | BH28: 0 | BI28: 0 | BJ28: 0 | BK28: 0 | BL28: 0 | BM28: 0 | BN28: 0 | BP28: 600 | BQ28: 600 | BR28: 0 | BS28: 0 | BT28: 0 | BU28: 0 | BV28: 0 | BX28: 0 | BY28: 0 | BZ28: 0 | CA28: 0 | CB28: 0 | CC28: 0 | CD28: 0
A29: Средства учредителей | B29: =(AZ29+BH29+BP29) -> 12136 | I29: =BA29+BI29+BQ29 -> 12136 | P29: =BB29+BJ29+BR29 -> 12136 | W29: =BC29+BK29+BS29 -> 12136 | AD29: =BD29+BL29+BT29 -> 12136 | AK29: =BE29+BM29+BU29 -> 12136 | AR29: =BF29+BN29+BV29 -> 12136 | AZ29: 136 | BA29: 136 | BB29: 136 | BC29: 136 | BD29: 136 | BE29: 136 | BF29: 136 | BH29: 8500 | BI29: 8500 | BJ29: 8500 | BK29: 8500 | BL29: 8500 | BM29: 8500 | BN29: 8500 | BP29: 3500 | BQ29: 3500 | BR29: 3500 | BS29: 3500 | BT29: 3500 | BU29: 3500 | BV29: 3500 | BX29: 0 | BY29: 0 | BZ29: 0 | CA29: 0 | CB29: 0 | CC29: 0 | CD29: 0
A30: Краткосрочные обязательства | B30: =(AZ30+BH30+BP30) -> 16970 | I30: =BA30+BI30+BQ30 -> 14011.75 | P30: =BB30+BJ30+BR30 -> 15341.595 | W30: =BC30+BK30+BS30 -> 17976.174 | AD30: =BD30+BL30+BT30 -> 21384.191 | AK30: =BE30+BM30+BU30 -> 24856.28 | AR30: =BF30+BN30+BV30 -> 27925.578 | AZ30: =SUM(AZ31:AZ32) -> 8000 | BA30: =SUM(BA31:BA32) -> 5741 | BB30: =SUM(BB31:BB32) -> 5741 | BC30: =SUM(BC31:BC32) -> 5741 | BD30: =SUM(BD31:BD32) -> 5741 | BE30: =SUM(BE31:BE32) -> 5741 | BF30: =SUM(BF31:BF32) -> 5741 | BH30: 7720 | BI30: 7725.75 | BJ30: 8456.0948 | BK30: 9259.4741 | BL30: 10143.191 | BM30: 11115.28 | BN30: 12184.578 | BP30: 1250 | BQ30: 545 | BR30: 1144.5 | BS30: 2975.7 | BT30: 5500 | BU30: 8000 | BV30: 10000 | BX30: 1500 | BY30: 1339.8153 | BZ30: 2339.8153 | CA30: 3339.8153 | CB30: 4339.8153 | CC30: 5339.8153 | CD30: 6339.8153
A31: Бюджет | B31: =(AZ31+BH31+BP31) -> 4420 | I31: =BA31+BI31+BQ31 -> 4169.3017 | P31: =BB31+BJ31+BR31 -> 4169.3017 | W31: =BC31+BK31+BS31 -> 4169.3017 | AD31: =BD31+BL31+BT31 -> 4169.3017 | AK31: =BE31+BM31+BU31 -> 4169.3017 | AR31: =BF31+BN31+BV31 -> 4169.3017 | AZ31: 4000 | BA31: 3747 | BB31: 3747 | BC31: 3747 | BD31: 3747 | BE31: 3747 | BF31: 3747 | BH31: 420 | BI31: 422.30168 | BJ31: 422.30168 | BK31: 422.30168 | BL31: 422.30168 | BM31: 422.30168 | BN31: 422.30168 | BP31: 0 | BQ31: 0 | BR31: 0 | BS31: 0 | BT31: 0 | BU31: 0 | BV31: 0 | BX31: 0 | BY31: 0 | BZ31: 0 | CA31: 0 | CB31: 0 | CC31: 0 | CD31: 0
A32: Прочие кредиторы | B32: =(AZ32+BH32+BP32) -> 12550 | I32: =BA32+BI32+BQ32 -> 9842.4483 | P32: =BB32+BJ32+BR32 -> 11172.293 | W32: =BC32+BK32+BS32 -> 13806.872 | AD32: =BD32+BL32+BT32 -> 17214.89 | AK32: =BE32+BM32+BU32 -> 20686.979 | AR32: =BF32+BN32+BV32 -> 23756.276 | AZ32: 4000 | BA32: 1994 | BB32: 1994 | BC32: 1994 | BD32: 1994 | BE32: 1994 | BF32: 1994 | BH32: 7300 | BI32: 7303.4483 | BJ32: 8033.7931 | BK32: 8837.1724 | BL32: 9720.8897 | BM32: 10692.979 | BN32: 11762.276 | BP32: 1250 | BQ32: 545 | BR32: 1144.5 | BS32: 2975.7 | BT32: 5500 | BU32: 8000 | BV32: 10000 | BX32: 1500 | BY32: 1339.8153 | BZ32: 2339.8153 | CA32: 3339.8153 | CB32: 4339.8153 | CC32: 5339.8153 | CD32: 6339.8153
A35: Выплаченные дивиденды (дивиденды материнской компании не выплачиваются) | B35: 7000 | C35: 10000 | D35: 16000 | E35: 20000 | F35: 25000 | G35: 32000 | H35: 39000 | AZ35: 7000 | BA35: 10000 | BB35: 16000 | BC35: 20000 | BD35: 25000 | BE35: 32000 | BF35: 39000 | BH35: 0 | BI35: 0 | BJ35: 6000 | BK35: 10000 | BL35: 16000 | BM35: 22000 | BN35: 29000 | BP35: 0 | BQ35: 0 | BR35: 0 | BS35: 0 | BT35: 4000 | BU35: 14000 | BV35: 29000 | BX35: 0 | BY35: 0 | BZ35: 0 | CA35: 0 | CB35: 0 | CC35: 0 | CD35: 1000
A37: *Величина акционерного капитала с даты приобретения компаний не менялась
A39: Расчёты для целей консолидации баланса:
A40: Шаг 1. Расчёт чистых активов на дату приобретения
A41: Компания А | B41: 31.12.25 план | C41: 31.12.25 факт | D41: 31.12.26 | E41: 31.12.27 | F41: 31.12.28 | G41: 31.12.29 | H41: 31.12.30
A42: Акционерный капитал, тыс. руб. | B42: =AZ20 -> 30001 | C42: =BA20 -> 30001 | D42: =BB20 -> 30001 | E42: =BC20 -> 30001 | F42: =BD20 -> 30001 | G42: =BE20 -> 30001 | H42: =BF20 -> 30001
A43: Нераспределённая прибыль, тыс. руб. | B43: =AZ23 -> 917 | C43: =BA23 -> 917.168 | D43: =BB23 -> 917.168 | E43: =BC23 -> 917.168 | F43: =BD23 -> 917.168 | G43: =BE23 -> 917.168 | H43: =BF23 -> 917.168
A44: Чистые активы, тыс. руб. | B44: =B42+B43 -> 30918 | C44: =C42+C43 -> 30918.168 | D44: =D42+D43 -> 30918.168 | E44: =E42+E43 -> 30918.168 | F44: =F42+F43 -> 30918.168 | G44: =G42+G43 -> 30918.168 | H44: =H42+H43 -> 30918.168
A45: Компания Б
A46: Акционерный капитал, тыс. руб. | B46: =BH20 -> 20030 | C46: =BI20 -> 20030.345 | D46: =BJ20 -> 20030.345 | E46: =BK20 -> 20030.345 | F46: =BL20 -> 20030.345 | G46: =BM20 -> 20030.345 | H46: =BN20 -> 20030.345
A47: Нераспределённая прибыль, тыс. руб. | B47: =BH23 -> 562 | C47: =BI23 -> 562.15747 | D47: =BJ23 -> 562.15747 | E47: =BK23 -> 562.15747 | F47: =BL23 -> 562.15747 | G47: =BM23 -> 562.15747 | H47: =BN23 -> 562.15747
A48: Чистые активы, тыс. руб. | B48: =B46+B47 -> 20592 | C48: =C46+C47 -> 20592.502 | D48: =D46+D47 -> 20592.502 | E48: =E46+E47 -> 20592.502 | F48: =F46+F47 -> 20592.502 | G48: =G46+G47 -> 20592.502 | H48: =H46+H47 -> 20592.502
A49: Компания В
A50: Акционерный капитал, тыс. руб. | B50: =BP20 -> 7001 | C50: =BQ20 -> 7001 | D50: =BR20 -> 7001 | E50: =BS20 -> 7001 | F50: =BT20 -> 7001 | G50: =BU20 -> 7001 | H50: =BV20 -> 7001
A51: Нераспределённая прибыль, тыс. руб. | B51: =BP23 -> 12 | C51: =BQ23 -> 12 | D51: =BR23 -> 12 | E51: =BS23 -> 12 | F51: =BT23 -> 12 | G51: =BU23 -> 12 | H51: =BV23 -> 12
A52: Чистые активы, тыс. руб. | B52: =B50+B51 -> 7013 | C52: =C50+C51 -> 7013 | D52: =D50+D51 -> 7013 | E52: =E50+E51 -> 7013 | F52: =F50+F51 -> 7013 | G52: =G50+G51 -> 7013 | H52: =H50+H51 -> 7013
A53: Компания Г
A54: Акционерный капитал, тыс. руб. | B54: =BX20 -> 6 | C54: =BY20 -> 5.5555556 | D54: =BZ20 -> 5.5555556 | E54: =CA20 -> 5.5555556 | F54: =CB20 -> 5.5555556 | G54: =CC20 -> 5.5555556 | H54: =CD20 -> 5.5555556
A55: Нераспределённая прибыль, тыс. руб. | B55: =BX23 -> 30 | C55: =BY23 -> 30.044843 | D55: =BZ23 -> 30.044843 | E55: =CA23 -> 30.044843 | F55: =CB23 -> 30.044843 | G55: =CC23 -> 30.044843 | H55: =CD23 -> 30.044843
A56: Чистые активы, тыс. руб. | B56: =B54+B55 -> 36 | C56: =C54+C55 -> 35.600398 | D56: =D54+D55 -> 35.600398 | E56: =E54+E55 -> 35.600398 | F56: =F54+F55 -> 35.600398 | G56: =G54+G55 -> 35.600398 | H56: =H54+H55 -> 35.600398
A58: Шаг 2. Расчёт гудвилла
A59: Компания Б | B59: 31.12.25 план | C59: 31.12.25 факт | D59: 31.12.26 | E59: 31.12.27 | F59: 31.12.28 | G59: 31.12.29 | H59: 31.12.30
A60: Первоначальные Инвестиции - приобретение 90% | B60: =AZ9 -> 2000 | C60: =BA9 -> 2000 | D60: =BB9 -> 2000 | E60: =BC9 -> 2000 | F60: =BD9 -> 2000 | G60: =BE9 -> 2000 | H60: =BF9 -> 2000
A61: Неконтролирующая доля на момент приобретения | B61: =(B46+B47)*10% -> 2059.2 | C61: =(C46+C47)*10% -> 2059.2502 | D61: =(D46+D47)*10% -> 2059.2502 | E61: =(E46+E47)*10% -> 2059.2502 | F61: =(F46+F47)*10% -> 2059.2502 | G61: =(G46+G47)*10% -> 2059.2502 | H61: =(H46+H47)*10% -> 2059.2502
A62: Чистые активы на момент вхождения в группу | B62: =B48 -> 20592 | C62: =C48 -> 20592.502 | D62: =D48 -> 20592.502 | E62: =E48 -> 20592.502 | F62: =F48 -> 20592.502 | G62: =G48 -> 20592.502 | H62: =H48 -> 20592.502
A63: Гудвилл | B63: =B60+B61-B62 -> -16532.8 | C63: =C60+C61-C62 -> -16533.252 | D63: =D60+D61-D62 -> -16533.252 | E63: =E60+E61-E62 -> -16533.252 | F63: =F60+F61-F62 -> -16533.252 | G63: =G60+G61-G62 -> -16533.252 | H63: =H60+H61-H62 -> -16533.252
A64: Компания В
A65: Первоначальные Инвестиции - приобретение 60% | B65: =AZ10 -> 1500 | C65: =BA10 -> 1500 | D65: =BB10 -> 1500 | E65: =BC10 -> 1500 | F65: =BD10 -> 1500 | G65: =BE10 -> 1500 | H65: =BF10 -> 1500
A66: Неконтролирующая доля на момент приобретения | B66: =(B50+B51)*40% -> 2805.2 | C66: =(C50+C51)*40% -> 2805.2 | D66: =(D50+D51)*40% -> 2805.2 | E66: =(E50+E51)*40% -> 2805.2 | F66: =(F50+F51)*40% -> 2805.2 | G66: =(G50+G51)*40% -> 2805.2 | H66: =(H50+H51)*40% -> 2805.2
A67: Чистые активы на момент вхождения в группу | B67: =B52 -> 7013 | C67: =C52 -> 7013 | D67: =D52 -> 7013 | E67: =E52 -> 7013 | F67: =F52 -> 7013 | G67: =G52 -> 7013 | H67: =H52 -> 7013
A68: Гудвилл | B68: =B65+B66-B67 -> -2707.8 | C68: =C65+C66-C67 -> -2707.8 | D68: =D65+D66-D67 -> -2707.8 | E68: =E65+E66-E67 -> -2707.8 | F68: =F65+F66-F67 -> -2707.8 | G68: =G65+G66-G67 -> -2707.8 | H68: =H65+H66-H67 -> -2707.8
A69: Компания Г
A70: Первоначальные Инвестиции - приобретение 30% | B70: =AZ11 -> 15 | C70: =BA11 -> 15 | D70: =BB11 -> 15 | E70: =BC11 -> 15 | F70: =BD11 -> 15 | G70: =BE11 -> 15 | H70: =BF11 -> 15
A71: Неконтролирующая доля на момент приобретения | B71: =(B54+B55)*70% -> 25.2 | C71: =(C54+C55)*70% -> 24.920279 | D71: =(D54+D55)*70% -> 24.920279 | E71: =(E54+E55)*70% -> 24.920279 | F71: =(F54+F55)*70% -> 24.920279 | G71: =(G54+G55)*70% -> 24.920279 | H71: =(H54+H55)*70% -> 24.920279
A72: Чистые активы на момент вхождения в группу | B72: =B56 -> 36 | C72: =C56 -> 35.600398 | D72: =D56 -> 35.600398 | E72: =E56 -> 35.600398 | F72: =F56 -> 35.600398 | G72: =G56 -> 35.600398 | H72: =H56 -> 35.600398
A73: Гудвилл | B73: =B70+B71-B72 -> 4.2 | C73: =C70+C71-C72 -> 4.3198805 | D73: =D70+D71-D72 -> 4.3198805 | E73: =E70+E71-E72 -> 4.3198805 | F73: =F70+F71-F72 -> 4.3198805 | G73: =G70+G71-G72 -> 4.3198805 | H73: =H70+H71-H72 -> 4.3198805
A74: Шаг 3. Расчёт неконтролирующей доли участия
A75: Компания Б | B75: 31.12.25 план | C75: 31.12.25 факт | D75: 31.12.26 | E75: 31.12.27 | F75: 31.12.28 | G75: 31.12.29 | H75: 31.12.30
A76: Неконтролирующая доля на момент приобретения | B76: =B61 -> 2059.2 | C76: =C61 -> 2059.2502 | D76: =D61 -> 2059.2502 | E76: =E61 -> 2059.2502 | F76: =F61 -> 2059.2502 | G76: =G61 -> 2059.2502 | H76: =H61 -> 2059.2502
A77: Доля прибыли (10%) после вхождения в группу | B77: =BH24*10% -> 1549.495 | C77: =BI24*10% -> 1567.5906 | D77: =BJ24*10% -> 1984.3044 | E77: =BK24*10% -> 2378.2451 | F77: =BL24*10% -> 2634.7089 | G77: =BM24*10% -> 2856.2813 | H77: =BN24*10% -> 3066.212
A78: Неконтролирующая доля | B78: =B76+B77 -> 3608.695 | C78: =C76+C77 -> 3626.8408 | D78: =D76+D77 -> 4043.5546 | E78: =E76+E77 -> 4437.4953 | F78: =F76+F77 -> 4693.9592 | G78: =G76+G77 -> 4915.5315 | H78: =H76+H77 -> 5125.4622
A79: Компания В
A80: Неконтролирующая доля на момент приобретения | B80: =B66 -> 2805.2 | C80: =C66 -> 2805.2 | D80: =D66 -> 2805.2 | E80: =E66 -> 2805.2 | F80: =F66 -> 2805.2 | G80: =G66 -> 2805.2 | H80: =H66 -> 2805.2
A81: Доля прибыли (40%) после вхождения в группу | B81: =BP24*40% -> 419.28 | C81: =BQ24*40% -> 371.28 | D81: =BR24*40% -> 1474.7385 | E81: =BS24*40% -> 3997.337 | F81: =BT24*40% -> 7116.7994 | G81: =BU24*40% -> 9886.9467 | H81: =BV24*40% -> 12028.251
A82: Неконтролирующая доля | B82: =B80+B81 -> 3224.48 | C82: =C80+C81 -> 3176.48 | D82: =D80+D81 -> 4279.9385 | E82: =E80+E81 -> 6802.537 | F82: =F80+F81 -> 9921.9994 | G82: =G80+G81 -> 12692.147 | H82: =H80+H81 -> 14833.451
A83: Итого неконтролирующая доля холдинга | B83: =B78+B82 -> 6833.175 | C83: =C78+C82 -> 6803.3208 | D83: =D78+D82 -> 8323.4931 | E83: =E78+E82 -> 11240.032 | F83: =F78+F82 -> 14615.959 | G83: =G78+G82 -> 17607.678 | H83: =H78+H82 -> 19958.913
A84: Шаг 4. Расчёт нераспределённой прибыли холдинга
A85: Компания А | B85: 31.12.25 план | C85: 31.12.25 факт | D85: 31.12.26 | E85: 31.12.27 | F85: 31.12.28 | G85: 31.12.29 | H85: 31.12.30
A86: Нераспределённая прибыль тыс. руб. | B86: =AZ22 -> 7440.8 | C86: =BA22 -> 7997.35 | D86: =BB22 -> 9222.0234 | E86: =BC22 -> 10484.46 | F86: =BD22 -> 11634.884 | G86: =BE22 -> 11717.25 | H86: =BF22 -> 11956.438
A87: Компания Б
A88: Нераспределённая прибыль тыс. руб.(90%) | B88: =BH24*90% -> 13945.455 | C88: =BI24*90% -> 14108.315 | D88: =BJ24*90% -> 17858.74 | E88: =BK24*90% -> 21404.206 | F88: =BL24*90% -> 23712.381 | G88: =BM24*90% -> 25706.532 | H88: =BN24*90% -> 27595.908
A89: Компания В
A90: Нераспределённая прибыль тыс. руб.(60%) | B90: =BP24*60% -> 628.92 | C90: =BQ24*60% -> 556.92 | D90: =BR24*60% -> 2212.1077 | E90: =BS24*60% -> 5996.0055 | F90: =BT24*60% -> 10675.199 | G90: =BU24*60% -> 14830.42 | H90: =BV24*60% -> 18042.376
A91: Компания Г
A92: Нераспределённая прибыль тыс. руб.(30%) | B92: =BX24*30% -> 677.925 | C92: =BY24*30% -> 607.32721 | D92: =BZ24*30% -> 1095.614 | E92: =CA24*30% -> 1745.0356 | F92: =CB24*30% -> 2579.8506 | G92: =CC24*30% -> 3627.4874 | H92: =CD24*30% -> 4618.9403
A93: Итого нераспределённая прибыль холдинга | B93: =B86+B88+B90+B92 -> 22693.1 | C93: =C86+C88+C90+C92 -> 23269.913 | D93: =D86+D88+D90+D92 -> 30388.485 | E93: =E86+E88+E90+E92 -> 39629.707 | F93: =F86+F88+F90+F92 -> 48602.314 | G93: =G86+G88+G90+G92 -> 55881.689 | H93: =H86+H88+H90+H92 -> 62213.663
A94: Шаг 5. Расчёт инвестиций в ассоциированные компании
B95: 31.12.25 план | C95: 31.12.25 факт | D95: 31.12.26 | E95: 31.12.27 | F95: 31.12.28 | G95: 31.12.29 | H95: 31.12.30
A96: Первоначальные инвестиции — приобретение 30% (компания Г) | B96: =B70 -> 15 | C96: =C70 -> 15 | D96: =D70 -> 15 | E96: =E70 -> 15 | F96: =F70 -> 15 | G96: =G70 -> 15 | H96: =H70 -> 15
A97: Первоначальные Инвестиции - приобретение 90% (компания Б) | B97: =B60 -> 2000 | C97: =C60 -> 2000 | D97: =D60 -> 2000 | E97: =E60 -> 2000 | F97: =F60 -> 2000 | G97: =G60 -> 2000 | H97: =H60 -> 2000
A98: Первоначальные Инвестиции - приобретение 60%(компания В) | B98: =B65 -> 1500 | C98: =C65 -> 1500 | D98: =D65 -> 1500 | E98: =E65 -> 1500 | F98: =F65 -> 1500 | G98: =G65 -> 1500 | H98: =H65 -> 1500
A99: Итого инвестиции в ассоциированную компанию | B99: =(BX20+BX22)*0.3+B73 -> 692.925 | C99: =(BY20+BY22)*0.3+C73 -> 622.32721 | D99: =(BZ20+BZ22)*0.3+D73 -> 1110.614 | E99: =(CA20+CA22)*0.3+E73 -> 1760.0356 | F99: =(CB20+CB22)*0.3+F73 -> 2594.8506 | G99: =(CC20+CC22)*0.3+G73 -> 3642.4874 | H99: =(CD20+CD22)*0.3+H73 -> 4633.9403

Sheet Группа компаний Конс.Отчетность
A1: Отчёт о прибылях и убытках, тыс. руб. | B1: Консолидация по группе | K1: Управленческий баланс*, тыс. руб. | L1: Консолидация по группе
B2: 2025 план | C2: 2025 факт | D2: 2026 | E2: 2027 | F2: 2028 | G2: 2029 | H2: 2030 | L2: 2025 план | M2: 2025 факт | N2: 2026 | O2: 2027 | P2: 2028 | Q2: 2029 | R2: 2030
A3: Выручка от реализации | B3: 115131 | C3: 116763.03 | D3: 137509.17 | E3: 163226.35 | F3: 195015.33 | G3: 235724.95 | H3: 287125.81 | K3: АКТИВЫ | L3: 133757.88 | M3: 131344.52 | N3: 140159.11 | O3: 154951.45 | P3: 170708 | Q3: 184451.18 | R3: 196203.69
A4: Комиссии за обработку платежей и переводов | B4: 51318 | C4: 51370 | D4: 59184.837 | E4: 68187.592 | F4: 78558.722 | G4: 90506.104 | H4: 104269.19 | K4: Внеоборотные активы: | L4: 98313.725 | M4: 101225.42 | N4: 97228.421 | O4: 93148.476 | P4: 88996.521 | Q4: 84785.928 | R4: 80232.864
A5: Разработка программного обеспечения | B5: 26290 | C5: 26879.768 | D5: 31825.926 | E5: 37792.193 | F5: 44832.388 | G5: 53139.818 | H5: 62942.585 | K5: Основные средства | L5: 47888.8 | M5: 47551.903 | N5: 45842.69 | O5: 43698.147 | P5: 41281.946 | Q5: 38850.514 | R5: 36603.729
A6: Аутсорсинговые услуги | B6: 13823 | C6: 13948.26 | D6: 16701.059 | E6: 19999.88 | F6: 23948.468 | G6: 28670.276 | H6: 34312.219 | K6: Нематериальные активы | L6: 48090 | M6: 51423.194 | N6: 48047.116 | O6: 45462.293 | P6: 42891.724 | Q6: 40064.926 | R6: 36767.194
A7: Комиссии трейдинговой площадки | B7: 23700 | C7: 24565 | D7: 29797.345 | E7: 37246.681 | F7: 47675.752 | G7: 63408.75 | H7: 85601.813 | K7: Финансовые вложения | L7: 1642 | M7: 1628 | N7: 2228 | O7: 2228 | P7: 2228 | Q7: 2228 | R7: 2228
A8: Комиссии за услуги бронирования | B8: 0 | C8: 0 | D8: 0 | E8: 0 | F8: 0 | G8: 0 | H8: 0 | K8: Инвестиции в дочерние и ассоциированные компании | L8: 692.925 | M8: 622.32721 | N8: 1110.614 | O8: 1760.0356 | P8: 2594.8506 | Q8: 3642.4874 | R8: 4633.9403
A9: Себестоимость реализации: | B9: 50290 | C9: 50750.063 | D9: 57356.908 | E9: 64843.676 | F9: 73210.956 | G9: 82588.037 | H9: 93126.421 | K9: в т. ч. в компанию Б | L9: 0 | M9: 0 | N9: 0 | O9: 0 | P9: 0 | Q9: 0 | R9: 0
A10: Прямые расходы на персонал | B10: 41960 | C10: 42144.562 | D10: 47630.464 | E10: 53668.304 | F10: 60323.627 | G10: 67670.773 | H10: 75794.136 | K10: в т. ч. в компанию В | L10: 0 | M10: 0 | N10: 0 | O10: 0 | P10: 0 | Q10: 0 | R10: 0
A11: Оборудование, лицензии и программное обеспечение | B11: 6640 | C11: 6977.7896 | D11: 8009.5555 | E11: 9364.4122 | F11: 10977.136 | G11: 12902.392 | H11: 15206.988 | K11: в т. ч. в компанию Г | L11: 692.925 | M11: 622.32721 | N11: 1110.614 | O11: 1760.0356 | P11: 2594.8506 | Q11: 3642.4874 | R11: 4633.9403
A12: Прочие расходы | B12: 1690 | C12: 1627.7118 | D12: 1716.8892 | E12: 1810.9599 | F12: 1910.193 | G12: 2014.8722 | H12: 2125.2968
A13: Валовая прибыль | B13: 64841 | C13: 66012.965 | D13: 80152.259 | E13: 98382.67 | F13: 121804.37 | G13: 153136.91 | H13: 193999.39 | K13: Оборотные активы: | L13: 35444.15 | M13: 30119.094 | N13: 42930.687 | O13: 61802.972 | P13: 81711.478 | Q13: 99665.255 | R13: 115970.83
A14: Операционные расходы | B14: 38032 | C14: 38479.669 | D14: 41615.091 | E14: 44770.252 | F14: 48203.285 | G14: 51942.29 | H14: 56200.83 | K14: Дебиторская задолженность | L14: 7500 | M14: 7599.7853 | N14: 7592.5171 | O14: 7588.2038 | P14: 7586.7909 | Q14: 7588.2257 | R14: 7592.4576
A15: Расходы на персонал | B15: 14623 | C15: 14650.085 | D15: 15595.929 | E15: 16604.31 | F15: 17679.337 | G15: 18825.394 | H15: 20047.153 | K15: Денежные средства | L15: 27944.15 | M15: 22519.308 | N15: 35338.17 | O15: 54214.769 | P15: 74124.687 | Q15: 92077.029 | R15: 108378.37
A16: Аренда | B16: 2191 | C16: 2190.7038 | D16: 2309.6184 | E16: 2435.022 | F16: 2567.2706 | G16: 2706.7398 | H16: 2853.826
A17: Реклама и маркетинг | B17: 15000 | C17: 15338.189 | D17: 17073.35 | E17: 18740.989 | F17: 20593.794 | G17: 22654.071 | H17: 25129.228 | K17: ПАССИВЫ | L17: 133757.88 | M17: 131344.52 | N17: 140159.11 | O17: 154951.45 | P17: 170708 | Q17: 184451.18 | R17: 196203.69
A18: Оборудование, лицензии и программное обеспечение | B18: 4850 | C18: 4910.741 | D18: 5174.2968 | E18: 5452.0725 | F18: 5744.8397 | G18: 6053.4118 | H18: 6378.6466 | K18: Собственные средства: | L18: 103497.88 | M18: 104042.77 | N18: 112681.51 | O18: 124839.27 | P18: 137187.81 | Q18: 147458.9 | R18: 156142.11
A19: Прочие расходы | B19: 1368 | C19: 1389.9497 | D19: 1461.8969 | E19: 1537.8588 | F19: 1618.0442 | G19: 1702.6732 | H19: 1791.9771 | K19: Собственный капитал | L19: 103497.88 | M19: 104042.77 | N19: 112681.51 | O19: 124839.27 | P19: 137187.81 | Q19: 147458.9 | R19: 156142.11
A20: Операционная прибыль | B20: 26809 | C20: 27533.296 | D20: 38537.168 | E20: 53612.418 | F20: 73601.089 | G20: 101194.62 | H20: 137798.56 | K20: Акционерный капитал* | L20: 30001 | M20: 30001 | N20: 30001 | O20: 30001 | P20: 30001 | Q20: 30001 | R20: 30001
A21: Внереализационные доходы | B21: 2274.125 | C21: 2205.3063 | D21: 2370.2791 | E21: 2558.0176 | F21: 2771.4082 | G21: 3013.6936 | H21: 3288.5167 | K21: Фонды и резервы | L21: 24730 | M21: 24727.483 | N21: 24727.483 | O21: 24727.483 | P21: 24727.483 | Q21: 24727.483 | R21: 24727.483
A22: Инвестиционный доход | B22: 1373 | C22: 1372.7123 | D22: 1372.7123 | E22: 1372.7123 | F22: 1372.7123 | G22: 1372.7123 | H22: 1372.7123 | K22: Нераспределённая прибыль | L22: 41933.7 | M22: 42510.965 | N22: 49629.537 | O22: 58870.759 | P22: 67843.366 | Q22: 75122.741 | R22: 81454.715
A23: Прочие доходы | B23: 405 | C23: 484 | D23: 509.28 | E23: 535.8838 | F23: 563.8809 | G23: 593.34447 | H23: 624.35152 | K23: в т. ч. на дату приобретения дочерних и ассоциированных компаний | L23: 0 | M23: 0 | N23: 0 | O23: 0 | P23: 0 | Q23: 0 | R23: 0
A24: Доля прибыли ассоциированной компании | B24: 496.125 | C24: 348.594 | D24: 488.28681 | E24: 649.42155 | F24: 834.81501 | G24: 1047.6368 | H24: 1291.4529 | K24: в т. ч. после приобретения дочерних и ассоциированных компаний | L24: 0 | M24: 0 | N24: 0 | O24: 0 | P24: 0 | Q24: 0 | R24: 0
A25: Внереализационные расходы | B25: 186 | C25: 210 | D25: 218.55 | E25: 176.561 | F25: 186.05792 | G25: 196.06704 | H25: 206.61605 | K25: Неконтролирующая доля меньшинства | L25: 6833.175 | M25: 6803.3208 | N25: 8323.4931 | O25: 11240.032 | P25: 14615.959 | Q25: 17607.678 | R25: 19958.913
A26: Проценты уплаченные (аннуитет, полное погашение долга в конце 2026) | B26: 51 | C26: 51 | D26: 51 | E26: 0 | F26: 0 | G26: 0 | H26: 0 | K26: Привлечённые средства: | L26: 30260 | M26: 27301.75 | N26: 27477.595 | O26: 30112.174 | P26: 33520.191 | Q26: 36992.28 | R26: 40061.578
A27: Прочие расходы | B27: 135 | C27: 159 | D27: 167.55 | E27: 176.561 | F27: 186.05792 | G27: 196.06704 | H27: 206.61605 | K27: Долгосрочные обязательства | L27: 13290 | M27: 13290 | N27: 12136 | O27: 12136 | P27: 12136 | Q27: 12136 | R27: 12136
A28: Прибыль до налогообложения | B28: 28897.125 | C28: 29528.602 | D28: 40688.897 | E28: 55993.874 | F28: 76186.439 | G28: 104012.25 | H28: 140880.46 | K28: Кредиты и заёмы свыше года | L28: 1154 | M28: 1154 | N28: 0 | O28: 0 | P28: 0 | Q28: 0 | R28: 0
... A32: принадлежащей неконтролируещей доли | B32: 903.375 | C32: 961.1256 | D32: 2120.1723 | E32: 3916.5392 | F32: 6575.9262 | G32: 10791.72 | H32: 16851.235 | K32: Прочие кредиторы | L32: 12550 | M32: 9842.4483 | N32: 11172.293 | O32: 13806.872 | P32: 17214.89 | Q32: 20686.979 | R32: 23756.276
A33: в т. ч. амортизация | B33: 4254 | C33: 4253.8487 | D33: 3299.28 | E33: 4729.3668 | F33: 4986.7699 | G33: 5258.2299 | H33: 5544.517
A34: EBITDA | B34: 31829.125 | C34: 32460.738 | D34: 42666.465 | E34: 59350.529 | F34: =F30+F29+F26-F22+F33 -> 79800.497 | G34: 107897.77 | H34: 145052.26

Sheet Финансовые показатели
A1: Показатель | B1: А | J1: Б | R1: В | Z1: Г | AH1: Группа
B2: 2025 план | C2: 2025 факт | D2: 2026 | E2: 2027 | F2: 2028 | G2: 2029 | H2: 2030 | J2: 2025 план | K2: 2025 факт | L2: 2026 | M2: 2027 | N2: 2028 | O2: 2029 | P2: 2030 | R2: 2025 план | S2: 2025 факт | T2: 2026 | U2: 2027 | V2: 2028 | W2: 2029 | X2: 2030 | Z2: 2025 план | AA2: 2025 факт | AB2: 2026 | AC2: 2027 | AD2: 2028 | AE2: 2029 | AF2: 2030 | AH2: 2025 план | AI2: 2025 факт | AJ2: 2026 | AK2: 2027 | AL2: 2028 | AM2: 2029 | AN2: 2030
A3: Показатели рентабельности
A4: Рентабельность продаж по валовой прибыли | B4: =Вводные!C52/Вводные!C42*100% -> 0.6627794 | C4: =Вводные!D52/Вводные!D42*100% -> 0.66282863 | D4: =Вводные!E52/Вводные!E42*100% -> 0.66404241 | E4: =Вводные!F52/Вводные!F42*100% -> 0.66857241 | F4: =Вводные!G52/Вводные!G42*100% -> 0.6757019 | G4: =Вводные!H52/Вводные!H42*100% -> 0.68483111 | H4: =Вводные!I52/Вводные!I42*100% -> 0.69546001 | J4: =Вводные!K52/Вводные!K42*100% -> 0.52235294 | K4: =Вводные!L52/Вводные!L42*100% -> 0.53 | L4: =Вводные!M52/Вводные!M42*100% -> 0.5439993 | M4: =Вводные!N52/Вводные!N42*100% -> 0.55734868 | N4: =Вводные!O52/Вводные!O42*100% -> 0.570095 | O4: =Вводные!P52/Вводные!P42*100% -> 0.58228068 | P4: =Вводные!Q52/Вводные!Q42*100% -> 0.59394417 | R4: =Вводные!S52/Вводные!S42 -> 0.36919831 | S4: =Вводные!T52/Вводные!T42 -> 0.37374313 | T4: =Вводные!U52/Вводные!U42 -> 0.44174221 | U4: =Вводные!V52/Вводные!V42 -> 0.51560447 | V4: =Вводные!W52/Вводные!W42 -> 0.58812467 | W4: =Вводные!X52/Вводные!X42 -> 0.66164891 | X4: =Вводные!Y52/Вводные!Y42 -> 0.72498956 | Z4: =Вводные!AA52/Вводные!AA42 -> 0.72352941 | AA4: =Вводные!AB52/Вводные!AB42 -> 0.69399148 | AB4: =Вводные!AC52/Вводные!AC42 -> 0.71040178 | AC4: =Вводные!AD52/Вводные!AD42 -> 0.72569647 | AD4: =Вводные!AE52/Вводные!AE42 -> 0.73995181 | AE4: =Вводные!AF52/Вводные!AF42 -> 0.75323884 | AF4: =Вводные!AG52/Вводные!AG42 -> 0.76562375 | AH4: ='Группа компаний Конс.Отчетность'!B13/'Группа компаний Конс.Отчетность'!B3 -> 0.56319323 | AI4: ='Группа компаний Конс.Отчетность'!C13/'Группа компаний Конс.Отчетность'!C3 -> 0.56535845 | AJ4: ='Группа компаний Конс.Отчетность'!D13/'Группа компаний Конс.Отчетность'!D3 -> 0.58288666 | AK4: ='Группа компаний Конс.Отчетность'!E13/'Группа компаний Конс.Отчетность'!E3 -> 0.60273769 | AL4: ='Группа компаний Конс.Отчетность'!F13/'Группа компаний Конс.Отчетность'!F3 -> 0.62458872 | AM4: ='Группа компаний Конс.Отчетность'!G13/'Группа компаний Конс.Отчетность'!G3 -> 0.64964236 | AN4: ='Группа компаний Конс.Отчетность'!H13/'Группа компаний Конс.Отчетность'!H3 -> 0.67565988
A5: Рентабельность продаж по EBITDA | B5: =Вводные!C70/Вводные!C42*100% -> 0.3851895 | C5: =Вводные!D70/Вводные!D42*100% -> 0.38730535 | D5: =Вводные!E70/Вводные!E42*100% -> 0.40619412 | E5: =Вводные!F70/Вводные!F42*100% -> 0.43154862 | F5: =Вводные!G70/Вводные!G42*100% -> 0.45824351 | G5: =Вводные!H70/Вводные!H42*100% -> 0.48578301 | H5: =Вводные!I70/Вводные!I42*100% -> 0.51376249 | J5: =Вводные!K70/Вводные!K42*100% -> 0.25614118 | K5: =Вводные!L70/Вводные!L42*100% -> 0.26602192 | L5: =Вводные!M70/Вводные!M42*100% -> 0.28414265 | M5: =Вводные!N70/Вводные!N42*100% -> 0.34515957 | N5: =Вводные!O70/Вводные!O42*100% -> 0.37984638 | O5: =Вводные!P70/Вводные!P42*100% -> 0.41169843 | P5: =Вводные!Q70/Вводные!Q42*100% -> 0.44099044 | R5: =Вводные!S70/Вводные!S42*100% -> 0.026540084 | S5: =Вводные!T70/Вводные!T42*100% -> 0.027233869 | T5: =Вводные!U70/Вводные!U42*100% -> 0.11910038 | U5: =Вводные!V70/Вводные!V42*100% -> 0.22335634 | V5: =Вводные!W70/Вводные!W42*100% -> 0.32898273 | W5: =Вводные!X70/Вводные!X42*100% -> 0.43997597 | X5: =Вводные!Y70/Вводные!Y42*100% -> 0.53561661 | Z5: =Вводные!AA70/Вводные!AA42 -> 0.27611765 | AA5: =Вводные!AB70/Вводные!AB42 -> 0.21372217 | AB5: =Вводные!AC70/Вводные!AC42 -> 0.26117706 | AC5: =Вводные!AD70/Вводные!AD42 -> 0.30544049 | AD5: =Вводные!AE70/Вводные!AE42 -> 0.34672962 | AE5: =Вводные!AF70/Вводные!AF42 -> 0.38524674 | AF5: =Вводные!AG70/Вводные!AG42 -> 0.42118035 | AH5: ='Группа компаний Конс.Отчетность'!B34/'Группа компаний Конс.Отчетность'!B3 -> 0.27646008 | AI5: ='Группа компаний Конс.Отчетность'!C34/'Группа компаний Конс.Отчетность'!C3 -> 0.27800528 | AJ5: ='Группа компаний Конс.Отчетность'!D34/'Группа компаний Конс.Отчетность'!D3 -> 0.31028087 | AK5: ='Группа компаний Конс.Отчетность'!E34/'Группа компаний Конс.Отчетность'!E3 -> 0.36360876 | AL5: ='Группа компаний Конс.Отчетность'!F34/'Группа компаний Конс.Отчетность'!F3 -> 0.40920115 | AM5: ='Группа компаний Конс.Отчетность'!G34/'Группа компаний Конс.Отчетность'!G3 -> 0.45772739 | AN5: ='Группа компаний Конс.Отчетность'!H34/'Группа компаний Конс.Отчетность'!H3 -> 0.50518713
A6: Рентабельность продаж по чистой прибыли | B6: =Вводные!C68/Вводные!C42*100% -> 0.27323615 | C6: =Вводные!D68/Вводные!D42*100% -> 0.27483884 | D6: =Вводные!E68/Вводные!E42*100% -> 0.29035191 | E6: =Вводные!F68/Вводные!F42*100% -> 0.31115983 | F6: =Вводные!G68/Вводные!G42*100% -> 0.33223471 | G6: =Вводные!H68/Вводные!H42*100% -> 0.35385674 | H6: =Вводные!I68/Вводные!I42*100% -> 0.37572915 | J6: =Вводные!K68/Вводные!K42*100% -> 0.15637059 | K6: =Вводные!L68/Вводные!L42*100% -> 0.16437004 | L6: =Вводные!M68/Вводные!M42*100% -> 0.19879051 | M6: =Вводные!N68/Вводные!N42*100% -> 0.23028514 | N6: =Вводные!O68/Вводные!O42*100% -> 0.2591348 | O6: =Вводные!P68/Вводные!P42*100% -> 0.28559277 | P6: =Вводные!Q68/Вводные!Q42*100% -> 0.30988738 | R6: =Вводные!S68/Вводные!S42 -> 0.025189873 | S6: =Вводные!T68/Вводные!T42 -> 0.02552412 | T6: =Вводные!U68/Вводные!U42 -> 0.09258027 | U6: =Вводные!V68/Вводные!V42 -> 0.169317 | V6: =Вводные!W68/Вводные!W42 -> 0.24747708 | W6: =Вводные!X68/Вводные!X42 -> 0.33000758 | X6: =Вводные!Y68/Вводные!Y42 -> 0.40131464 | Z6: =Вводные!AA68/Вводные!AA42 -> 0.19455882 | AA6: =Вводные!AB68/Вводные!AB42 -> 0.14686592 | AB6: =Вводные!AC68/Вводные!AC42 -> 0.18343274 | AC6: =Вводные!AD68/Вводные!AD42 -> 0.21753506 | AD6: =Вводные!AE68/Вводные!AE42 -> 0.24934091 | AE6: =Вводные!AF68/Вводные!AF42 -> 0.27900679 | AF6: =Вводные!AG68/Вводные!AG42 -> 0.30667849 | AH6: ='Группа компаний Конс.Отчетность'!B30/'Группа компаний Конс.Отчетность'!B3 -> 0.18932238 | AI6: ='Группа компаний Конс.Отчетность'!C30/'Группа компаний Конс.Отчетность'!C3 -> 0.19041644 | AJ6: ='Группа компаний Конс.Отчетность'!D30/'Группа компаний Конс.Отчетность'!D3 -> 0.22281238 | AK6: ='Группа компаний Конс.Отчетность'!E30/'Группа компаний Конс.Отчетность'!E3 -> 0.25827792 | AL6: ='Группа компаний Конс.Отчетность'!F30/'Группа компаний Конс.Отчетность'!F3 -> 0.29407192 | AM6: ='Группа компаний Конс.Отчетность'!G30/'Группа компаний Конс.Отчетность'!G3 -> 0.33204417 | AN6: ='Группа компаний Конс.Отчетность'!H30/'Группа компаний Конс.Отчетность'!H3 -> 0.36911766
A7: Рентабельность затрат (ROCS) | B7: =Вводные!C68/(Вводные!C48+Вводные!C53) -> 0.42646523 | C7: =Вводные!D68/(Вводные!D48+Вводные!D53) -> 0.43005256 | D7: =Вводные!E68/(Вводные!E48+Вводные!E53) -> 0.46993185 | E7: =Вводные!F68/(Вводные!F48+Вводные!F53) -> 0.52705201 | F7: =Вводные!G68/(Вводные!G48+Вводные!G53) -> 0.59143462 | G7: =Вводные!H68/(Вводные!H48+Вводные!H53) -> 0.6645989 | H7: =Вводные!I68/(Вводные!I48+Вводные!I53) -> 0.74720573 | J7: =Вводные!K68/(Вводные!K48+Вводные!K53) -> 0.19444526 | K7: =Вводные!L68/(Вводные!L48+Вводные!L53) -> 0.20701517 | L7: =Вводные!M68/(Вводные!M48+Вводные!M53) -> 0.26641339 | M7: =Вводные!N68/(Вводные!N48+Вводные!N53) -> 0.32779158 | N7: =Вводные!O68/(Вводные!O48+Вводные!O53) -> 0.3910474 | O7: =Вводные!P68/(Вводные!P48+Вводные!P53) -> 0.45607385 | P7: =Вводные!Q68/(Вводные!Q48+Вводные!Q53) -> 0.52276116 | R7: =Вводные!S68/(Вводные!S48+Вводные!S53) -> 0.025190936 | S7: =Вводные!T68/(Вводные!T48+Вводные!T53) -> 0.025568877 | T7: =Вводные!U68/(Вводные!U48+Вводные!U53) -> 0.10250606 | U7: =Вводные!V68/(Вводные!V48+Вводные!V53) -> 0.21283604 | V7: =Вводные!W68/(Вводные!W48+Вводные!W53) -> 0.36040925 | W7: =Вводные!X68/(Вводные!X48+Вводные!X53) -> 0.57644477 | X7: =Вводные!Y68/(Вводные!Y48+Вводные!Y53) -> 0.84635228 | Z7: =Вводные!AA68/(Вводные!AA48+Вводные!AA53) -> 0.2627085 | AA7: =Вводные!AB68/(Вводные!AB48+Вводные!AB53) -> 0.18254238 | AB7: =Вводные!AC68/(Вводные!AC48+Вводные!AC53) -> 0.24270825 | AC7: =Вводные!AD68/(Вводные!AD48+Вводные!AD53) -> 0.30626693 | AD7: =Вводные!AE68/(Вводные!AE48+Вводные!AE53) -> 0.37334989 | AE7: =Вводные!AF68/(Вводные!AF48+Вводные!AF53) -> 0.44408644 | AF7: =Вводные!AG68/(Вводные!AG48+Вводные!AG53) -> 0.51860269 | AH7: ='Группа компаний Конс.Отчетность'!B30/('Группа компаний Конс.Отчетность'!B9+'Группа компаний Конс.Отчетность'!B14) -> 0.24678874 | AI7: ='Группа компаний Конс.Отчетность'!C30/('Группа компаний Конс.Отчетность'!C9+'Группа компаний Конс.Отчетность'!C14) -> 0.24917255 | AJ7: ='Группа компаний Конс.Отчетность'!D30/('Группа компаний Конс.Отчетность'!D9+'Группа компаний Конс.Отчетность'!D14) -> 0.30956982 | AK7: ='Группа компаний Конс.Отчетность'!E30/('Группа компаний Конс.Отчетность'!E9+'Группа компаний Конс.Отчетность'!E14) -> 0.38460223 | AL7: ='Группа компаний Конс.Отчетность'!F30/('Группа компаний Конс.Отчетность'!F9+'Группа компаний Конс.Отчетность'!F14) -> 0.47233778 | AM7: ='Группа компаний Конс.Отчетность'!G30/('Группа компаний Конс.Отчетность'!G9+'Группа компаний Конс.Отчетность'!G14) -> 0.58181004 | AN7: ='Группа компаний Конс.Отчетность'!H30/('Группа компаний Конс.Отчетность'!H9+'Группа компаний Конс.Отчетность'!H14) -> 0.70973789
A8: Рентабельность собственного капитала (ROE) | B8: =Вводные!C68/Вводные!C129*100% -> 0.24490521 | C8: =Вводные!D68/Вводные!D129*100% -> 0.24425229 | D8: =Вводные!E68/Вводные!E129*100% -> 0.29107521 | E8: =Вводные!F68/Вводные!F129*100% -> 0.35180308 | F8: =Вводные!G68/Вводные!G129*100% -> 0.42459648 | G8: =Вводные!H68/Вводные!H129*100% -> 0.52021592 | H8: =Вводные!I68/Вводные!I129*100% -> 0.63380569 | J8: =Вводные!K68/Вводные!K129*100% -> 0.17789862 | K8: =Вводные!L68/Вводные!L129*100% -> 0.18920376 | L8: =Вводные!M68/Вводные!M129*100% -> 0.24375763 | M8: =Вводные!N68/Вводные!N129*100% -> 0.3053577 | N8: =Вводные!O68/Вводные!O129*100% -> 0.38504605 | O8: =Вводные!P68/Вводные!P129*100% -> 0.4801868 | P8: =Вводные!Q68/Вводные!Q129*100% -> 0.59203954 | R8: =Вводные!S68/Вводные!S129 -> 0.051638238 | S8: =Вводные!T68/Вводные!T129 -> 0.054801944 | T8: =Вводные!U68/Вводные!U129 -> 0.19427297 | U8: =Вводные!V68/Вводные!V129 -> 0.30753882 | V8: =Вводные!W68/Вводные!W129 -> 0.41684001 | W8: =Вводные!X68/Вводные!X129 -> 0.59395829 | X8: =Вводные!Y68/Вводные!Y129 -> 0.84648078 | Z8: =Вводные!AA68/Вводные!AA129 -> 0.47307445 | AA8: =Вводные!AB68/Вводные!AB129 -> 0.35282532 | AB8: =Вводные!AC68/Вводные!AC129 -> 0.33075171 | AC8: =Вводные!AD68/Вводные!AD129 -> 0.30550725 | AD8: =Вводные!AE68/Вводные!AE129 -> 0.28198154 | AE8: =Вводные!AF68/Вводные!AF129 -> 0.26137551 | AF8: =Вводные!AG68/Вводные!AG129 -> 0.25831019 | AH8: ='Группа компаний Конс.Отчетность'!B30/'Группа компаний Конс.Отчетность'!L19 -> 0.21060215 | AI8: ='Группа компаний Конс.Отчетность'!C30/'Группа компаний Конс.Отчетность'!M19 -> 0.21369674 | AJ8: ='Группа компаний Конс.Отчетность'!D30/'Группа компаний Конс.Отчетность'!N19 -> 0.27190569 | AK8: ='Группа компаний Конс.Отчетность'!E30/'Группа компаний Конс.Отчетность'!O19 -> 0.3376963 | AL8: ='Группа компаний Конс.Отчетность'!F30/'Группа компаний Конс.Отчетность'!P19 -> 0.41802937 | AM8: ='Группа компаний Конс.Отчетность'!G30/'Группа компаний Конс.Отчетность'!Q19 -> 0.53079939 | AN8: ='Группа компаний Конс.Отчетность'!H30/'Группа компаний Конс.Отчетность'!R19 -> 0.67876121
A9: Рентабельность активов (ROA) | B9: =Вводные!C68/Вводные!C113*100% -> 0.21079053 | C9: =Вводные!D68/Вводные!D113*100% -> 0.21782453 | D9: =Вводные!E68/Вводные!E113*100% -> 0.26477898 | E9: =Вводные!F68/Вводные!F113*100% -> 0.32062564 | F9: =Вводные!G68/Вводные!G113*100% -> 0.38760959 | G9: =Вводные!H68/Вводные!H113*100% -> 0.47495481 | H9: =Вводные!I68/Вводные!I113*100% -> 0.57885634 | J9: =Вводные!K68/Вводные!K113*100% -> 0.12404122 | K9: =Вводные!L68/Вводные!L113*100% -> 0.13210778 | L9: =Вводные!M68/Вводные!M113*100% -> 0.17330509 | M9: =Вводные!N68/Вводные!N113*100% -> 0.21983356 | N9: =Вводные!O68/Вводные!O113*100% -> 0.27767571 | O9: =Вводные!P68/Вводные!P113*100% -> 0.34571627 | P9: =Вводные!Q68/Вводные!Q113*100% -> 0.42477452 | R9: =Вводные!S68/Вводные!S113*100% -> 0.035302048 | S9: =Вводные!T68/Вводные!T113*100% -> 0.038977509 | T9: =Вводные!U68/Вводные!U113*100% -> 0.14639119 | U9: =Вводные!V68/Вводные!V113*100% -> 0.23372939 | V9: =Вводные!W68/Вводные!W113*100% -> 0.31627547 | W9: =Вводные!X68/Вводные!X113*100% -> 0.44778952 | X9: =Вводные!Y68/Вводные!Y113*100% -> 0.6351878 | Z9: =Вводные!AA68/Вводные!AA113 -> 0.33103138 | AA9: =Вводные!AB68/Вводные!AB113 -> 0.25079572 | AB9: =Вводные!AC68/Вводные!AC113 -> 0.22416588 | AC9: =Вводные!AD68/Вводные!AD113 -> 0.20763814 | AD9: =Вводные!AE68/Вводные!AE113 -> 0.19585216 | AE9: =Вводные!AF68/Вводные!AF113 -> 0.1867408 | AF9: =Вводные!AG68/Вводные!AG113 -> 0.18712464 | AH9: ='Группа компаний Конс.Отчетность'!B30/'Группа компаний Конс.Отчетность'!L3 -> 0.1629577 | AI9: ='Группа компаний Конс.Отчетность'!C30/'Группа компаний Конс.Отчетность'!M3 -> 0.16927695 | AJ9: ='Группа компаний Конс.Отчетность'!D30/'Группа компаний Конс.Отчетность'!N3 -> 0.21859974 | AK9: ='Группа компаний Конс.Отчетность'!E30/'Группа компаний Конс.Отчетность'!O3 -> 0.27207078 | AL9: ='Группа компаний Конс.Отчетность'!F30/'Группа компаний Конс.Отчетность'!P3 -> 0.3359452 | AM9: ='Группа компаний Конс.Отчетность'!G30/'Группа компаний Конс.Отчетность'!Q3 -> 0.42434586 | AN9: ='Группа компаний Конс.Отчетность'!H30/'Группа компаний Конс.Отчетность'!R3 -> 0.5401693
A10: Показатели ликвидности и платёжеспособности
A11: Коэффициент текущей ликвидности | B11: =Вводные!C123/Вводные!C139 -> 1.955625 | C11: =Вводные!D123/Вводные!D139 -> 1.9397927 | D11: =Вводные!E123/Вводные!E139 -> 2.2636515 | E11: =Вводные!F123/Вводные!F139 -> 2.7009389 | F11: =Вводные!G123/Вводные!G139 -> 3.1295846 | G11: =Вводные!H123/Вводные!H139 -> 3.383603 | H11: =Вводные!I123/Вводные!I139 -> 3.676921 | J11: =Вводные!K123/Вводные!K139 -> 2.2863925 | K11: =Вводные!L123/Вводные!L139 -> 2.2965465 | L11: =Вводные!M123/Вводные!M139 -> 2.9884997 | M11: =Вводные!N123/Вводные!N139 -> 3.541188 | N11: =Вводные!O123/Вводные!O139 -> 3.8613365 | O11: =Вводные!P123/Вводные!P139 -> 4.0883836 | P11: =Вводные!Q123/Вводные!Q139 -> 4.2571432 | R11: =Вводные!S123/Вводные!S139 -> 1.71856 | S11: =Вводные!T123/Вводные!T139 -> 2.2755963 | T11: =Вводные!U123/Вводные!U139 -> 4.0751649 | U11: =Вводные!V123/Вводные!V139 -> 4.5392154 | V11: =Вводные!W123/Вводные!W139 -> 4.4687741 | W11: =Вводные!X123/Вводные!X139 -> 4.3495576 | X11: =Вводные!Y123/Вводные!Y139 -> 4.2990127 | Z11: =Вводные!AA123/Вводные!AA139 -> 2.2931667 | AA11: =Вводные!AB123/Вводные!AB139 -> 2.3043937 | AB11: =Вводные!AC123/Вводные!AC139 -> 2.505488 | AC11: =Вводные!AD123/Вводные!AD139 -> 2.7487461 | AD11: =Вводные!AE123/Вводные!AE139 -> 3.0237081 | AE11: =Вводные!AF123/Вводные!AF139 -> 3.3297301 | AF11: =Вводные!AG123/Вводные!AG139 -> 3.5107175 | AH11: ='Группа компаний Конс.Отчетность'!L13/'Группа компаний Конс.Отчетность'!L30 -> 2.0886358 | AI11: ='Группа компаний Конс.Отчетность'!M13/'Группа компаний Конс.Отчетность'!M30 -> 2.1495598 | AJ11: ='Группа компаний Конс.Отчетность'!N13/'Группа компаний Конс.Отчетность'!N30 -> 2.7983197 | AK11: ='Группа компаний Конс.Отчетность'!O13/'Группа компаний Конс.Отчетность'!O30 -> 3.4380493 | AL11: ='Группа компаний Конс.Отчетность'!P13/'Группа компаний Конс.Отчетность'!P30 -> 3.8211161 | AM11: ='Группа компаний Конс.Отчетность'!Q13/'Группа компаний Конс.Отчетность'!Q30 -> 4.0096609 | AN11: ='Группа компаний Конс.Отчетность'!R13/'Группа компаний Конс.Отчетность'!R30 -> 4.1528532
A12: Коэффициент срочной ликвидности | B12: =Вводные!C123/Вводные!C139 -> 1.955625 | C12: =Вводные!D123/Вводные!D139 -> 1.9397927 | D12: =Вводные!E123/Вводные!E139 -> 2.2636515 | E12: =Вводные!F123/Вводные!F139 -> 2.7009389 | F12: =Вводные!G123/Вводные!G139 -> 3.1295846 | G12: =Вводные!H123/Вводные!H139 -> 3.383603 | H12: =Вводные!I123/Вводные!I139 -> 3.676921 | J12: =Вводные!K123/Вводные!K139 -> 2.2863925 | K12: =Вводные!L123/Вводные!L139 -> 2.2965465 | L12: =Вводные!M123/Вводные!M139 -> 2.9884997 | M12: =Вводные!N123/Вводные!N139 -> 3.541188 | N12: =Вводные!O123/Вводные!O139 -> 3.8613365 | O12: =Вводные!P123/Вводные!P139 -> 4.0883836 | P12: =Вводные!Q123/Вводные!Q139 -> 4.2571432 | R12: =Вводные!S123/Вводные!S139 -> 1.71856 | S12: =Вводные!T123/Вводные!T139 -> 2.2755963 | T12: =Вводные!U123/Вводные!U139 -> 4.0751649 | U12: =Вводные!V123/Вводные!V139 -> 4.5392154 | V12: =Вводные!W123/Вводные!W139 -> 4.4687741 | W12: =Вводные!X123/Вводные!X139 -> 4.3495576 | X12: =Вводные!Y123/Вводные!Y139 -> 4.2990127 | Z12: =Вводные!AA123/Вводные!AA139 -> 2.2931667 | AA12: =Вводные!AB123/Вводные!AB139 -> 2.3043937 | AB12: =Вводные!AC123/Вводные!AC139 -> 2.505488 | AC12: =Вводные!AD123/Вводные!AD139 -> 2.7487461 | AD12: =Вводные!AE123/Вводные!AE139 -> 3.0237081 | AE12: =Вводные!AF123/Вводные!AF139 -> 3.3297301 | AF12: =Вводные!AG123/Вводные!AG139 -> 3.5107175 | AH12: ='Группа компаний Конс.Отчетность'!L13/'Группа компаний Конс.Отчетность'!L30 -> 2.0886358 | AI12: ='Группа компаний Конс.Отчетность'!M13/'Группа компаний Конс.Отчетность'!M30 -> 2.1495598 | AJ12: ='Группа компаний Конс.Отчетность'!N13/'Группа компаний Конс.Отчетность'!N30 -> 2.7983197 | AK12: ='Группа компаний Конс.Отчетность'!O13/'Группа компаний Конс.Отчетность'!O30 -> 3.4380493 | AL12: ='Группа компаний Конс.Отчетность'!P13/'Группа компаний Конс.Отчетность'!P30 -> 3.8211161 | AM12: ='Группа компаний Конс.Отчетность'!Q13/'Группа компаний Конс.Отчетность'!Q30 -> 4.0096609 | AN12: ='Группа компаний Конс.Отчетность'!R13/'Группа компаний Конс.Отчетность'!R30 -> 4.1528532
A13: Коэффициент абсолютной ликвидности | B13: =Вводные!C125/Вводные!C139 -> 1.668125 | C13: =Вводные!D125/Вводные!D139 -> 1.5227922 | D13: =Вводные!E125/Вводные!E139 -> 1.859161 | E13: =Вводные!F125/Вводные!F139 -> 2.3085831 | F13: =Вводные!G125/Вводные!G139 -> 2.7489995 | G13: =Вводные!H125/Вводные!H139 -> 3.0144354 | H13: =Вводные!I125/Вводные!I139 -> 3.3188285 | J13: =Вводные!K125/Вводные!K139 -> 1.6128174 | K13: =Вводные!L125/Вводные!L139 -> 1.6227238 | L13: =Вводные!M125/Вводные!M139 -> 2.3652407 | M13: =Вводные!N125/Вводные!N139 -> 2.964947 | N13: =Вводные!O125/Вводные!O139 -> 3.3287772 | O13: =Вводные!P125/Вводные!P139 -> 3.596373 | P13: =Вводные!Q125/Вводные!Q139 -> 3.8027452 | R13: =Вводные!S125/Вводные!S139 -> 1.71856 | S13: =Вводные!T125/Вводные!T139 -> 2.2755963 | T13: =Вводные!U125/Вводные!U139 -> 4.0751649 | U13: =Вводные!V125/Вводные!V139 -> 4.5392154 | V13: =Вводные!W125/Вводные!W139 -> 4.4687741 | W13: =Вводные!X125/Вводные!X139 -> 4.3495576 | X13: =Вводные!Y125/Вводные!Y139 -> 4.2990127 | Z13: =Вводные!AA125/Вводные!AA139 -> 2.2265 | AA13: =Вводные!AB125/Вводные!AB139 -> 2.1990724 | AB13: =Вводные!AC125/Вводные!AC139 -> 2.4451794 | AC13: =Вводные!AD125/Вводные!AD139 -> 2.7064949 | AD13: =Вводные!AE125/Вводные!AE139 -> 2.9911927 | AE13: =Вводные!AF125/Вводные!AF139 -> 3.3033039 | AF13: =Вводные!AG125/Вводные!AG139 -> 3.4884596 | AH13: ='Группа компаний Конс.Отчетность'!L15/'Группа компаний Конс.Отчетность'!L30 -> 1.6466794 | AI13: ='Группа компаний Конс.Отчетность'!M15/'Группа компаний Конс.Отчетность'!M30 -> 1.6071732 | AJ13: ='Группа компаний Конс.Отчетность'!N15/'Группа компаний Конс.Отчетность'!N30 -> 2.3034222 | AK13: ='Группа компаний Конс.Отчетность'!O15/'Группа компаний Конс.Отчетность'!O30 -> 3.0159237 | AL13: ='Группа компаний Конс.Отчетность'!P15/'Группа компаний Конс.Отчетность'!P30 -> 3.4663311 | AM13: ='Группа компаний Конс.Отчетность'!Q15/'Группа компаний Конс.Отчетность'!Q30 -> 3.7043768 | AN13: ='Группа компаний Конс.Отчетность'!R15/'Группа компаний Конс.Отчетность'!R30 -> 3.8809713
A14: Показатели финансовой устойчивости компании
A15: Коэффициент финансовой независимости | B15: =Вводные!C129/Вводные!C113 -> 0.86070252 | C15: =Вводные!D129/Вводные!D113 -> 0.89180139 | D15: =Вводные!E129/Вводные!E113 -> 0.90965831 | E15: =Вводные!F129/Вводные!F113 -> 0.91137813 | F15: =Вводные!G129/Вводные!G113 -> 0.91288931 | G15: =Вводные!H129/Вводные!H113 -> 0.91299553 | H15: =Вводные!I129/Вводные!I113 -> 0.91330252 | J15: =Вводные!K129/Вводные!K113 -> 0.69725787 | K15: =Вводные!L129/Вводные!L113 -> 0.69823024 | L15: =Вводные!M129/Вводные!M113 -> 0.71097298 | M15: =Вводные!N129/Вводные!N113 -> 0.71992147 | N15: =Вводные!O129/Вводные!O113 -> 0.72114936 | O15: =Вводные!P129/Вводные!P113 -> 0.71996205 | P15: =Вводные!Q129/Вводные!Q113 -> 0.71747661 | R15: =Вводные!S129/Вводные!S113 -> 0.68364161 | S15: =Вводные!T129/Вводные!T113 -> 0.71124318 | T15: =Вводные!U129/Вводные!U113 -> 0.7535335 | U15: =Вводные!V129/Вводные!V113 -> 0.75999964 | V15: =Вводные!W129/Вводные!W113 -> 0.75874547 | W15: =Вводные!X129/Вводные!X113 -> 0.75390735 | X15: =Вводные!Y129/Вводные!Y113 -> 0.75038656 | Z15: =Вводные!AA129/Вводные!AA113 -> 0.69974478 | AA15: =Вводные!AB129/Вводные!AB113 -> 0.71082122 | AB15: =Вводные!AC129/Вводные!AC113 -> 0.67774671 | AC15: =Вводные!AD129/Вводные!AD113 -> 0.67965044 | AD15: =Вводные!AE129/Вводные!AE113 -> 0.69455669 | AE15: =Вводные!AF129/Вводные!AF113 -> 0.71445409 | AF15: =Вводные!AG129/Вводные!AG113 -> 0.72441836 | AH15: ='Группа компаний Конс.Отчетность'!L19/'Группа компаний Конс.Отчетность'!L3 -> 0.77377033 | AI15: ='Группа компаний Конс.Отчетность'!M19/'Группа компаний Конс.Отчетность'!M3 -> 0.79213636 | AJ15: ='Группа компаний Конс.Отчетность'!N19/'Группа компаний Конс.Отчетность'!N3 -> 0.80395427 | AK15: ='Группа компаний Конс.Отчетность'!O19/'Группа компаний Конс.Отчетность'!O3 -> 0.80566704 | AL15: ='Группа компаний Конс.Отчетность'!P19/'Группа компаний Конс.Отчетность'!P3 -> 0.80364018 | AM15: ='Группа компаний Конс.Отчетность'!Q19/'Группа компаний Конс.Отчетность'!Q3 -> 0.79944677 | AN15: ='Группа компаний Конс.Отчетность'!R19/'Группа компаний Конс.Отчетность'!R3 -> 0.79581639
A16: Коэффициент финансовой устойчивости | B16: =(Вводные!C129+Вводные!C136)/Вводные!C113 -> 0.88004522 | C16: =(Вводные!D129+Вводные!D136)/Вводные!D113 -> 0.91165293 | D16: =(Вводные!E129+Вводные!E136)/Вводные!E113 -> 0.91174891 | E16: =(Вводные!F129+Вводные!F136)/Вводные!F113 -> 0.91342894 | F16: =(Вводные!G129+Вводные!G136)/Вводные!G113 -> 0.91490514 | G16: =(Вводные!H129+Вводные!H136)/Вводные!H113 -> 0.9150089 | H16: =(Вводные!I129+Вводные!I136)/Вводные!I113 -> 0.91530879 | J16: =(Вводные!K129+Вводные!K136)/Вводные!K113 -> 0.85590818 | K16: =(Вводные!L129+Вводные!L136)/Вводные!L113 -> 0.85631495 | L16: =(Вводные!M129+Вводные!M136)/Вводные!M113 -> 0.85586069 | M16: =(Вводные!N129+Вводные!N136)/Вводные!N113 -> 0.85397203 | N16: =(Вводные!O129+Вводные!O136)/Вводные!O113 -> 0.84828588 | O16: =(Вводные!P129+Вводные!P136)/Вводные!P113 -> 0.84131247 | P16: =(Вводные!Q129+Вводные!Q136)/Вводные!Q113 -> 0.83357512 | R16: =(Вводные!S129+Вводные!S136)/Вводные!S113 -> 0.92608449 | S16: =(Вводные!T129+Вводные!T136)/Вводные!T113 -> 0.96612003 | T16: =(Вводные!U129+Вводные!U136)/Вводные!U113 -> 0.9392656 | U16: =(Вводные!V129+Вводные!V136)/Вводные!V113 -> 0.88971554 | V16: =(Вводные!W129+Вводные!W136)/Вводные!W113 -> 0.85256667 | W16: =(Вводные!X129+Вводные!X136)/Вводные!X113 -> 0.82880511 | X16: =(Вводные!Y129+Вводные!Y136)/Вводные!Y113 -> 0.81510116 | Z16: =(Вводные!AA129+Вводные!AA136)/Вводные!AA113 -> 0.69974478 | AA16: =(Вводные!AB129+Вводные!AB136)/Вводные!AB113 -> 0.71082122 | AB16: =(Вводные!AC129+Вводные!AC136)/Вводные!AC113 -> 0.67774671 | AC16: =(Вводные!AD129+Вводные!AD136)/Вводные!AD113 -> 0.67965044 | AD16: =(Вводные!AE129+Вводные!AE136)/Вводные!AE113 -> 0.69455669 | AE16: =(Вводные!AF129+Вводные!AF136)/Вводные!AF113 -> 0.71445409 | AF16: =(Вводные!AG129+Вводные!AG136)/Вводные!AG113 -> 0.72441836 | AH16: =('Группа компаний Конс.Отчетность'!L19+'Группа компаний Конс.Отчетность'!L27)/'Группа компаний Конс.Отчетность'!L3 -> 0.87312897 | AI16: =('Группа компаний Конс.Отчетность'!M19+'Группа компаний Конс.Отчетность'!M27)/'Группа компаний Конс.Отчетность'!M3 -> 0.89332063 | AJ16: =('Группа компаний Конс.Отчетность'!N19+'Группа компаний Конс.Отчетность'!N27)/'Группа компаний Конс.Отчетность'!N3 -> 0.89054158 | AK16: =('Группа компаний Конс.Отчетность'!O19+'Группа компаний Конс.Отчетность'!O27)/'Группа компаний Конс.Отчетность'!O3 -> 0.88398834 | AL16: =('Группа компаний Конс.Отчетность'!P19+'Группа компаний Конс.Отчетность'!P27)/'Группа компаний Конс.Отчетность'!P3 -> 0.87473234 | AM16: =('Группа компаний Конс.Отчетность'!Q19+'Группа компаний Конс.Отчетность'!Q27)/'Группа компаний Конс.Отчетность'!Q3 -> 0.86524196 | AN16: =('Группа компаний Конс.Отчетность'!R19+'Группа компаний Конс.Отчетность'!R27)/'Группа компаний Конс.Отчетность'!R3 -> 0.85767047
A17: Коэффициент обеспеченности собственными оборотными средствами | B17: =(Вводные!C123-Вводные!C139)/Вводные!C123 -> 0.48865452 | C17: =(Вводные!D123-Вводные!D139)/Вводные!D123 -> 0.484481 | D17: =(Вводные!E123-Вводные!E139)/Вводные!E123 -> 0.55823589 | E17: =(Вводные!F123-Вводные!F139)/Вводные!F123 -> 0.62975838 | F17: =(Вводные!G123-Вводные!G139)/Вводные!G123 -> 0.68046878 | G17: =(Вводные!H123-Вводные!H139)/Вводные!H123 -> 0.70445705 | H17: =(Вводные!I123-Вводные!I139)/Вводные!I123 -> 0.72803332 | J17: =(Вводные!K123-Вводные!K139)/Вводные!K123 -> 0.56262977 | K17: =(Вводные!L123-Вводные!L139)/Вводные!L123 -> 0.56456357 | L17: =(Вводные!M123-Вводные!M139)/Вводные!M123 -> 0.66538394 | M17: =(Вводные!N123-Вводные!N139)/Вводные!N123 -> 0.7176089 | N17: =(Вводные!O123-Вводные!O139)/Вводные!O123 -> 0.74102231 | O17: =(Вводные!P123-Вводные!P139)/Вводные!P123 -> 0.75540455 | P17: =(Вводные!Q123-Вводные!Q139)/Вводные!Q123 -> 0.76510069 | R17: =(Вводные!S123-Вводные!S139)/Вводные!S123 -> 0.41811749 | S17: =(Вводные!T123-Вводные!T139)/Вводные!T123 -> 0.56055475 | T17: =(Вводные!U123-Вводные!U139)/Вводные!U123 -> 0.75461116 | U17: =(Вводные!V123-Вводные!V139)/Вводные!V123 -> 0.77969761 | V17: =(Вводные!W123-Вводные!W139)/Вводные!W123 -> 0.77622498 | W17: =(Вводные!X123-Вводные!X139)/Вводные!X123 -> 0.77009156 | X17: =(Вводные!Y123-Вводные!Y139)/Вводные!Y123 -> 0.76738845 | Z17: =(Вводные!AA123-Вводные!AA139)/Вводные!AA123 -> 0.5639218 | AA17: =(Вводные!AB123-Вводные!AB139)/Вводные!AB123 -> 0.56604637 | AB17: =(Вводные!AC123-Вводные!AC139)/Вводные!AC123 -> 0.60087616 | AC17: =(Вводные!AD123-Вводные!AD139)/Вводные!AD123 -> 0.63619775 | AD17: =(Вводные!AE123-Вводные!AE139)/Вводные!AE123 -> 0.66928025 | AE17: =(Вводные!AF123-Вводные!AF139)/Вводные!AF123 -> 0.69967536 | AF17: =(Вводные!AG123-Вводные!AG139)/Вводные!AG123 -> 0.71515794 | AH17: =('Группа компаний Конс.Отчетность'!L13-'Группа компаний Конс.Отчетность'!L30)/'Группа компаний Конс.Отчетность'!L13 -> 0.52121859 | AI17: =('Группа компаний Конс.Отчетность'!M13-'Группа компаний Конс.Отчетность'!M30)/'Группа компаний Конс.Отчетность'!M13 -> 0.53478846 | AJ17: =('Группа компаний Конс.Отчетность'!N13-'Группа компаний Конс.Отчетность'!N30)/'Группа компаний Конс.Отчетность'!N13 -> 0.64264269 | AK17: =('Группа компаний Конс.Отчетность'!O13-'Группа компаний Конс.Отчетность'!O30)/'Группа компаний Конс.Отчетность'!O13 -> 0.70913739 | AL17: =('Группа компаний Конс.Отчетность'!P13-'Группа компаний Конс.Отчетность'!P30)/'Группа компаний Конс.Отчетность'!P13 -> 0.73829636 | AM17: =('Группа компаний Конс.Отчетность'!Q13-'Группа компаний Конс.Отчетность'!Q30)/'Группа компаний Конс.Отчетность'!Q13 -> 0.75060235 | AN17: =('Группа компаний Конс.Отчетность'!R13-'Группа компаний Конс.Отчетность'!R30)/'Группа компаний Конс.Отчетность'!R13 -> 0.75920169
A18: Коэффициент маневренности собственного капитала | B18: =(Вводные!C123-Вводные!C139)/Вводные!C129 -> 0.13318398 | C18: =(Вводные!D123-Вводные!D139)/Вводные!D129 -> 0.093101369 | D18: =(Вводные!E123-Вводные!E139)/Вводные!E129 -> 0.12259397 | E18: =(Вводные!F123-Вводные!F139)/Вводные!F129 -> 0.1615708 | F18: =(Вводные!G123-Вводные!G139)/Вводные!G129 -> 0.19850896 | G18: =(Вводные!H123-Вводные!H139)/Вводные!H129 -> 0.2218905 | H18: =(Вводные!I123-Вводные!I139)/Вводные!I129 -> 0.24823283 | J18: =(Вводные!K123-Вводные!K139)/Вводные!K129 -> 0.26583942 | K18: =(Вводные!L123-Вводные!L139)/Вводные!L129 -> 0.26680934 | L18: =(Вводные!M123-Вводные!M139)/Вводные!M129 -> 0.40313907 | M18: =(Вводные!N123-Вводные!N139)/Вводные!N129 -> 0.51545139 | N18: =(Вводные!O123-Вводные!O139)/Вводные!O129 -> 0.6019629 | O18: =(Вводные!P123-Вводные!P139)/Вводные!P129 -> 0.68071359 | P18: =(Вводные!Q123-Вводные!Q139)/Вводные!Q129 -> 0.75552242 | R18: =(Вводные!S123-Вводные!S139)/Вводные!S129 -> 0.077690897 | S18: =(Вводные!T123-Вводные!T139)/Вводные!T129 -> 0.060762857 | T18: =(Вводные!U123-Вводные!U139)/Вводные!U129 -> 0.24785664 | U18: =(Вводные!V123-Вводные!V139)/Вводные!V129 -> 0.5135798 | V18: =(Вводные!W123-Вводные!W139)/Вводные!W129 -> 0.67402432 | W18: =(Вводные!X123-Вводные!X139)/Вводные!X129 -> 0.76060693 | X18: =(Вводные!Y123-Вводные!Y139)/Вводные!Y129 -> 0.81289253 | Z18: =(Вводные!AA123-Вводные!AA139)/Вводные!AA129 -> 0.55488808 | AA18: =(Вводные!AB123-Вводные!AB139)/Вводные!AB129 -> 0.53065801 | AB18: =(Вводные!AC123-Вводные!AC139)/Вводные!AC129 -> 0.71582564 | AC18: =(Вводные!AD123-Вводные!AD139)/Вводные!AD129 -> 0.82426201 | AD18: =(Вводные!AE123-Вводные!AE139)/Вводные!AE129 -> 0.88996065 | AE18: =(Вводные!AF123-Вводные!AF139)/Вводные!AF129 -> 0.9311234 | AF18: =(Вводные!AG123-Вводные!AG139)/Вводные!AG129 -> 0.95512164 | AH18: =('Группа компаний Конс.Отчетность'!L13-'Группа компаний Конс.Отчетность'!L30)/'Группа компаний Конс.Отчетность'!L19 -> 0.17849787 | AI18: =('Группа компаний Конс.Отчетность'!M13-'Группа компаний Конс.Отчетность'!M30)/'Группа компаний Конс.Отчетность'!M19 -> 0.15481464 | AJ18: =('Группа компаний Конс.Отчетность'!N13-'Группа компаний Конс.Отчетность'!N30)/'Группа компаний Конс.Отчетность'!N19 -> 0.24484133 | AK18: =('Группа компаний Конс.Отчетность'!O13-'Группа компаний Конс.Отчетность'!O30)/'Группа компаний Конс.Отчетность'!O19 -> 0.35106579 | AL18: =('Группа компаний Конс.Отчетность'!P13-'Группа компаний Конс.Отчетность'!P30)/'Группа компаний Конс.Отчетность'!P19 -> 0.43974233 | AM18: =('Группа компаний Конс.Отчетность'!Q13-'Группа компаний Конс.Отчетность'!Q30)/'Группа компаний Конс.Отчетность'!Q19 -> 0.50732084 | AN18: =('Группа компаний Конс.Отчетность'!R13-'Группа компаний Конс.Отчетность'!R30)/'Группа компаний Конс.Отчетность'!R19 -> 0.56387894

Sheet План факт анализ
A1: Отчёт о прибылях и убытках, тыс. руб. | B1: А | F1: Б | J1: В | N1: Г | R1: Группа (Консолидация)
B2: 2025 план | C2: 2025 факт | D2: Δ (+-) тыс.руб. | E2: Δ, (+-)% | F2: 2025 план | G2: 2025 факт | H2: Δ (+-) тыс.руб. | I2: Δ, (+-)% | J2: 2025 план | K2: 2025 факт | L2: Δ (+-) тыс.руб. | M2: Δ, (+-)% | N2: 2025 план | O2: 2025 факт | P2: Δ (+-) тыс.руб. | Q2: Δ, (+-)% | R2: 2025 план | S2: 2025 факт | T2: Δ (+-) тыс.руб. | U2: Δ, (+-)%
A3: Выручка от реализации | B3: 51450 | C3: 51502 | D3: =C3-B3 -> 52 | E3: =D3/B3 -> 0.00101069 | F3: 42500 | G3: 43215.028 | H3: =G3-F3 -> 715.02786 | I3: =H3/F3 -> 0.016824185 | J3: 23700 | K3: 24565 | L3: =K3-J3 -> 865 | M3: =L3/J3 -> 0.03649789 | N3: 8500 | O3: 7911.8422 | P3: =O3-N3 -> -588.15778 | Q3: =P3/N3 -> -0.069195033 | R3: 115131 | S3: 116763 | T3: =S3-R3 -> 1632 | U3: =T3/R3 -> 0.014175157
A4: Комиссии за обработку платежей и переводов | B4: 51450 | C4: 51502 | D4: =C4-B4 -> 52 | E4: =D4/B4 -> 0.00101069 | F4: 0 | G4: 0 | H4: =G4-F4 -> 0 | I4: 0 | J4: 0 | K4: 0 | L4: =K4-J4 -> 0 | M4: 0 | N4: 0 | O4: 0 | P4: =O4-N4 -> 0 | Q4: 0 | R4: 51318 | S4: 51370 | T4: =S4-R4 -> 52 | U4: =T4/R4 -> 0.0010132897
A5: Разработка программного обеспечения | B5: 0 | C5: 0 | D5: =C5-B5 -> 0 | E5: 0 | F5: 27500 | G5: 28089.768 | H5: =G5-F5 -> 589.76811 | I5: =H5/F5 -> 0.021446113 | J5: 0 | K5: 0 | L5: =K5-J5 -> 0 | M5: 0 | N5: 0 | O5: 0 | P5: =O5-N5 -> 0 | Q5: 0 | R5: 26290 | S5: 26880 | T5: =S5-R5 -> 590 | U5: =T5/R5 -> 0.022441993
A6: Аутсорсинговые услуги | B6: 0 | C6: 0 | D6: =C6-B6 -> 0 | E6: 0 | F6: 15000 | G6: 15125.26 | H6: =G6-F6 -> 125.25975 | I6: =H6/F6 -> 0.0083506501 | J6: 0 | K6: 0 | L6: =K6-J6 -> 0 | M6: 0 | N6: 0 | O6: 0 | P6: =O6-N6 -> 0 | Q6: 0 | R6: 13823 | S6: 13948 | T6: =S6-R6 -> 125 | U6: =T6/R6 -> 0.0090428995
A7: Комиссии трейдинговой площадки | B7: 0 | C7: 0 | D7: =C7-B7 -> 0 | E7: 0 | F7: 0 | G7: 0 | H7: =G7-F7 -> 0 | I7: 0 | J7: 23700 | K7: 24565 | L7: =K7-J7 -> 865 | M7: =L7/J7 -> 0.03649789 | N7: 0 | O7: 0 | P7: =O7-N7 -> 0 | Q7: 0 | R7: 23700 | S7: 24565 | T7: =S7-R7 -> 865 | U7: =T7/R7 -> 0.03649789
A8: Комиссии за услуги бронирования | B8: 0 | C8: 0 | D8: =C8-B8 -> 0 | E8: 0 | F8: 0 | G8: 0 | H8: =G8-F8 -> 0 | I8: 0 | J8: 0 | K8: 0 | L8: =K8-J8 -> 0 | M8: 0 | N8: 8500 | O8: 7911.8422 | P8: =O8-N8 -> -588.15778 | Q8: =P8/N8 -> -0.069195033 | R8: 0 | S8: 0 | T8: =S8-R8 -> 0 | U8: 0
A9: Себестоимость реализации: | B9: 17350 | C9: 17365 | D9: =C9-B9 -> 15 | E9: =D9/B9 -> 0.00086455331 | F9: 20300 | G9: 20311.063 | H9: =G9-F9 -> 11.063095 | I9: =H9/F9 -> 0.00054498006 | J9: 14950 | K9: 15384 | L9: =K9-J9 -> 434 | M9: =L9/J9 -> 0.0290301 | N9: 2350 | O9: 2421.0911 | P9: =O9-N9 -> 71.091111 | Q9: =P9/N9 -> 0.030251537 | R9: 50290 | S9: 50750 | T9: =S9-R9 -> 460 | U9: =T9/R9 -> 0.0091469477
A10: Прямые расходы на персонал | B10: 13710 | C10: 13690.913 | D10: =C10-B10 -> -19.0867 | E10: =D10/B10 -> -0.0013921736 | F10: 16000 | G10: 16013.648 | H10: =G10-F10 -> 13.648365 | I10: =H10/F10 -> 0.00085302284 | J10: 13350 | K10: 13540 | L10: =K10-J10 -> 190 | M10: =L10/J10 -> 0.01423221 | N10: 1800 | O10: 1834.98 | P10: =O10-N10 -> 34.98 | Q10: =P10/N10 -> 0.019433333 | R10: 41960 | S10: 42145 | T10: =S10-R10 -> 185 | U10: =T10/R10 -> 0.0044089609
A11: Оборудование, лицензии и программное обеспечение | B11: 3450 | C11: 3484.7242 | D11: =C11-B11 -> 34.724229 | E11: =D11/B11 -> 0.010064994 | F11: 2900 | G11: 2979.0654 | H11: =G11-F11 -> 79.065369 | I11: =H11/F11 -> 0.02726392 | J11: 1500 | K11: 1724 | L11: =K11-J11 -> 224 | M11: =L11/J11 -> 0.14933333 | N11: 500 | O11: 531.66667 | P11: =O11-N11 -> 31.666667 | Q11: =P11/N11 -> 0.063333333 | R11: 6640 | S11: 6978 | T11: =S11-R11 -> 338 | U11: =T11/R11 -> 0.050903614
A12: Прочие расходы | B12: 190 | C12: 189.36247 | D12: =C12-B12 -> -0.63752922 | E12: =D12/B12 -> -0.003355417 | F12: 1400 | G12: 1318.3494 | H12: =G12-F12 -> -81.650639 | I12: =H12/F12 -> -0.058321885 | J12: 100 | K12: 120 | L12: =K12-J12 -> 20 | M12: =L12/J12 -> 0.2 | N12: 50 | O12: 54.444444 | P12: =O12-N12 -> 4.4444444 | Q12: =P12/N12 -> 0.088888889 | R12: 1690 | S12: 1628 | T12: =S12-R12 -> -62 | U12: =T12/R12 -> -0.036686391
A13: Валовая прибыль | B13: 34100 | C13: 34137 | D13: =C13-B13 -> 37 | E13: =D13/B13 -> 0.001085044 | F13: 22200 | G13: 22903.965 | H13: =G13-F13 -> 703.96477 | I13: =H13/F13 -> 0.031710125 | J13: 8750 | K13: 9181 | L13: =K13-J13 -> 431 | M13: =L13/J13 -> 0.049257143 | N13: 6150 | O13: 5490.7511 | P13: =O13-N13 -> -659.24889 | Q13: =P13/N13 -> -0.10719494 | R13: 64841 | S13: 66013 | T13: =S13-R13 -> 1172 | U13: =T13/R13 -> 0.018074983
A14: Операционные расходы | B14: 15614 | C14: 15549 | D14: =C14-B14 -> -65 | E14: =D14/B14 -> -0.0041629307 | F14: 13878 | G14: 14001.669 | H14: =G14-F14 -> 123.66903 | I14: =H14/F14 -> 0.0089111563 | J14: 8749 | K14: 9138 | L14: =K14-J14 -> 389 | M14: =L14/J14 -> 0.044462224 | N14: 3945 | O14: 3944.4444 | P14: =O14-N14 -> -0.55555556 | Q14: =P14/N14 -> -0.00014082524 | R14: 38032 | S14: 38480 | T14: =S14-R14 -> 448 | U14: =T14/R14 -> 0.011779554
A15: Расходы на персонал | B15: 7400 | C15: 7405.1667 | D15: =C15-B15 -> 5.1666667 | E15: =D15/B15 -> 0.0006981982 | F15: 4600 | G15: 4606.9184 | H15: =G15-F15 -> 6.918402 | I15: =H15/F15 -> 0.0015040004 | J15: 2700 | K15: 2715 | L15: =K15-J15 -> 15 | M15: =L15/J15 -> 0.0055555556 | N15: 3180 | O15: 3177.7778 | P15: =O15-N15 -> -2.2222222 | Q15: =P15/N15 -> -0.00069881202 | R15: 14623 | S15: 14650 | T15: =S15-R15 -> 27 | U15: =T15/R15 -> 0.0018464063
A16: Аренда | B16: 864 | C16: 863.83333 | D16: =C16-B16 -> -0.16666667 | E16: =D16/B16 -> -0.00019290123 | F16: 778 | G16: 777.8705 | H16: =G16-F16 -> -0.12949848 | I16: =H16/F16 -> -0.00016645049 | J16: 549 | K16: 549 | L16: =K16-J16 -> 0 | M16: =L16/J16 -> 0 | N16: 200 | O16: 200 | P16: =O16-N16 -> 0 | Q16: =P16/N16 -> 0 | R16: 2191 | S16: 2191 | T16: =S16-R16 -> 0 | U16: =T16/R16 -> 0
A17: Реклама и маркетинг | B17: 3800 | C17: 3767 | D17: =C17-B17 -> -33 | E17: =D17/B17 -> -0.0086842105 | F17: 6800 | G17: 6871.1894 | H17: =G17-F17 -> 71.18943 | I17: =H17/F17 -> 0.010469034 | J17: 4400 | K17: 4700 | L17: =K17-J17 -> 300 | M17: =L17/J17 -> 0.068181818 | N17: 360 | O17: 366.66667 | P17: =O17-N17 -> 6.6666667 | Q17: =P17/N17 -> 0.018518519 | R17: 15000 | S17: 15338 | T17: =S17-R17 -> 338 | U17: =T17/R17 -> 0.022533333
A18: Оборудование, лицензии и программное обеспечение | B18: 2350 | C18: 2331 | D18: =C18-B18 -> -19 | E18: =D18/B18 -> -0.0080851064 | F18: 1500 | G18: 1555.741 | H18: =G18-F18 -> 55.741003 | I18: =H18/F18 -> 0.037160669 | J18: 1000 | K18: 1024 | L18: =K18-J18 -> 24 | M18: =L18/J18 -> 0.024 | N18: 200 | O18: 196 | P18: =O18-N18 -> -4 | Q18: =P18/N18 -> -0.02 | R18: 4850 | S18: 4911 | T18: =S18-R18 -> 61 | U18: =T18/R18 -> 0.01257732
A19: Прочие расходы | B19: 1200 | C19: 1182 | D19: =C19-B19 -> -18 | E19: =D19/B19 -> -0.015 | F19: 200 | G19: 189.94969 | H19: =G19-F19 -> -10.050309 | I19: =H19/F19 -> -0.050251547 | J19: 100 | K19: 150 | L19: =K19-J19 -> 50 | M19: =L19/J19 -> 0.5 | N19: 5 | O19: 4 | P19: =O19-N19 -> -1 | Q19: =P19/N19 -> -0.2 | R19: 1368 | S19: 1390 | T19: =S19-R19 -> 22 | U19: =T19/R19 -> 0.016081871
A20: Операционная прибыль | B20: 18486 | C20: 18588 | D20: =C20-B20 -> 102 | E20: =D20/B20 -> 0.0055176891 | F20: 8322 | G20: 8902.2957 | H20: =G20-F20 -> 580.29574 | I20: =H20/F20 -> 0.069730322 | J20: 1 | K20: 43 | L20: =K20-J20 -> 42 | M20: =L20/J20 -> 42 | N20: 2205 | O20: 1546.3067 | P20: =O20-N20 -> -658.69333 | Q20: =P20/N20 -> -0.29872714 | R20: 26809 | S20: 27533 | T20: =S20-R20 -> 724 | U20: =T20/R20 -> 0.027005856
A21: Внереализационные доходы | B21: 359 | C21: 385 | D21: =C21-B21 -> 26 | E21: =D21/B21 -> 0.072423398 | F21: 619 | G21: 668.71228 | H21: =G21-F21 -> 49.712276 | I21: =H21/F21 -> 0.080310623 | J21: 800 | K21: 803 | L21: =K21-J21 -> 3 | M21: =L21/J21 -> 0.00375 | N21: 10 | O21: 15 | P21: =O21-N21 -> 5 | Q21: =P21/N21 -> 0.5 | R21: 2274 | S21: 2205 | T21: =S21-R21 -> -69 | U21: =T21/R21 -> -0.030343008
A22: Инвестиционный доход | B22: 109 | C22: 109 | D22: =C22-B22 -> 0 | E22: =D22/B22 -> 0 | F22: 469 | G22: 468.71228 | H22: =G22-F22 -> -0.28772414 | I22: =H22/F22 -> -0.0006134843 | J22: 795 | K22: 795 | L22: =K22-J22 -> 0 | M22: =L22/J22 -> 0 | N22: 0 | O22: 0 | P22: =O22-N22 -> 0 | Q22: 0 | R22: 1373 | S22: 1373 | T22: =S22-R22 -> 0 | U22: =T22/R22 -> 0
A23: Прочие доходы | B23: 250 | C23: 276 | D23: =C23-B23 -> 26 | E23: =D23/B23 -> 0.104 | F23: 150 | G23: 200 | H23: =G23-F23 -> 50 | I23: =H23/F23 -> 0.33333333 | J23: 5 | K23: 8 | L23: =K23-J23 -> 3 | M23: =L23/J23 -> 0.6 | N23: 10 | O23: 15 | P23: =O23-N23 -> 5 | Q23: =P23/N23 -> 0.5 | R23: 405 | S23: 484 | T23: =S23-R23 -> 79 | U23: =T23/R23 -> 0.19506173
A24: Доля прибыли ассоциированной компании | D24: =C24-B24 -> 0 | E24: 0 | H24: =G24-F24 -> 0 | I24: 0 | L24: =K24-J24 -> 0 | M24: 0 | P24: =O24-N24 -> 0 | Q24: 0 | R24: 496 | S24: 349 | T24: =S24-R24 -> -147 | U24: =T24/R24 -> -0.29637097
A25: Внереализационные расходы | B25: 101 | C25: 100 | D25: =C25-B25 -> -1 | E25: =D25/B25 -> -0.0099009901 | F25: 80 | G25: 100 | H25: =G25-F25 -> 20 | I25: =H25/F25 -> 0.25 | J25: 5 | K25: 10 | L25: =K25-J25 -> 5 | M25: =L25/J25 -> 1 | N25: 10 | O25: 12 | P25: =O25-N25 -> 2 | Q25: =P25/N25 -> 0.2 | R25: 186 | S25: 210 | T25: =S25-R25 -> 24 | U25: =T25/R25 -> 0.12903226
A26: Проценты уплаченные (аннуитет, полное погашение долга в конце 2026) | B26: 51 | C26: 51 | D26: =C26-B26 -> 0 | E26: =D26/B26 -> 0 | F26: 0 | G26: 0 | H26: =G26-F26 -> 0 | I26: 0 | J26: 0 | K26: 0 | L26: =K26-J26 -> 0 | M26: 0 | N26: 0 | O26: 0 | P26: =O26-N26 -> 0 | Q26: 0 | R26: 51 | S26: 51 | T26: =S26-R26 -> 0 | U26: =T26/R26 -> 0
A27: Прочие расходы | B27: 50 | C27: 49 | D27: =C27-B27 -> -1 | E27: =D27/B27 -> -0.02 | F27: 80 | G27: 100 | H27: =G27-F27 -> 20 | I27: =H27/F27 -> 0.25 | J27: 5 | K27: 10 | L27: =K27-J27 -> 5 | M27: =L27/J27 -> 1 | N27: 10 | O27: 12 | P27: =O27-N27 -> 2 | Q27: =P27/N27 -> 0.2 | R27: 135 | S27: 159 | T27: =S27-R27 -> 24 | U27: =T27/R27 -> 0.17777778
A28: Прибыль до налогообложения | B28: 18744 | C28: 18873 | D28: =C28-B28 -> 129 | E28: =D28/B28 -> 0.0068822023 | F28: 8861 | G28: 9471.008 | H28: =G28-F28 -> 610.00802 | I28: =H28/F28 -> 0.068841893 | J28: 796 | K28: 836 | L28: =K28-J28 -> 40 | M28: =L28/J28 -> 0.050251256 | N28: 2205 | O28: 1549.3067 | P28: =O28-N28 -> -655.69333 | Q28: =P28/N28 -> -0.29736659 | R28: 28897 | S28: 29529 | T28: =S28-R28 -> 632 | U28: =T28/R28 -> 0.021870782
A29: Налог на прибыль | B29: 4686 | C29: 4718.25 | D29: =C29-B29 -> 32.25 | E29: =D29/B29 -> 0.0068822023 | F29: 2215.25 | G29: 2367.752 | H29: =G29-F29 -> 152.502 | I29: =H29/F29 -> 0.068841893 | J29: 199 | K29: 209 | L29: =K29-J29 -> 10 | M29: =L29/J29 -> 0.050251256 | N29: 551.25 | O29: 387.32667 | P29: =O29-N29 -> -163.92333 | Q29: =P29/N29 -> -0.29736659 | R29: 7100 | S29: 7295 | T29: =S29-R29 -> 195 | U29: =T29/R29 -> 0.027464789
A30: Чистая прибыль | B30: 14058 | C30: 14154.75 | D30: =C30-B30 -> 96.75 | E30: =D30/B30 -> 0.0068822023 | F30: 6645.75 | G30: 7103.256 | H30: =G30-F30 -> 457.50601 | I30: =H30/F30 -> 0.068841893 | J30: 597 | K30: 627 | L30: =K30-J30 -> 30 | M30: =L30/J30 -> 0.050251256 | N30: 1653.75 | O30: 1161.98 | P30: =O30-N30 -> -491.77 | Q30: =P30/N30 -> -0.29736659 | R30: 21797 | S30: 22234 | T30: =S30-R30 -> 437 | U30: =T30/R30 -> 0.020048631
A31: принадлежащей группе | D31: =C31-B31 -> 0 | E31: 0 | H31: =G31-F31 -> 0 | I31: 0 | L31: =K31-J31 -> 0 | M31: 0 | P31: =O31-N31 -> 0 | Q31: 0 | R31: 20894 | S31: 21272 | T31: =S31-R31 -> 378 | U31: =T31/R31 -> 0.018091318
A32: принадлежащей неконтролируещей доли | D32: =C32-B32 -> 0 | E32: 0 | H32: =G32-F32 -> 0 | I32: 0 | L32: =K32-J32 -> 0 | M32: 0 | P32: =O32-N32 -> 0 | Q32: 0 | R32: 903 | S32: 961 | T32: =S32-R32 -> 58 | U32: =T32/R32 -> 0.064230343
A33: в т. ч. амортизация | B33: 1132 | C33: 1132 | D33: =C33-B33 -> 0 | E33: =D33/B33 -> 0 | F33: 2494 | G33: 2493.8487 | H33: =G33-F33 -> -0.15126231 | I33: =H33/F33 -> -6.0650484e-05 | J33: 628 | K33: 628 | L33: =K33-J33 -> 0 | M33: =L33/J33 -> 0 | N33: 142 | O33: 141.62944 | P33: =O33-N33 -> -0.37055556 | Q33: =P33/N33 -> -0.0026095462 | R33: 4254 | S33: 4254 | T33: =S33-R33 -> 0 | U33: =T33/R33 -> 0
A34: EBITDA | B34: 19818 | C34: 19947 | D34: =C34-B34 -> 129 | E34: =D34/B34 -> 0.006509234 | F34: 10886 | G34: 11496.144 | H34: =G34-F34 -> 610.14448 | I34: =H34/F34 -> 0.056048547 | J34: 629 | K34: 669 | L34: =K34-J34 -> 40 | M34: =L34/J34 -> 0.063593005 | N34: 2347 | O34: 1690.9361 | P34: =O34-N34 -> -656.06389 | Q34: =P34/N34 -> -0.27953297 | R34: 31829 | S34: 32461 | T34: =S34-R34 -> 632 | U34: =T34/R34 -> 0.019856106

Sheet Факторный анализ
A2: Факторный анализ влияния показателей ОПУ на Чистую Прибыль | B2: А | F2: Б | J2: В | N2: Г | R2: Группа (Консолидация)
B3: 2025 план | C3: 2025 факт | D3: Δ (+-) тыс.руб. | E3: Δ, (+-)% | F3: 2025 план | G3: 2025 факт | H3: Δ (+-) тыс.руб. | I3: Δ, (+-)% | J3: 2025 план | K3: 2025 факт | L3: Δ (+-) тыс.руб. | M3: Δ, (+-)% | N3: 2025 план | O3: 2025 факт | P3: Δ (+-) тыс.руб. | Q3: Δ, (+-)% | R3: 2025 план | S3: 2025 факт | T3: Δ (+-) тыс.руб. | U3: Δ, (+-)%
A4: Выручка от реализации | B4: 51450 | C4: 51502 | D4: =C4-B4 -> 52 | E4: =D4/B4 -> 0.00101069 | F4: 42500 | G4: 43215.028 | H4: =G4-F4 -> 715.02786 | I4: =H4/F4 -> 0.016824185 | J4: 23700 | K4: 24565 | L4: =K4-J4 -> 865 | M4: =L4/J4 -> 0.03649789 | N4: 8500 | O4: 7911.8422 | P4: =O4-N4 -> -588.15778 | Q4: =P4/N4 -> -0.069195033 | R4: 115131 | S4: 116763 | T4: =S4-R4 -> 1632 | U4: =T4/R4 -> 0.014175157
A5: Себестоимость реализации: | B5: 17350 | C5: 17365 | D5: =C5-B5 -> 15 | E5: =D5/B5 -> 0.00086455331 | F5: 20300 | G5: 20311.063 | H5: =G5-F5 -> 11.063095 | I5: =H5/F5 -> 0.00054498006 | J5: 14950 | K5: 15384 | L5: =K5-J5 -> 434 | M5: =L5/J5 -> 0.0290301 | N5: 2350 | O5: 2421.0911 | P5: =O5-N5 -> 71.091111 | Q5: =P5/N5 -> 0.030251537 | R5: 50290 | S5: 50750 | T5: =S5-R5 -> 460 | U5: =T5/R5 -> 0.0091469477
A6: Операционные расходы | B6: 15614 | C6: 15549 | D6: =C6-B6 -> -65 | E6: =D6/B6 -> -0.0041629307 | F6: 13878 | G6: 14001.669 | H6: =G6-F6 -> 123.66903 | I6: =H6/F6 -> 0.0089111563 | J6: 8749 | K6: 9138 | L6: =K6-J6 -> 389 | M6: =L6/J6 -> 0.044462224 | N6: 3945 | O6: 3944.4444 | P6: =O6-N6 -> -0.55555556 | Q6: =P6/N6 -> -0.00014082524 | R6: 38032 | S6: 38480 | T6: =S6-R6 -> 448 | U6: =T6/R6 -> 0.011779554
A7: Внереализационные доходы | B7: 359 | C7: 385 | D7: =C7-B7 -> 26 | E7: =D7/B7 -> 0.072423398 | F7: 619 | G7: 668.71228 | H7: =G7-F7 -> 49.712276 | I7: =H7/F7 -> 0.080310623 | J7: 800 | K7: 803 | L7: =K7-J7 -> 3 | M7: =L7/J7 -> 0.00375 | N7: 10 | O7: 15 | P7: =O7-N7 -> 5 | Q7: =P7/N7 -> 0.5 | R7: 2274 | S7: 2205 | T7: =S7-R7 -> -69 | U7: =T7/R7 -> -0.030343008
A8: Внереализационные расходы | B8: 101 | C8: 100 | D8: =C8-B8 -> -1 | E8: =D8/B8 -> -0.0099009901 | F8: 80 | G8: 100 | H8: =G8-F8 -> 20 | I8: =H8/F8 -> 0.25 | J8: 5 | K8: 10 | L8: =K8-J8 -> 5 | M8: =L8/J8 -> 1 | N8: 10 | O8: 12 | P8: =O8-N8 -> 2 | Q8: =P8/N8 -> 0.2 | R8: 186 | S8: 210 | T8: =S8-R8 -> 24 | U8: =T8/R8 -> 0.12903226
A9: Налог на прибыль | B9: 4686 | C9: 4718.25 | D9: =C9-B9 -> 32.25 | E9: =D9/B9 -> 0.0068822023 | F9: 2215.25 | G9: 2367.752 | H9: =G9-F9 -> 152.502 | I9: =H9/F9 -> 0.068841893 | J9: 199 | K9: 209 | L9: =K9-J9 -> 10 | M9: =L9/J9 -> 0.050251256 | N9: 551.25 | O9: 387.32667 | P9: =O9-N9 -> -163.92333 | Q9: =P9/N9 -> -0.29736659 | R9: 7100 | S9: 7295 | T9: =S9-R9 -> 195 | U9: =T9/R9 -> 0.027464789
A10: Чистая прибыль | B10: 14058 | C10: 14154.75 | D10: =C10-B10 -> 96.75 | E10: =D10/B10 -> 0.0068822023 | F10: 6645.75 | G10: 7103.256 | H10: =G10-F10 -> 457.50601 | I10: =H10/F10 -> 0.068841893 | J10: 597 | K10: 627 | L10: =K10-J10 -> 30 | M10: =L10/J10 -> 0.050251256 | N10: 1653.75 | O10: 1161.98 | P10: =O10-N10 -> -491.77 | Q10: =P10/N10 -> -0.29736659 | R10: 21797 | S10: 22234 | T10: =S10-R10 -> 437 | U10: =T10/R10 -> 0.020048631
A11: Чистая прибыль, % | B11: =B10/B4*100% -> 0.27323615 | C11: =C10/C4*100% -> 0.27483884 | E11: =(C11-B11)/B11 -> 0.005865584 | F11: =F10/F4*100% -> 0.15637059 | G11: =G10/G4*100% -> 0.16437004 | I11: =(G11-F11)/F11 -> 0.051157033 | J11: =J10/J4 -> 0.025189873 | K11: =K10/K4 -> 0.02552412 | M11: =(K11-J11)/J11 -> 0.013269073 | N11: =N10/N4 -> 0.19455882 | O11: =O10/O4 -> 0.14686592 | Q11: =(O11-N11)/N11 -> -0.24513358 | R11: =R10/R4 -> 0.18932347 | S11: =S10/S4 -> 0.19041991 | U11: =(S11-R11)/R11 -> 0.0057913798
A12: Фактор ОПУ на ЧП | B12: 2025 план | C12: 2025 факт | D12: Δ (+-) тыс.руб. | E12: Δ, (+-)% | F12: 2025 план | G12: 2025 факт | H12: Δ (+-) тыс.руб. | I12: Δ, (+-)% | J12: 2025 план | K12: 2025 факт | L12: Δ (+-) тыс.руб. | M12: Δ, (+-)% | N12: 2025 план | O12: 2025 факт | P12: Δ (+-) тыс.руб. | Q12: Δ, (+-)% | R12: 2025 план | S12: 2025 факт | T12: Δ (+-) тыс.руб. | U12: Δ, (+-)%
A13: Выручка от реализации | B13: 51450 | C13: 51502 | D13: =C13-B13 -> 52 | E13: =D13/$B$19 -> 0.0036989614 | F13: 42500 | G13: 43215.028 | H13: =G13-F13 -> 715.02786 | I13: =H13/F19 -> 0.10759175 | J13: 23700 | K13: 24565 | L13: =K13-J13 -> 865 | M13: =L13/$J$19 -> 1.4489112 | N13: 8500 | O13: 7911.8422 | P13: =O13-N13 -> -588.15778 | Q13: =P13/$N$19 -> -0.35565096 | R13: 115131 | S13: 116763 | T13: =S13-R13 -> 1632 | U13: =T13/$R$19 -> 0.074872689
A14: Себестоимость реализации: | B14: 17350 | C14: 17365 | D14: =C14-B14 -> 15 | E14: =-D14/$B$19 -> -0.0010670081 | F14: 20300 | G14: 20311.063 | H14: =G14-F14 -> 11.063095 | I14: =-H14/F19 -> -0.0016646872 | J14: 14950 | K14: 15384 | L14: =K14-J14 -> 434 | M14: =-L14/$J$19 -> -0.72696817 | N14: 2350 | O14: 2421.0911 | P14: =O14-N14 -> 71.091111 | Q14: =-P14/$N$19 -> -0.042987822 | R14: 50290 | S14: 50750 | T14: =S14-R14 -> 460 | U14: =-T14/$R$19 -> -0.021103822
A15: Операционные расходы | B15: 15614 | C15: 15549 | D15: =C15-B15 -> -65 | E15: =-D15/$B$19 -> 0.0046237018 | F15: 13878 | G15: 14001.669 | H15: =G15-F15 -> 123.66903 | I15: =-H15/F19 -> -0.018608739 | J15: 8749 | K15: 9138 | L15: =K15-J15 -> 389 | M15: =-L15/$J$19 -> -0.65159129 | N15: 3945 | O15: 3944.4444 | P15: =O15-N15 -> -0.55555556 | Q15: =-P15/$N$19 -> 0.00033593684 | R15: 38032 | S15: 38480 | T15: =S15-R15 -> 448 | U15: =-T15/$R$19 -> -0.020553287
A16: Внереализационные доходы | B16: 359 | C16: 385 | D16: =C16-B16 -> 26 | E16: =D16/$B$19 -> 0.0018494807 | F16: 619 | G16: 668.71228 | H16: =G16-F16 -> 49.712276 | I16: =H16/F19 -> 0.0074803109 | J16: 800 | K16: 803 | L16: =K16-J16 -> 3 | M16: =L16/$J$19 -> 0.0050251256 | N16: 10 | O16: 15 | P16: =O16-N16 -> 5 | Q16: =P16/$N$19 -> 0.0030234316 | R16: 2274 | S16: 2205 | T16: =S16-R16 -> -69 | U16: =T16/$R$19 -> -0.0031655732
A17: Внереализационные расходы | B17: 101 | C17: 100 | D17: =C17-B17 -> -1 | E17: =-D17/$B$19 -> 7.1133874e-05 | F17: 80 | G17: 100 | H17: =G17-F17 -> 20 | I17: =-H17/F19 -> -0.0030094421 | J17: 5 | K17: 10 | L17: =K17-J17 -> 5 | M17: =-L17/$J$19 -> -0.0083752094 | N17: 10 | O17: 12 | P17: =O17-N17 -> 2 | Q17: =-P17/$N$19 -> -0.0012093726 | R17: 186 | S17: 210 | T17: =S17-R17 -> 24 | U17: =-T17/$R$19 -> -0.001101069
A18: Налог на прибыль | B18: 4686 | C18: 4718.25 | D18: =C18-B18 -> 32.25 | E18: =-D18/$B$19 -> -0.0022940674 | F18: 2215.25 | G18: 2367.752 | H18: =G18-F18 -> 152.502 | I18: =-H18/F19 -> -0.022947298 | J18: 199 | K18: 209 | L18: =K18-J18 -> 10 | M18: =-L18/$J$19 -> -0.016750419 | N18: 551.25 | O18: 387.32667 | P18: =O18-N18 -> -163.92333 | Q18: =-P18/$N$19 -> 0.099122197 | R18: 7100 | S18: 7295 | T18: =S18-R18 -> 195 | U18: =-T18/$R$19 -> -0.0089461853
A19: Чистая прибыль | B19: 14058 | C19: 14154.75 | D19: =C19-B19 -> 96.75 | E19: =D19/$B$19 -> 0.0068822023 | F19: 6645.75 | G19: 7103.256 | H19: =G19-F19 -> 457.50601 | I19: =H19/F19 -> 0.068841893 | J19: 597 | K19: 627 | L19: =K19-J19 -> 30 | M19: =(K19-J19)/J19 -> 0.050251256 | N19: 1653.75 | O19: 1161.98 | P19: =O19-N19 -> -491.77 | Q19: =-P19/N19 -> 0.29736659 | R19: 21797 | S19: 22234 | T19: =S19-R19 -> 437 | U19: =(S19-R19)/R19 -> 0.020048631
E22: Факторный анализ отклонения чистой прибыли каждой компании на группу
A24: Компания | B24: 2025 план | C24: 2025 факт | D24: Δ (+-) тыс.руб. | E24: Δ, (+-)% | H24: Контролируемая доля
A25: А | B25: =B19 -> 14058 | C25: =C19 -> 14154.75 | D25: =C25-B25 -> 96.75 | E25: =D25/$B$29 -> 0.0044386842 | H25: А | I25: 1
A26: Б | B26: =F19 -> 6645.75 | C26: =G19 -> 7103.256 | D26: =C26-B26 -> 457.50601 | E26: =D26/$B$29 -> 0.020989403 | H26: Б | I26: 0.9
A27: В | B27: =J19 -> 597 | C27: =K19 -> 627 | D27: =C27-B27 -> 30 | E27: =D27/$B$29 -> 0.0013763362 | H27: В | I27: 0.6
A28: Г с учетом владения доли | B28: =N19 -> 1653.75 | C28: =O19 -> 1161.98 | D28: =(C28-B28)*0.3 -> -147.531 | E28: =D28/$B$29 -> -0.0067684085 | H28: Г | I28: 0.3
A29: Группа | B29: =R19 -> 21797 | C29: =S19 -> 22234 | D29: =C29-B29 -> 437 | E29: =D29/$B$29 -> 0.020048631
